Workbook

Sheet TRACK
A1: =1000000+SUM(M3:M73) -> 1052540.2 | B1: 46129
B2: Stock | C2: Buy | D2: Sell | E2: Shares0 | F2: Shares | G2: PriceAcq | H2: Amount | I2: % Fund0 | J2: % fund1 | K2: MtM | L2: %perform | M2: Net P&L | N2: Sector
B3: Trade 1 | C3: 45985 | D3: 45995 | F3: 643 | G3: 311 | H3: =+F3*G3 -> 199973 | I3: =+H3/$A$1 -> 0.18999085 | J3: =+K3*F3/$K$91 -> 0.17405161 | K3: 316 | L3: =+K3/G3-1 -> 0.01607717 | M3: =+(K3-G3)*F3 -> 3215
B4: Trade 2 | C4: 45993 | D4: 45995 | F4: 4800 | G4: 40.93 | H4: =+F4*G4 -> 196464 | I4: =+H4/$A$1 -> 0.18665701 | J4: =+K4*F4/$K$91 -> 0.174336 | K4: 42.4 | L4: =+K4/G4-1 -> 0.035914977 | M4: =+(K4-G4)*F4 -> 7056
B5: Trade 3 | C5: 46001 | D5: 46003 | F5: 27000 | G5: 2.02 | H5: =+F5*G5 -> 54540 | I5: =+H5/$A$1 -> 0.0518175 | J5: =+K5*F5/$K$91 -> 0.048569435 | K5: 2.1 | L5: =+K5/G5-1 -> 0.03960396 | M5: =+(K5-G5)*F5 -> 2160
B6: Trade 4 | C6: 46003 | D6: 46003 | F6: 4900 | G6: 11.15 | H6: =+F6*G6 -> 54635 | I6: =+H6/$A$1 -> 0.051907758 | J6: =+K6*F6/$K$91 -> 0.044282133 | K6: 10.55 | L6: =+K6/G6-1 -> -0.053811659 | M6: =+(K6-G6)*F6 -> -2940
B7: Trade 5 | C7: 46002 | D7: 46003 | F7: 470 | G7: 117 | H7: =+F7*G7 -> 54990 | I7: =+H7/$A$1 -> 0.052245038 | J7: =+K7*F7/$K$91 -> 0.04496279 | K7: 111.68 | L7: =+K7/G7-1 -> -0.045470085 | M7: =+(K7-G7)*F7 -> -2500.4
B8: Trade 6 | C8: 46000 | D8: 46003 | F8: 3600 | G8: 15.6 | H8: =+F8*G8 -> 56160 | I8: =+H8/$A$1 -> 0.053356634 | J8: =+K8*F8/$K$91 -> 0.044838069 | K8: 14.54 | L8: =+K8/G8-1 -> -0.067948718 | M8: =+(K8-G8)*F8 -> -3816
B9: Trade 7 | C9: 45981 | D9: 46006 | F9: 2500 | G9: 20.4 | H9: =+F9*G9 -> 51000 | I9: =+H9/$A$1 -> 0.048454208 | J9: =+K9*F9/$K$91 -> 0.037155189 | K9: 17.35 | L9: =+K9/G9-1 -> -0.1495098 | M9: =+(K9-G9)*F9 -> -7625
B10: Trade 8 | C10: 45979 | D10: 46006 | F10: 6400 | G10: 7.87 | H10: =+F10*G10 -> 50368 | I10: =+H10/$A$1 -> 0.047853756 | J10: =+K10*F10/$K$91 -> 0.062114054 | K10: 11.33 | L10: =+K10/G10-1 -> 0.43964422 | M10: =+(K10-G10)*F10 -> 22144
B11: Trade 9 | C11: 45982 | D11: 46007 | F11: 1077 | G11: 92.83 | H11: =+F11*G11 -> 99977.91 | I11: =+H11/$A$1 -> 0.094987264 | J11: =+K11*F11/$K$91 -> 0.082569324 | K11: 89.5 | L11: =+K11/G11-1 -> -0.035872024 | M11: =+(K11-G11)*F11 -> -3586.41
B12: Trade 10 | C12: 45981 | D12: 46007 | F12: 1700 | G12: 30.34 | H12: =+F12*G12 -> 51578 | I12: =+H12/$A$1 -> 0.049003356 | J12: =+K12*F12/$K$91 -> 0.041764574 | K12: 28.68 | L12: =+K12/G12-1 -> -0.05471325 | M12: =+(K12-G12)*F12 -> -2822
B13: Trade 11 | C13: 45980 | D13: 46007 | F13: 600 | G13: 83.4 | H13: =+F13*G13 -> 50040 | I13: =+H13/$A$1 -> 0.047542129 | J13: =+K13*F13/$K$91 -> 0.044596506 | K13: 86.77 | L13: =+K13/G13-1 -> 0.040407674 | M13: =+(K13-G13)*F13 -> 2022
B14: Trade 12 | C14: 45985 | D14: 46008 | F14: =50000/2 -> 25000 | G14: 2 | H14: =+F14*G14 -> 50000 | I14: =+H14/$A$1 -> 0.047504126 | J14: =+K14*F14/$K$91 -> 0.041759435 | K14: 1.95 | L14: =+K14/G14-1 -> -0.025 | M14: =+(K14-G14)*F14 -> -1250
B15: Trade 13 | C15: 45979 | D15: 46008 | F15: 2500 | G15: 19.71 | H15: =+F15*G15 -> 49275 | I15: =+H15/A1 -> 0.046815316 | J15: =+K15*F15/$K$91 -> 0.036662642 | K15: 17.12 | L15: =+K15/G15-1 -> -0.13140538 | M15: =+(K15-G15)*F15 -> -6475
B16: Trade 14 | C16: 46006 | D16: 46024 | F16: =55000/5 -> 11000 | G16: 5 | H16: =+F16*G16 -> 55000 | I16: =+H16/$A$1 -> 0.052254538 | J16: =+K16*F16/$K$91 -> 0.046453623 | K16: 4.93 | L16: =+K16/G16-1 -> -0.014 | M16: =+(K16-G16)*F16 -> -770
B17: Trade 15 | C17: 46009 | D17: 46029 | F17: 2000 | G17: 25.42 | H17: =+F17*G17 -> 50840 | I17: =+H17/$A$1 -> 0.048302195 | J17: =+K17*F17/$K$91 -> 0.037810491 | K17: 22.07 | L17: =+K17/G17-1 -> -0.131786 | M17: =+(K17-G17)*F17 -> -6700
B18: Trade 16 | C18: 45981 | D18: 46031 | F18: 12000 | G18: 4.21 | H18: =+F18*G18 -> 50520 | I18: =+H18/$A$1 -> 0.047998169 | J18: =+K18*F18/$K$91 -> 0.052835321 | K18: 5.14 | L18: =+K18/G18-1 -> 0.22090261 | M18: =+(K18-G18)*F18 -> 11160
B19: Trade 17 | C19: 45980 | D19: 46031 | F19: 12000 | G19: 4.21 | H19: =+F19*G19 -> 50520 | I19: =+H19/$A$1 -> 0.047998169 | J19: =+K19*F19/$K$91 -> 0.051601812 | K19: 5.02 | L19: =+K19/G19-1 -> 0.19239905 | M19: =+(K19-G19)*F19 -> 9720
B20: Trade 18 | C20: 46008 | D20: 46035 | F20: 14000 | G20: 3.91 | H20: =+F20*G20 -> 54740 | I20: =+H20/$A$1 -> 0.052007517 | J20: =+K20*F20/$K$91 -> 0.047610038 | K20: 3.97 | L20: =+K20/G20-1 -> 0.015345269 | M20: =+(K20-G20)*F20 -> 840
B21: Trade 19 | C21: 46036 | D21: 46042 | F21: 2616 | G21: 19.11 | H21: =+F21*G21 -> 49991.76 | I21: =+H21/$A$1 -> 0.047496297 | J21: =+K21*F21/$K$91 -> 0.039484226 | K21: 17.62 | L21: =+K21/G21-1 -> -0.077969649 | M21: =+(K21-G21)*F21 -> -3897.84
B22: Trade 20 | C22: 46002 | D22: 46043 | F22: 1700 | G22: 16 | H22: =+F22*G22 -> 27200 | I22: =+H22/$A$1 -> 0.025842244 | J22: =+K22*F22/$K$91 -> 0.039609359 | K22: 27.2 | L22: =+K22/G22-1 -> 0.7 | M22: =+(K22-G22)*F22 -> 19040
B23: Trade 21 | C23: 46034 | D23: 46049 | F23: =60000+26851 -> 86851 | G23: 1.88 | H23: =+F23*G23 -> 163279.88 | I23: =+H23/$A$1 -> 0.15512936 | J23: =+K23*F23/$K$91 -> 0.12349885 | K23: 1.66 | L23: =+K23/G23-1 -> -0.11702128 | M23: =+(K23-G23)*F23 -> -19107.22
B24: Trade 22 | C24: 46036 | D24: 46050 | F24: 5568 | G24: 8.98 | H24: =+F24*G24 -> 50000.64 | I24: =+H24/$A$1 -> 0.047504734 | J24: =+K24*F24/$K$91 -> 0.039682821 | K24: 8.32 | L24: =+K24/G24-1 -> -0.073496659 | M24: =+(K24-G24)*F24 -> -3674.88
B25: Trade 23 | C25: 46045 | D25: 46050 | F25: =ROUND(50000/G25,0) -> 24631 | G25: 2.03 | H25: =+F25*G25 -> 50000.93 | I25: =+H25/$A$1 -> 0.047505009 | J25: =+K25*F25/$K$91 -> 0.040510095 | K25: 1.92 | L25: =+K25/G25-1 -> -0.054187192 | M25: =+(K25-G25)*F25 -> -2709.41
B26: Trade 24 | C26: 46042 | D26: 46052 | F26: =ROUND(50000/G26,0) -> 18116 | G26: 2.76 | H26: =+F26*G26 -> 50000.16 | I26: =+H26/$A$1 -> 0.047504278 | J26: =+K26*F26/$K$91 -> 0.038485221 | K26: 2.48 | L26: =+K26/G26-1 -> -0.10144928 | M26: =+(K26-G26)*F26 -> -5072.48
B27: Trade 25 | C27: 46031 | D27: 46052 | F27: 2778 | G27: 18 | H27: =+F27*G27 -> 50004 | I27: =+H27/$A$1 -> 0.047507926 | J27: =+K27*F27/$K$91 -> 0.049234862 | K27: 20.69 | L27: =+K27/G27-1 -> 0.14944444 | M27: =+(K27-G27)*F27 -> 7472.82
B28: Trade 26 | C28: 45981 | D28: 46057 | F28: 670 | G28: 74.69 | H28: =+F28*G28 -> 50042.3 | I28: =+H28/$A$1 -> 0.047544314 | J28: =+K28*F28/$K$91 -> 0.044306974 | K28: 77.2 | L28: =+K28/G28-1 -> 0.03360557 | M28: =+(K28-G28)*F28 -> 1681.7
B29: Trade 27 | C29: 45981 | D29: 46057 | F29: 6500 | G29: 7.65 | H29: =+F29*G29 -> 49725 | I29: =+H29/$A$1 -> 0.047242853 | J29: =+K29*F29/$K$91 -> 0.059561374 | K29: =(4300*10.88+2200*10.34)/F29 -> 10.697231 | L29: =+K29/G29-1 -> 0.39833082 | M29: =+(K29-G29)*F29 -> 19807
B30: Trade 28 | C30: 46002 | D30: 46057 | F30: 1700 | G30: 16 | H30: =+F30*G30 -> 27200 | I30: =+H30/$A$1 -> 0.025842244 | J30: =+K30*F30/$K$91 -> 0.033329597 | K30: =+(1000*23.04+700*22.67)/F30 -> 22.887647 | L30: =+K30/G30-1 -> 0.43047794 | M30: =+(K30-G30)*F30 -> 11709
B31: Trade 29 | C31: 46050 | D31: 46057 | F31: 10163 | G31: 4.92 | H31: =+F31*G31 -> 50001.96 | I31: =+H31/$A$1 -> 0.047505988 | J31: =+K31*F31/$K$91 -> 0.039610772 | K31: 4.55 | L31: =+K31/G31-1 -> -0.075203252 | M31: =+(K31-G31)*F31 -> -3760.31
B32: Trade 30 | C32: 46031 | D32: 46057 | F32: =1800+907 -> 2707 | G32: 18.47 | H32: =+F32*G32 -> 49998.29 | I32: =+H32/$A$1 -> 0.047502501 | J32: =+K32*F32/$K$91 -> 0.04370019 | K32: =+(1800*19.01+907*18.52)/F32 -> 18.845822 | L32: =+K32/G32-1 -> 0.020347696 | M32: =+(K32-G32)*F32 -> 1017.35
B33: Trade 31 | C33: 46002 | D33: 46057 | F33: 2300 | G33: 24 | H33: =+F33*G33 -> 55200 | I33: =+H33/$A$1 -> 0.052444555 | J33: =+K33*F33/$K$91 -> 0.049894601 | K33: =+(1500*25.53+800*24.94)/F33 -> 25.324783 | L33: =+K33/G33-1 -> 0.055199275 | M33: =+(K33-G33)*F33 -> 3047
B34: Trade 32 | C34: 46001 | D34: 46057 | F34: 1600 | G34: 34.4 | H34: =+F34*G34 -> 55040 | I34: =+H34/$A$1 -> 0.052292542 | J34: =+K34*F34/$K$91 -> 0.046731163 | K34: =+(1000*34.46+600*33.49)/F34 -> 34.09625 | L34: =+K34/G34-1 -> -0.0088299419 | M34: =+(K34-G34)*F34 -> -486
B35: Trade 33 | C35: 46043 | D35: 46057 | F35: 2200 | G35: 11.4 | H35: =+F35*G35 -> 25080 | I35: =+H35/$A$1 -> 0.02382807 | J35: =+K35*F35/$K$91 -> 0.020880574 | K35: 11.08 | L35: =+K35/G35-1 -> -0.028070175 | M35: =+(K35-G35)*F35 -> -704
B36: Trade 34 | C36: 45979 | D36: 46057 | F36: 11500 | G36: 4.32 | H36: =+F36*G36 -> 49680 | I36: =+H36/$A$1 -> 0.047200099 | J36: =+K36*F36/$K$91 -> 0.054771246 | K36: 5.56 | L36: =+K36/G36-1 -> 0.28703704 | M36: =+(K36-G36)*F36 -> 14260
B37: Trade 35 | C37: 46036 | D37: 46057 | F37: 4558 | G37: 10.97 | H37: =+F37*G37 -> 50001.26 | I37: =+H37/$A$1 -> 0.047505323 | J37: =+K37*F37/$K$91 -> 0.048063165 | K37: 12.31 | L37: =+K37/G37-1 -> 0.12215132 | M37: =+(K37-G37)*F37 -> 6107.72
B38: Trade 36 | C38: 46030 | D38: 46057 | F38: 4634 | G38: 10.79 | H38: =+F38*G38 -> 50000.86 | I38: =+H38/$A$1 -> 0.047504943 | J38: =+K38*F38/$K$91 -> 0.048269144 | K38: 12.16 | L38: =+K38/G38-1 -> 0.12696942 | M38: =+(K38-G38)*F38 -> 6348.58
B39: Trade 37 | C39: 46042 | D39: 46057 | F39: 5952 | G39: 8.4 | H39: =+F39*G39 -> 49996.8 | I39: =+H39/$A$1 -> 0.047501086 | J39: =+K39*F39/$K$91 -> 0.041705777 | K39: 8.18 | L39: =+K39/G39-1 -> -0.026190476 | M39: =+(K39-G39)*F39 -> -1309.44
B40: Trade 38 | C40: 46043 | D40: 46058 | F40: =4386-2200 -> 2186 | G40: 11.4 | H40: =+F40*G40 -> 24920.4 | I40: =+H40/$A$1 -> 0.023676436 | J40: =+K40*F40/$K$91 -> 0.019942507 | K40: 10.65 | L40: =+K40/G40-1 -> -0.065789474 | M40: =+(K40-G40)*F40 -> -1639.5
B41: Trade 39 | C41: 46058 | D41: 46058 | F41: =ROUND(H41/G41,0) -> 18868 | G41: 2.65 | H41: 50000 | I41: =+H41/$A$1 -> 0.047504126 | J41: =+K41*F41/$K$91 -> 0.041375745 | K41: 2.56 | L41: =+K41/G41-1 -> -0.033962264 | M41: =+(K41-G41)*F41 -> -1698.12
B42: Trade 40 | C42: 46059 | D42: 46064 | F42: =ROUND(H42/G42,0) -> 1842 | G42: 27.15 | H42: 50000 | I42: =+H42/$A$1 -> 0.047504126 | J42: =+K42*F42/$K$91 -> 0.041276927 | K42: 26.16 | L42: =+K42/G42-1 -> -0.036464088 | M42: =+(K42-G42)*F42 -> -1823.58
B43: Trade 41 | C43: 46063 | D43: 46064 | F43: =ROUND(H43/G43,0) -> 10799 | G43: 4.63 | H43: 50000 | I43: =+H43/$A$1 -> 0.047504126 | J43: =+K43*F43/$K$91 -> 0.041072061 | K43: 4.44 | L43: =+K43/G43-1 -> -0.041036717 | M43: =+(K43-G43)*F43 -> -2051.81
B44: Trade 42 | C44: 46059 | D44: 46070 | F44: =ROUND(H44/G44,0) -> 18248 | G44: 2.74 | H44: 50000 | I44: =+H44/$A$1 -> 0.047504126 | J44: =+K44*F44/$K$91 -> 0.039390891 | K44: 2.52 | L44: =+K44/G44-1 -> -0.080291971 | M44: =+(K44-G44)*F44 -> -4014.56
B45: Trade 43 | C45: 46064 | D45: 46070 | F45: =ROUND(H45/G45,0) -> 767 | G45: 65.19 | H45: 50000 | I45: =+H45/$A$1 -> 0.047504126 | J45: =+K45*F45/$K$91 -> 0.039026697 | K45: 59.4 | L45: =+K45/G45-1 -> -0.088817303 | M45: =+(K45-G45)*F45 -> -4440.93
B46: Trade 44 | C46: 46071 | D46: 46078 | F46: =ROUND(H46/G46,0) -> 2764 | G46: 18.09 | H46: 50000 | I46: =+H46/$A$1 -> 0.047504126 | J46: =+K46*F46/$K$91 -> 0.039468773 | K46: 16.67 | L46: =+K46/G46-1 -> -0.078496407 | M46: =+(K46-G46)*F46 -> -3924.88
B47: Trade 45 | C47: 46056 | D47: 46080 | F47: =ROUND(H47/G47,0) -> 8993 | G47: 5.56 | H47: 50000 | I47: =+H47/$A$1 -> 0.047504126 | J47: =+K47*F47/$K$91 -> 0.042445942 | K47: 5.51 | L47: =+K47/G47-1 -> -0.0089928058 | M47: =+(K47-G47)*F47 -> -449.65
B48: Trade 46 | C48: 46072 | D48: 46084 | F48: 7356 | G48: 13.48 | H48: 100000 | I48: =+H48/$A$1 -> 0.095008252 | J48: =+K48*F48/$K$91 -> 0.080403024 | K48: 12.76 | L48: =+K48/G48-1 -> -0.053412463 | M48: =+(K48-G48)*F48 -> -5296.32
B49: Trade 47 | C49: 46071 | D49: 46084 | F49: =ROUND(H49/G49,0) -> 799 | G49: 62.61 | H49: 50000 | I49: =+H49/$A$1 -> 0.047504126 | J49: =+K49*F49/$K$91 -> 0.043221529 | K49: 63.15 | L49: =+K49/G49-1 -> 0.0086248203 | M49: =+(K49-G49)*F49 -> 431.46
B50: Trade 48 | C50: 46071 | D50: 46084 | F50: =ROUND(H50/G50,0) -> 298 | G50: 168 | H50: 50000 | I50: =+H50/$A$1 -> 0.047504126 | J50: =+K50*F50/$K$91 -> 0.039839666 | K50: 156.07 | L50: =+K50/G50-1 -> -0.071011905 | M50: =+(K50-G50)*F50 -> -3555.14
B51: Trade 49 | C51: 46073 | D51: 46084 | F51: =ROUND(H51/G51,0) -> 816 | G51: 61.27 | H51: 50000 | I51: =+H51/$A$1 -> 0.047504126 | J51: =+K51*F51/$K$91 -> 0.042225907 | K51: 60.41 | L51: =+K51/G51-1 -> -0.014036233 | M51: =+(K51-G51)*F51 -> -701.76
B52: Trade 50 | C52: 46065 | D52: 46084 | F52: =ROUND(H52/G52,0) -> 2290 | G52: 21.83 | H52: 50000 | I52: =+H52/$A$1 -> 0.047504126 | J52: =+K52*F52/$K$91 -> 0.05469004 | K52: 27.88 | L52: =+K52/G52-1 -> 0.27714155 | M52: =+(K52-G52)*F52 -> 13854.5
B53: Trade 51 | C53: 46072 | D53: 46084 | F53: =ROUND(H53/G53,0) -> 1934 | G53: 25.85 | H53: 50000 | I53: =+H53/$A$1 -> 0.047504126 | J53: =+K53*F53/$K$91 -> 0.041963495 | K53: 25.33 | L53: =+K53/G53-1 -> -0.020116054 | M53: =+(K53-G53)*F53 -> -1005.68
B54: Trade 52 | C54: 46084 | D54: 46100 | F54: =ROUND(H54/G54,0) -> 2740 | G54: 18.25 | H54: 50000 | I54: =+H54/$A$1 -> 0.047504126 | J54: =+K54*F54/$K$91 -> 0.039454656 | K54: 16.81 | L54: =+K54/G54-1 -> -0.07890411 | M54: =+(K54-G54)*F54 -> -3945.6
B55: Trade 53 | C55: 46097 | D55: 46100 | F55: =ROUND(H55/G55,0) -> 3720 | G55: 13.44 | H55: 50000 | I55: =+H55/$A$1 -> 0.047504126 | J55: =+K55*F55/$K$91 -> 0.04097924 | K55: 12.86 | L55: =+K55/G55-1 -> -0.043154762 | M55: =+(K55-G55)*F55 -> -2157.6
B56: Trade 54 | C56: 46093 | D56: 46100 | F56: =ROUND(H56/G56,0) -> 3994 | G56: 12.52 | H56: 50000 | I56: =+H56/$A$1 -> 0.047504126 | J56: =+K56*F56/$K$91 -> 0.038934115 | K56: 11.38 | L56: =+K56/G56-1 -> -0.091054313 | M56: =+(K56-G56)*F56 -> -4553.16
B57: Trade 55 | C57: 46100 | D57: 46105 | F57: =ROUND(H57/G57,0) -> 1311 | G57: 38.15 | H57: 50000 | I57: =+H57/$A$1 -> 0.047504126 | J57: =+K57*F57/$K$91 -> 0.041315448 | K57: 36.79 | L57: =+K57/G57-1 -> -0.035648755 | M57: =+(K57-G57)*F57 -> -1782.96
A58: SHORT | B58: Trade 56 | C58: 46090 | D58: 46114 | F58: 980 | G58: 102 | H58: =+F58*G58 -> 99960 | I58: =+H58/$A$1 -> 0.094970248 | J58: =+K58*F58/$K$91 -> 0.090662945 | K58: 108 | L58: =+G58/K58-1 -> -0.055555556 | M58: =+(G58-K58)*F58 -> -5880
B59: Trade 57 | C59: 46112 | D59: 46114 | F59: 9311 | G59: 5.37 | H59: =+F59*G59 -> 50000.07 | I59: =+H59/$A$1 -> 0.047504192 | J59: =+K59*F59/$K$91 -> 0.041952907 | K59: 5.26 | L59: =+K59/G59-1 -> -0.020484171 | M59: =+(K59-G59)*F59 -> -1024.21
B60: Trade 58 | C60: 46118 | D60: 46119 | F60: 8000 | G60: 6.25 | H60: =+F60*G60 -> 50000 | I60: =+H60/$A$1 -> 0.047504126 | J60: =+K60*F60/$K$91 -> 0.039266718 | K60: 5.73 | L60: =+K60/G60-1 -> -0.0832 | M60: =+(K60-G60)*F60 -> -4160
B61: Trade 59 | C61: 46079 | D61: 46121 | F61: 1367 | G61: 36.58 | H61: =+F61*G61 -> 50004.86 | I61: =+H61/$A$1 -> 0.047508743 | J61: =+K61*F61/$K$91 -> 0.04243622 | K61: 36.24 | L61: =+K61/G61-1 -> -0.0092946966 | M61: =+(K61-G61)*F61 -> -464.78
B62: Trade 60 | C62: 46112 | D62: 46125 | F62: 175 | G62: 94.96 | H62: =+F62*G62 -> 16618 | I62: =+H62/$A$1 -> 0.015788471 | J62: =+K62*F62/$K$91 -> 0.019457755 | K62: 129.8 | L62: =+K62/G62-1 -> 0.36689132 | M62: =+(K62-G62)*F62 -> 6097
B63: Trade 61 | C63: 46070 | D63: 46125 | F63: 2020 | G63: 12.38 | H63: =+F63*G63 -> 25007.6 | I63: =+H63/$A$1 -> 0.023759284 | J63: =+K63*F63/$K$91 -> 0.024138238 | K63: 13.95 | L63: =+K63/G63-1 -> 0.12681745 | M63: =+(K63-G63)*F63 -> 3171.4
B64: Trade 62 | C64: 46121 | D64: 46126 | F64: 1190 | G64: 6.31 | H64: =+F64*G64 -> 7508.9 | I64: =+H64/$A$1 -> 0.0071340746 | J64: =+K64*F64/$K$91 -> 0.0074413171 | K64: 7.3 | L64: =+K64/G64-1 -> 0.15689382 | M64: =+(K64-G64)*F64 -> 1178.1
B65: Trade 63 | C65: 46112 | D65: 46126 | F65: 48 | G65: 155.61 | H65: =+F65*G65 -> 7469.28 | I65: =+H65/$A$1 -> 0.0070964323 | J65: =+K65*F65/$K$91 -> 0.007900628 | K65: 192.15 | L65: =+K65/G65-1 -> 0.23481781 | M65: =+(K65-G65)*F65 -> 1753.92
B66: Trade 64 | C66: 46113 | D66: 46126 | F66: 388 | G66: 19.32 | H66: =+F66*G66 -> 7496.16 | I66: =+H66/$A$1 -> 0.0071219706 | J66: =+K66*F66/$K$91 -> 0.0077108046 | K66: 23.2 | L66: =+K66/G66-1 -> 0.20082816 | M66: =+(K66-G66)*F66 -> 1505.44
B67: Trade 65 | C67: 46086 | D67: 46127 | F67: =14286*0.15 -> 2142.9 | G67: 3.5 | H67: =+F67*G67 -> 7500.15 | I67: =+H67/$A$1 -> 0.0071257614 | J67: =+K67*F67/$K$91 -> 0.0087742457 | K67: 4.78 | L67: =+K67/G67-1 -> 0.36571429 | M67: =+(K67-G67)*F67 -> 2742.912
B68: Trade 66 | C68: 46118 | D68: 46127 | F68: =3243*0.15 -> 486.45 | G68: 15.42 | H68: =+F68*G68 -> 7501.059 | I68: =+H68/$A$1 -> 0.007126625 | J68: =+K68*F68/$K$91 -> 0.008188055 | K68: 19.65 | L68: =+K68/G68-1 -> 0.27431907 | M68: =+(K68-G68)*F68 -> 2057.6835
B69: Trade 67 | C69: 46112 | D69: 46128 | F69: 63 | G69: 94.96 | H69: =+F69*G69 -> 5982.48 | I69: =+H69/$A$1 -> 0.0056838497 | J69: =+K69*F69/$K$91 -> 0.0070301558 | K69: 130.27 | L69: =+K69/G69-1 -> 0.37184078 | M69: =+(K69-G69)*F69 -> 2224.53
B70: Trade 68 | C70: 46118 | D70: 46128 | F70: =5405*0.333333333333333 -> 1801.6667 | G70: 9.25 | H70: =+F70*G70 -> 16665.417 | I70: =+H70/$A$1 -> 0.015833521 | J70: =+K70*F70/$K$91 -> 0.014414557 | K70: 9.34 | L70: =+K70/G70-1 -> 0.0097297297 | M70: =+(K70-G70)*F70 -> 162.15
B71: Trade 69 | C71: 46112 | D71: 46129 | F71: 32 | G71: 155.61 | H71: =+F71*G71 -> 4979.52 | I71: =+H71/$A$1 -> 0.0047309549 | J71: =+K71*F71/$K$91 -> 0.0056300112 | K71: 205.39 | L71: =+K71/G71-1 -> 0.31990232 | M71: =+(K71-G71)*F71 -> 1592.96
B72: Trade 70 | C72: 46121 | D72: 46129 | F72: 792 | G72: 6.31 | H72: =+F72*G72 -> 4997.52 | I72: =+H72/$A$1 -> 0.0047480564 | J72: =+K72*F72/$K$91 -> 0.0049118346 | K72: 7.24 | L72: =+K72/G72-1 -> 0.1473851 | M72: =+(K72-G72)*F72 -> 736.56
A75: 1 | B75: CGEM | C75: 46070 | F75: =4039-2020 -> 2019 | G75: 12.38 | H75: 25000 | I75: 0.05 | J75: =+K75*F75/$K$91 -> 0.026046015 | K75: =INDEX(Precios!AU:AU,MATCH($B$1,Precios!$A:$A,0)) -> 15.06 | L75: =+K75/G75-1 -> 0.21647819 | M75: =+(K75-G75)*F75 -> 5410.92 | N75: Biotech
A76: =+A75+1 -> 2 | B76: ALTO | C76: 46086 | F76: =14286-2143 -> 12143 | G76: 3.5 | H76: =+F76*G76 -> 42500.5 | I76: 0.05 | J76: =+K76*F76/$K$91 -> 0.051384594 | K76: =INDEX(Precios!BD:BD,MATCH($B$1,Precios!$A:$A,0)) -> 4.94 | L76: =+K76/G76-1 -> 0.41142857 | M76: =+(K76-G76)*F76 -> 17485.92 | N76: Biofuels
A77: =+A76+1 -> 3 | B77: CAPR | C77: 46090 | F77: =ROUND(H77/G77,0) -> 1633 | G77: 30.62 | H77: 50000 | I77: 0.05 | J77: =+K77*F77/$K$91 -> 0.048539539 | K77: =INDEX(Precios!BF:BF,MATCH($B$1,Precios!$A:$A,0)) -> 34.7 | L77: =+K77/G77-1 -> 0.13324624 | M77: =+(K77-G77)*F77 -> 6662.64 | N77: Biotech
A78: =+A77+1 -> 4 | B78: LABU | C78: 46112 | F78: =321-48-32 -> 241 | G78: 155.61 | H78: =+F78*G78 -> 37502.01 | I78: 0.05 | J78: =+K78*F78/$K$91 -> 0.043522 | K78: =INDEX(Precios!BK:BK,MATCH($B$1,Precios!$A:$A,0)) -> 210.82 | L78: =+K78/G78-1 -> 0.35479725 | M78: =+(K78-G78)*F78 -> 13305.61 | N78: Biotech
A79: =+A78+1 -> 5 | B79: MRVL | C79: 46112 | F79: =527-175-63 -> 289 | G79: 94.96 | H79: =+F79*G79 -> 27443.44 | I79: =50000/$A$1 -> 0.047504126 | J79: =+K79*F79/$K$91 -> 0.034581446 | K79: =INDEX(Precios!BJ:BJ,MATCH($B$1,Precios!$A:$A,0)) -> 139.69 | L79: =+K79/G79-1 -> 0.47104044 | M79: =+(K79-G79)*F79 -> 12926.97 | N79: Semiconductors
A80: =+A79+1 -> 6 | B80: LUNR | C80: 46113 | F80: =2588-388 -> 2200 | G80: 19.32 | H80: =+F80*G80 -> 42504 | I80: =50000/$A$1 -> 0.047504126 | J80: =+K80*F80/$K$91 -> 0.051975291 | K80: =INDEX(Precios!BN:BN,MATCH($B$1,Precios!$A:$A,0)) -> 27.58 | L80: =+K80/G80-1 -> 0.42753623 | M80: =+(K80-G80)*F80 -> 18172 | N80: Aerospace
A81: =+A80+1 -> 7 | B81: NTLA | C81: 46113 | F81: =ROUND(H81/G81,0) -> 3693 | G81: 13.54 | H81: 50000 | I81: =50000/$A$1 -> 0.047504126 | J81: =+K81*F81/$K$91 -> 0.047293395 | K81: =INDEX(Precios!BM:BM,MATCH($B$1,Precios!$A:$A,0)) -> 14.95 | L81: =+K81/G81-1 -> 0.10413589 | M81: =+(K81-G81)*F81 -> 5207.13 | N81: Biotech
A82: =+A81+1 -> 8 | B82: WULF | C82: 46118 | F82: =3243-486 -> 2757 | G82: 15.42 | H82: =+F82*G82 -> 42512.94 | I82: =50000/$A$1 -> 0.047504126 | J82: =+K82*F82/$K$91 -> 0.048744593 | K82: =INDEX(Precios!BP:BP,MATCH($B$1,Precios!$A:$A,0)) -> 20.64 | L82: =+K82/G82-1 -> 0.3385214 | M82: =+(K82-G82)*F82 -> 14391.54 | N82: Crypto/Data Centers
A83: =+A82+1 -> 9 | B83: BCRX | C83: 46118 | F83: =5405-1802 -> 3603 | G83: 9.25 | H83: 50000 | I83: =50000/$A$1 -> 0.047504126 | J83: =+K83*F83/$K$91 -> 0.029320263 | K83: =INDEX(Precios!BQ:BQ,MATCH($B$1,Precios!$A:$A,0)) -> 9.5 | L83: =+K83/G83-1 -> 0.027027027 | M83: =+(K83-G83)*F83 -> 900.75 | N83: Biotech
A84: =+A83+1 -> 10 | B84: POET | C84: 46121 | F84: =7924-1190-792 -> 5942 | G84: 6.31 | H84: =+F84*G84 -> 37494.02 | I84: =50000/$A$1 -> 0.047504126 | J84: =+K84*F84/$K$91 -> 0.036952962 | K84: =INDEX(Precios!BR:BR,MATCH($B$1,Precios!$A:$A,0)) -> 7.26 | L84: =+K84/G84-1 -> 0.15055468 | M84: =+(K84-G84)*F84 -> 5644.9 | N84: Semiconductors
A85: =+A84+1 -> 11 | B85: ARM | C85: 46122 | F85: =ROUND(H85/G85,0) -> 328 | G85: 152.23 | H85: 50000 | I85: =+H85/$A$1 -> 0.047504126 | J85: =+K85*F85/$K$91 -> 0.046845468 | K85: =INDEX(Precios!BS:BS,MATCH($B$1,Precios!$A:$A,0)) -> 166.73 | L85: =+K85/G85-1 -> 0.095250608 | M85: =+(K85-G85)*F85 -> 4756 | N85: Semiconductors
A86: =+A85+1 -> 12 | B86: CAVA | C86: 46125 | F86: =ROUND(H86/G86,0) -> 586 | G86: 85.31 | H86: 50000 | I86: =+H86/$A$1 -> 0.047504126 | J86: =+K86*F86/$K$91 -> 0.047576699 | K86: =INDEX(Precios!BT:BT,MATCH($B$1,Precios!$A:$A,0)) -> 94.78 | L86: =+K86/G86-1 -> 0.11100692 | M86: =+(K86-G86)*F86 -> 5549.42 | N86: Consumer
A87: =+A86+1 -> 13 | B87: YOU | C87: 46127 | F87: =ROUND(H87/G87,0) -> 1027 | G87: 48.7 | H87: 50000 | I87: =+H87/$A$1 -> 0.047504126 | J87: =+K87*F87/$K$91 -> 0.046652193 | K87: =INDEX(Precios!BU:BU,MATCH($B$1,Precios!$A:$A,0)) -> 53.03 | L87: =+K87/G87-1 -> 0.088911704 | M87: =+(K87-G87)*F87 -> 4446.91 | N87: Software
B89: Cash | J89: =+K89/K91 -> 0.44056554 | K89: =+A1-H90 -> 514316.6 | N89: Cash
B90: Invested | H90: =+SUMPRODUCT(F75:F88,G75:G88) -> 538223.56 | J90: =+K90/K91 -> 0.55943446 | K90: =+SUMPRODUCT(F75:F88,K75:K88) -> 653084.27 | L90: =+K90/H90-1 -> 0.21340706 | M90: =+SUM(M75:M89) -> 114860.71
B91: Portfolio | J91: =+J89+J90 -> 1 | K91: =+K90+K89 -> 1167400.9 | L91: =+K91/1000000-1 -> 0.16740087 | M91: =+SUM(M3:M88) -> 167400.87
A93: VOO | B93: S&P500 | C93: 45979 | D93: 46129 | G93: 607 | K93: 652.78 | L93: =+K93/G93-1 -> 0.075420099

Sheet Portfolio
A2: Date | B2: Invested | C2: Cash | D2: Portoflio | E2: Performance | G2: S&P500
A3: =+Precios!A5 -> 45979 | B3: =+SUM(Value!F7:XFD7) -> 0 | C3: =+Value!D7 -> 1000000 | D3: =+B3+C3 -> 1000000 | G3: 607
A4: =+Precios!A6 -> 45980 | B4: =+SUM(Value!F8:XFD8) -> 0 | C4: =+Value!D8 -> 1000000 | D4: =+B4+C4 -> 1000000 | E4: =+D4/$D$3-1 -> 0 | G4: 609.2
A5: =+Precios!A7 -> 45981 | B5: =+SUM(Value!F9:XFD9) -> 0 | C5: =+Value!D9 -> 1000000 | D5: =+B5+C5 -> 1000000 | E5: =+D5/$D$3-1 -> 0 | G5: 599.96
A6: =+Precios!A8 -> 45982 | B6: =+SUM(Value!F10:XFD10) -> 0 | C6: =+Value!D10 -> 1000000 | D6: =+B6+C6 -> 1000000 | E6: =+D6/$D$3-1 -> 0 | G6: 605.93
A7: =+Precios!A9 -> 45985 | B7: =+SUM(Value!F11:XFD11) -> 0 | C7: =+Value!D11 -> 1000000 | D7: =+B7+C7 -> 1000000 | E7: =+D7/$D$3-1 -> 0 | G7: 614.94
A8: =+Precios!A10 -> 45986 | B8: =+SUM(Value!F12:XFD12) -> 0 | C8: =+Value!D12 -> 1000000 | D8: =+B8+C8 -> 1000000 | E8: =+D8/$D$3-1 -> 0 | G8: 620.66
A9: =+Precios!A11 -> 45987 | B9: =+SUM(Value!F13:XFD13) -> 0 | C9: =+Value!D13 -> 1000000 | D9: =+B9+C9 -> 1000000 | E9: =+D9/$D$3-1 -> 0 | G9: 624.95
A10: =+Precios!A12 -> 45988 | B10: =+SUM(Value!F14:XFD14) -> 0 | C10: =+Value!D14 -> 1000000 | D10: =+B10+C10 -> 1000000 | E10: =+D10/$D$3-1 -> 0 | G10: 628.41
A11: =+Precios!A13 -> 45989 | B11: =+SUM(Value!F15:XFD15) -> 0 | C11: =+Value!D15 -> 1000000 | D11: =+B11+C11 -> 1000000 | E11: =+D11/$D$3-1 -> 0 | G11: 628.41
A12: =+Precios!A14 -> 45992 | B12: =+SUM(Value!F16:XFD16) -> 0 | C12: =+Value!D16 -> 1000000 | D12: =+B12+C12 -> 1000000 | E12: =+D12/$D$3-1 -> 0 | G12: 625.52
A13: =+Precios!A15 -> 45993 | B13: =+SUM(Value!F17:XFD17) -> 0 | C13: =+Value!D17 -> 1000000 | D13: =+B13+C13 -> 1000000 | E13: =+D13/$D$3-1 -> 0 | G13: 626.58
A14: =+Precios!A16 -> 45994 | B14: =+SUM(Value!F18:XFD18) -> 0 | C14: =+Value!D18 -> 1000000 | D14: =+B14+C14 -> 1000000 | E14: =+D14/$D$3-1 -> 0 | G14: 628.77
A15: =+Precios!A17 -> 45995 | B15: =+SUM(Value!F19:XFD19) -> 0 | C15: =+Value!D19 -> 1010271 | D15: =+B15+C15 -> 1010271 | E15: =+D15/$D$3-1 -> 0.010271 | G15: 629.3
... A111: =+Precios!A113 -> 46129 | B111: =+SUM(Value!F115:XFD115) -> 653084.27 | C111: =+Value!D115 -> 514717.76 | D111: =+B111+C111 -> 1167802 | E111: =+D111/$D$3-1 -> 0.16780203 | G111: 652.78

Sheet Precios
A1: BUY | B1: 45985 | C1: 45993 | D1: 46001 | E1: 46003 | F1: 46002 | G1: 46000 | H1: 45981 | I1: 45979 | J1: 45982 | K1: 45981 | L1: 45980 | M1: 45985 | N1: 45979 | O1: 46006 | P1: 46009 | Q1: 45981 | R1: 45980 | S1: 46008 | T1: 46036 | U1: 46002 | V1: 46034 | W1: 46036 | X1: 46045 | Y1: 46042 | Z1: 46031 | AA1: 45979 | AB1: 45981 | AC1: 45981 | AD1: 46001 | AE1: 46002 | AF1: 46002 | AG1: 46030 | AH1: 46036 | AI1: 46031 | AJ1: 46042 | AK1: 46043 | AL1: 46043 | AM1: 46050 | AN1: 46056 | AO1: 46058 | AP1: 46059 | AQ1: 46059 | AR1: 46063 | AS1: 46064 | AT1: 46065 | AU1: 46070 | AV1: 46071 | AW1: 46071 | AX1: 46071 | AY1: 46072 | AZ1: 46072 | BA1: 46073 | BB1: 46079 | BC1: 46084 | BD1: 46086 | BE1: 46090 | BF1: 46090 | BG1: 46093 | BH1: 46097 | BI1: 46100 | BJ1: 46112 | BK1: 46112 | BL1: 46112 | BM1: 46113 | BN1: 46113 | BO1: 46118 | BP1: 46118 | BQ1: 46118 | BR1: 46121 | BS1: 46122 | BT1: 46125 | BU1: 46127
A2: SELL | B2: 45995 | C2: 45995 | D2: 46003 | E2: 46003 | F2: 46003 | G2: 46003 | H2: 46006 | I2: 46006 | J2: 46007 | K2: 46007 | L2: 46007 | M2: 46008 | N2: 46008 | O2: 46024 | P2: 46029 | Q2: 46031 | R2: 46031 | S2: 46035 | T2: 46042 | U2: 46043 | V2: 46049 | W2: 46050 | X2: 46050 | Y2: 46052 | Z2: 46052 | AA2: 46057 | AB2: 46057 | AC2: 46057 | AD2: 46057 | AE2: 46057 | AF2: 46057 | AG2: 46057 | AH2: 46057 | AI2: 46057 | AJ2: 46057 | AK2: 46057 | AL2: 46058 | AM2: 46057 | AN2: 46080 | AO2: 46058 | AP2: 46070 | AQ2: 46064 | AR2: 46064 | AS2: 46070 | AT2: 46084 | AV2: 46084 | AW2: 46078 | AX2: 46084 | AY2: 46084 | AZ2: 46084 | BA2: 46084 | BB2: 46121 | BC2: 46100 | BE2: 46114 | BG2: 46100 | BH2: 46100 | BI2: 46105 | BL2: 46114 | BO2: 46119
A3: Shares | AU3: 4039 | BD3: 14286 | BF3: 1633 | BJ3: 527 | BK3: 321 | BM3: 3693 | BN3: 2588 | BP3: 3243 | BQ3: 5405 | BR3: 7942 | BS3: 328 | BT3: 586 | BU3: 1027
AU4: CGEM | BD4: ALTO | BF4: CAPR | BJ4: MRVL | BK4: LABU | BM4: NTLA | BN4: LUNR | BP4: WULF | BQ4: BCRX | BR4: POET | BS4: ARM | BT4: CAVA | BU4: YOU
A5: 45979 | I5: 7.87 | N5: 19.71 | AA5: 4.32
A6: 45980 | I6: 8.23 | L6: 83.4 | N6: 18.95 | R6: 4.21 | AA6: 4.25
A7: 45981 | H7: 20.4 | I7: 7.44 | K7: 30.34 | L7: 85.65 | N7: 17.81 | Q7: 4.21 | R7: 3.99 | AA7: 4.2 | AB7: 74.69 | AC7: 7.65
A8: 45982 | H8: 17.93 | I8: 7.09 | J8: 92.83 | K8: 31.42 | L8: 93.55 | N8: 17.93 | Q8: 4.19 | R8: 4.19 | AA8: 4.27 | AB8: 67.35 | AC8: 6.74
A9: 45985 | B9: 311 | H9: 18.09 | I9: 7.49 | J9: 111.4 | K9: 31.4 | L9: 111.4 | M9: 2 | N9: 18.09 | Q9: 4.42 | R9: 4.42 | AA9: 4.63 | AB9: 73 | AC9: 8.72
A10: 45986 | B10: 323.64 | H10: 18.65 | I10: 7.39 | J10: 107.69 | K10: 31.51 | L10: 107.69 | M10: 2.04 | N10: 18.65 | Q10: 4.59 | R10: 4.59 | AA10: 4.67 | AB10: 74 | AC10: 8.44
A11: 45987 | B11: 320.28 | H11: 19.23 | I11: 7.68 | J11: 110.16 | K11: 30.86 | L11: 110.16 | M11: 2.08 | N11: 19.23 | Q11: 4.86 | R11: 4.86 | AA11: 4.84 | AB11: 77.53 | AC11: 8.24
A12: 45988 | B12: 320.12 | H12: 20.25 | I12: 7.67 | J12: 110.39 | K12: 31.34 | L12: 110.39 | M12: 2.15 | N12: 20.25 | Q12: 4.74 | R12: 4.74 | AA12: 4.95 | AB12: 78.12 | AC12: 7.9
A13: 45989 | B13: 320.12 | H13: 20.25 | I13: 7.67 | J13: 110.39 | K13: 31.34 | L13: 110.39 | M13: 2.15 | N13: 20.25 | Q13: 4.74 | R13: 4.74 | AA13: 4.95 | AB13: 78.12 | AC13: 7.9
A14: 45992 | B14: 315.12 | H14: 18.55 | I14: 6.73 | J14: 98.27 | K14: 29.53 | L14: 98.27 | M14: 2.09 | N14: 18.55 | Q14: 4.43 | R14: 4.43 | AA14: 4.61 | AB14: 75.27 | AC14: 7.58
A15: 45993 | B15: 316.02 | C15: 40.93 | H15: 18.18 | I15: 6.56 | J15: 97.38 | K15: 28.44 | L15: 97.38 | M15: 2.05 | N15: 18.18 | Q15: 4.06 | R15: 4.06 | AA15: 4.68 | AB15: 72.16 | AC15: 8.07
A16: 45994 | B16: 320.62 | C16: 43.76 | H16: 17.85 | I16: 7.18 | J16: 101.19 | K16: 30.4 | L16: 101.19 | M16: 2.29 | N16: 17.85 | Q16: 4.49 | R16: 4.49 | AA16: 6.01 | AB16: 73.59 | AC16: 8.92
A17: 45995 | B17: 316 | C17: 42.2 | H17: 18.35 | I17: 7.84 | J17: 104.71 | K17: 29.38 | L17: 104.71 | M17: 2.44 | N17: 18.35 | Q17: 5.06 | R17: 5.06 | AA17: 6.37 | AB17: 76.8 | AC17: 9.19
A18: 45996 | H18: 17.58 | I18: 7.8 | J18: 100.98 | K18: 29.38 | L18: 100.98 | M18: 2.37 | N18: 17.58 | Q18: 5.05 | R18: 5.05 | AA18: 6.05 | AB18: 78.97 | AC18: 9.07
A19: 45999 | H19: 18.06 | I19: 8.27 | J19: 99.8 | K19: 30 | L19: 99.8 | M19: 2.42 | N19: 18.06 | Q19: 5.45 | R19: 5.45 | AA19: 6.23 | AB19: 77.17 | AC19: 9.02
A20: 46000 | G20: 15.6 | H20: 17.87 | I20: 7.91 | J20: 97.46 | K20: 29 | L20: 97.46 | M20: 2.45 | N20: 17.87 | Q20: 5.31 | R20: 5.31 | AA20: 6.9 | AB20: 79.17 | AC20: 9.23
A21: 46001 | D21: 2.02 | G21: 15.76 | H21: 18.32 | I21: 8.18 | J21: 94.93 | K21: 29 | L21: 94.93 | M21: 2.36 | N21: 18.32 | Q21: 5.56 | R21: 5.56 | AA21: 7.15 | AB21: 78.37 | AC21: 8.32 | AD21: 34.4
A22: 46002 | D22: 2.2 | F22: 117 | G22: 15.83 | H22: 18.71 | I22: 8.36 | J22: 95.06 | K22: 29 | L22: 95.06 | M22: 2.32 | N22: 18.71 | Q22: 5.76 | R22: 5.76 | U22: 16 | AA22: 7.22 | AB22: 82.01 | AC22: 9.02 | AD22: 39.67 | AE22: 16 | AF22: 24
A23: 46003 | D23: 2.1 | E23: 10.06 | F23: 111.68 | G23: 14.45 | H23: 17.93 | I23: 8.78 | J23: 90.82 | K23: 31 | L23: 90.82 | M23: 2.17 | N23: 17.93 | Q23: 5.79 | R23: 5.79 | U23: 18.24 | AA23: 6.5 | AB23: 77.85 | AC23: 8.75 | AD23: 36.31 | AE23: 18.24 | AF23: 26.42
A24: 46006 | H24: 17.35 | I24: 11.33 | J24: 91.04 | K24: 31 | L24: 91.04 | M24: 2.15 | N24: 17.35 | O24: 5 | Q24: 5.76 | R24: 5.76 | U24: 18.05 | AA24: 5.94 | AB24: 75.07 | AC24: 7.69 | AD24: 36.75 | AE24: 18.05 | AF24: 26
A25: 46007 | J25: 89.5 | K25: 28.68 | L25: 86.77 | M25: 2.1 | N25: 17.54 | O25: 5.17 | Q25: 5.82 | R25: 5.82 | U25: 17.88 | AA25: 6.07 | AB25: 81.36 | AC25: 8.09 | AD25: 34.36 | AE25: 17.88 | AF25: 26.61
A26: 46008 | M26: 1.95 | N26: 17.12 | O26: 5.27 | Q26: 5.44 | R26: 5.44 | S26: 3.91 | U26: 16.47 | AA26: 5.97 | AB26: 79.1 | AC26: 7.37 | AD26: 32.96 | AE26: 16.47 | AF26: 26.98
A27: 46009 | O27: 5.77 | P27: 25.42 | Q27: 5.45 | R27: 5.45 | S27: 4.17 | U27: 17.49 | AA27: 6.13 | AB27: 82.82 | AC27: 7.8 | AD27: 32.87 | AE27: 17.49 | AF27: 26.18
A28: 46010 | O28: 5.6 | P28: 24.49 | Q28: 5.49 | R28: 5.49 | S28: 4.32 | U28: 19.18 | AA28: 6.78 | AB28: 82.61 | AC28: 9.22 | AD28: 33.09 | AE28: 19.18 | AF28: 26.68
A29: 46013 | O29: 5.71 | P29: 27.13 | Q29: 5.86 | R29: 5.86 | S29: 4.38 | U29: 20.6 | AA29: 7.61 | AB29: 82.52 | AC29: 9.27 | AD29: 34.42 | AE29: 20.6 | AF29: 27.54
A30: 46014 | O30: 5.75 | P30: 23.93 | Q30: 5.71 | R30: 5.71 | S30: 4.07 | U30: 20.73 | AA30: 7.15 | AB30: 78.92 | AC30: 8.96 | AD30: 34.2 | AE30: 20.73 | AF30: 26.76
A31: 46015 | O31: 5.87 | P31: 24.36 | Q31: 5.91 | R31: 5.91 | S31: 4.19 | U31: 20.32 | AA31: 7.02 | AB31: 79.8 | AC31: 9.13 | AD31: 33.67 | AE31: 20.32 | AF31: 26.88
A32: 46016 | O32: 5.28 | P32: 24.18 | Q32: 5.83 | R32: 5.83 | S32: 4.16 | U32: 19.36 | AA32: 6.81 | AB32: 74.69 | AC32: 8.48 | AD32: 33.73 | AE32: 19.36 | AF32: 26.16
A33: 46017 | O33: 5.28 | P33: 24.18 | Q33: 5.83 | R33: 5.83 | S33: 4.16 | U33: 19.36 | AA33: 6.81 | AB33: 74.69 | AC33: 8.48 | AD33: 33.73 | AE33: 19.36 | AF33: 26.16
A34: 46020 | O34: 5.21 | P34: 24.31 | Q34: 5.65 | R34: 5.65 | S34: 4.45 | U34: 19.87 | AA34: 6.54 | AB34: 71.32 | AC34: 8.46 | AD34: 32.97 | AE34: 19.87 | AF34: 25.61
A35: 46021 | O35: 5.18 | P35: 23.79 | Q35: 5.66 | R35: 5.66 | S35: 4.26 | U35: 19.74 | AA35: 6.52 | AB35: 71.8 | AC35: 8.99 | AD35: 33.7 | AE35: 19.74 | AF35: 25.35
A36: 46022 | O36: 5.18 | P36: 23.77 | Q36: 5.5 | R36: 5.5 | S36: 4.18 | U36: 19.72 | AA36: 6.33 | AB36: 71.18 | AC36: 9.76 | AD36: 32 | AE36: 19.72 | AF36: 25.42
A37: 46023 | O37: 4.64 | P37: 25.41 | Q37: 5.25 | R37: 5.25 | S37: 4.28 | U37: 20.41 | AA37: 7.16 | AB37: 75.96 | AC37: 11.02 | AD37: 33.41 | AE37: 20.41 | AF37: 25.91
A38: 46024 | O38: 4.93 | P38: 25.41 | Q38: 5.25 | R38: 5.25 | S38: 4.28 | U38: 20.41 | AA38: 7.16 | AB38: 75.96 | AC38: 11.02 | AD38: 33.41 | AE38: 20.41 | AF38: 25.91
A39: 46027 | P39: 25.18 | Q39: 4.89 | R39: 4.89 | S39: 4.18 | U39: 21.39 | AA39: 7.43 | AB39: 76.85 | AC39: 12.53 | AD39: 33.38 | AE39: 21.39 | AF39: 24.97
A40: 46028 | P40: 23.48 | Q40: 5.26 | R40: 5.26 | S40: 4.55 | U40: 21.84 | AA40: 7.35 | AB40: 80.02 | AC40: 12.84 | AD40: 35.2 | AE40: 21.84 | AF40: 25.9
A41: 46029 | P41: 22.07 | Q41: 5.31 | R41: 5.31 | S41: 4.85 | U41: 22.61 | AA41: 7.45 | AB41: 81 | AC41: 12.18 | AD41: 34.86 | AE41: 22.61 | AF41: 26.73
A42: 46030 | Q42: 5.14 | R42: 5.14 | S42: 4.61 | U42: 22.44 | AA42: 7.28 | AB42: 80.76 | AC42: 14.01 | AD42: 31.78 | AE42: 22.44 | AF42: 26.31 | AG42: 10.79
A43: 46031 | Q43: 5.14 | R43: 5.02 | S43: 4.59 | U43: 22.71 | Z43: 18 | AA43: 7.39 | AB43: 79.65 | AC43: 13.69 | AD43: 33.33 | AE43: 22.71 | AF43: 26.03 | AG43: 10.9 | AI43: 18.47
A44: 46034 | S44: 4.14 | U44: 25.44 | V44: 1.88 | Z44: 18.68 | AA44: 7.21 | AB44: 86.51 | AC44: 13.19 | AD44: 33.7 | AE44: 25.44 | AF44: 25.81 | AG44: 10.61 | AI44: 18.91
A45: 46035 | S45: 3.97 | U45: 25.32 | V45: 1.87 | Z45: 18.43 | AA45: 7.14 | AB45: 81.42 | AC45: 13.89 | AD45: 33.39 | AE45: 25.32 | AF45: 26.18 | AG45: 10.73 | AI45: 18.45
A46: 46036 | T46: 19.11 | U46: 26.73 | V46: 1.87 | W46: 8.98 | Z46: 20.86 | AA46: 8.09 | AB46: 81.14 | AC46: 13.56 | AD46: 31.42 | AE46: 26.73 | AF46: 27.35 | AG46: 10.87 | AH46: 10.97 | AI46: 17.6
A47: 46037 | T47: 18.26 | U47: 28.28 | V47: 1.97 | W47: 8.72 | Z47: 18.44 | AA47: 8.31 | AB47: 80.19 | AC47: 12.82 | AD47: 34.22 | AE47: 28.28 | AF47: 26 | AG47: 10.66 | AH47: 10.66 | AI47: 17.33
A48: 46038 | T48: 18.23 | U48: 28.78 | V48: 1.92 | W48: 8.36 | Z48: 19.47 | AA48: 8.3 | AB48: 79.41 | AC48: 12.16 | AD48: 34.53 | AE48: 28.78 | AF48: 26.27 | AG48: 10.72 | AH48: 10.72 | AI48: 17.68
A49: 46041 | T49: 16.79 | U49: 28 | V49: 1.82 | W49: 9.02 | Z49: 19.17 | AA49: 8.24 | AB49: 78.24 | AC49: 13.13 | AD49: 34.44 | AE49: 28 | AF49: 26.14 | AG49: 10.87 | AH49: 10.87 | AI49: 17.27
A50: 46042 | T50: 17.62 | U50: 28 | V50: 1.82 | W50: 9.02 | Y50: 2.76 | Z50: 19.17 | AA50: 8.24 | AB50: 78.24 | AC50: 13.13 | AD50: 34.44 | AE50: 28 | AF50: 26.14 | AG50: 10.87 | AH50: 10.87 | AI50: 17.27 | AJ50: 8.4
A51: 46043 | U51: 27.2 | V51: 1.83 | W51: 9.48 | Y51: 2.87 | Z51: 20.32 | AA51: 8.37 | AB51: 85.36 | AC51: 12.55 | AD51: 36.25 | AE51: 26.38 | AF51: 26.02 | AG51: 11.6 | AH51: 11.6 | AI51: 18.1 | AJ51: 9.9 | AK51: 11.4 | AL51: 11.4
A52: 46044 | V52: 1.86 | W52: 10.51 | Y52: 2.89 | Z52: 19.69 | AA52: 6.94 | AB52: 96.57 | AC52: 12.62 | AD52: 36.17 | AE52: 26.06 | AF52: 26.18 | AG52: 12.57 | AH52: 12.57 | AI52: 18.63 | AJ52: 9.75 | AK52: 11 | AL52: 11
A53: 46045 | V53: 1.83 | W53: 9.76 | X53: 2.03 | Y53: 2.82 | Z53: 20.11 | AA53: 6.91 | AB53: 93.25 | AC53: 12.17 | AD53: 34.72 | AE53: 26.94 | AF53: 26.01 | AG53: 12.5 | AH53: 12.5 | AI53: 19.38 | AJ53: 9.17 | AK53: 10.94 | AL53: 10.94
A54: 46048 | V54: 1.7 | W54: 8.88 | X54: 2.01 | Y54: 2.67 | Z54: 20.53 | AA54: 6.46 | AB54: 89.88 | AC54: 11.16 | AD54: 34.69 | AE54: 25.87 | AF54: 26.6 | AG54: 11.97 | AH54: 11.97 | AI54: 19.51 | AJ54: 9.63 | AK54: 11.12 | AL54: 11.12
A55: 46049 | V55: 1.66 | W55: 9.28 | X55: 2.04 | Y55: 2.62 | Z55: 21.6 | AA55: 6.79 | AB55: 87.75 | AC55: 12.26 | AD55: 35.62 | AE55: 28.07 | AF55: 26.83 | AG55: 12.34 | AH55: 12.34 | AI55: 21.04 | AJ55: 9.82 | AK55: 10.75 | AL55: 10.75
A56: 46050 | W56: 8.32 | X56: 1.92 | Y56: 2.61 | Z56: 22.16 | AA56: 6.22 | AB56: 92.06 | AC56: 12.27 | AD56: 35.94 | AE56: 27.88 | AF56: 26.06 | AG56: 11.85 | AH56: 11.85 | AI56: 20.26 | AJ56: 9.23 | AK56: 10.66 | AL56: 10.66 | AM56: 4.92
A57: 46051 | Y57: 2.57 | Z57: 22.02 | AA57: 5.95 | AB57: 91.28 | AC57: 11.27 | AD57: 35.28 | AE57: 26.35 | AF57: 26.45 | AG57: 11.92 | AH57: 11.92 | AI57: 20.47 | AJ57: 9.44 | AK57: 11.44 | AL57: 11.44 | AM57: 4.53
A58: 46052 | Y58: 2.48 | Z58: 20.69 | AA58: 5.8 | AB58: 86.73 | AC58: 10.36 | AD58: 34.57 | AE58: 24.97 | AF58: 26 | AG58: 11.96 | AH58: 11.96 | AI58: 20.22 | AJ58: 8.85 | AK58: 11.49 | AL58: 11.49 | AM58: 4.49
A59: 46055 | AA59: 5.84 | AB59: 80.57 | AC59: 10.64 | AD59: 36.1 | AE59: 22.85 | AF59: 26.08 | AG59: 12.71 | AH59: 12.71 | AI59: 19.98 | AJ59: 8.69 | AK59: 11.83 | AL59: 11.83 | AM59: 4.83
A60: 46056 | AA60: 6.04 | AB60: 82.69 | AC60: 11.38 | AD60: 35.19 | AE60: 23.95 | AF60: 25.8 | AG60: 13.21 | AH60: 13.21 | AI60: 19.98 | AJ60: 8.37 | AK60: 11.83 | AL60: 11.83 | AM60: 4.8 | AN60: 5.56
A61: 46057 | AA61: 5.56 | AB61: 77.2 | AC61: 10.7 | AD61: 34.1 | AE61: 22.89 | AF61: 25.32 | AG61: 12.16 | AH61: 12.31 | AI61: 18.85 | AJ61: 8.18 | AK61: 11.08 | AL61: 11.18 | AM61: 4.55 | AN61: 5.96
A62: 46058 | AL62: 10.65 | AN62: 6.04 | AO62: 2.65
A63: 46059 | AN63: 6.36 | AO63: 2.56 | AP63: 2.74 | AQ63: 27.15
A64: 46062 | AN64: 6.16 | AP64: 2.77 | AQ64: 27.49
A65: 46063 | AN65: 6.01 | AP65: 2.75 | AQ65: 26.68 | AR65: 4.63
A66: 46064 | AN66: 5.81 | AP66: 2.77 | AQ66: 26.16 | AR66: 4.44 | AS66: 65.19
A67: 46065 | AN67: 5.63 | AP67: 2.64 | AS67: 62.04 | AT67: 21.83
A68: 46066 | AN68: 5.91 | AP68: 2.68 | AS68: 62.84 | AT68: 22.2
A69: 46069 | AN69: 6.07 | AP69: 2.54 | AS69: 61.09 | AT69: 27.85
A70: 46070 | AN70: 6.07 | AP70: 2.52 | AS70: 59.4 | AT70: 27.85 | AU70: 12.19
A71: 46071 | AN71: 6.46 | AT71: 29.03 | AU71: 12.44 | AV71: 62.61 | AW71: 18.09 | AX71: 168
A72: 46072 | AN72: 5.91 | AT72: 29.18 | AU72: 13.88 | AV72: 62.57 | AW72: 18.19 | AX72: 170.74 | AY72: 25.85 | AZ72: 13.48
A73: 46073 | AN73: 5.98 | AT73: 29.27 | AU73: 13.65 | AV73: 64.34 | AW73: 17.55 | AX73: 163.19 | AY73: 28.51 | AZ73: 12.47 | BA73: 61.27
A74: 46076 | AN74: 5.83 | AT74: 28.66 | AU74: 13.99 | AV74: 65.55 | AW74: 18.14 | AX74: 170.88 | AY74: 27.87 | AZ74: 12.45 | BA74: 59.81
A75: 46077 | AN75: 5.73 | AT75: 29.08 | AU75: 14.27 | AV75: 67.88 | AW75: 18.9 | AX75: 179.4 | AY75: 27.91 | AZ75: 12.6 | BA75: 61.41
A76: 46078 | AN76: 5.57 | AT76: 29.2 | AU76: 14.36 | AV76: 68.82 | AW76: 16.67 | AX76: 176.87 | AY76: 28.35 | AZ76: 16.37 | BA76: 64.9
A77: 46079 | AN77: 5.8 | AT77: 28.86 | AU77: 15.21 | AV77: 68.38 | AX77: 173.7 | AY77: 27.89 | AZ77: 16.22 | BA77: 63.47 | BB77: 36.58
A78: 46080 | AN78: 5.51 | AT78: 28.83 | AU78: 15.5 | AV78: 68.08 | AX78: 172.7 | AY78: 27.93 | AZ78: 14.41 | BA78: 62.08 | BB78: 36.45
A79: 46083 | AT79: 28.83 | AU79: 15.99 | AV79: 68.29 | AX79: 169.5 | AY79: 26.86 | AZ79: 14.02 | BA79: 64.08 | BB79: 36.14
A80: 46084 | AT80: 27.88 | AU80: 15.73 | AV80: 63.15 | AX80: 156.07 | AY80: 25.33 | AZ80: 12.76 | BA80: 60.4 | BB80: 36.82 | BC80: 18.25
A81: 46085 | AU81: 16.3 | BB81: 39.17 | BC81: 18.62
A82: 46086 | AU82: 15.6 | BB82: 39.67 | BC82: 17.67 | BD82: 3.5
A83: 46087 | AU83: 15.74 | BB83: 42.02 | BC83: 17.63 | BD83: 4.39
A84: 46090 | AU84: 15.31 | BB84: 41.84 | BC84: 18.08 | BD84: 4.37 | BE84: 94.77 | BF84: 30.63
A85: 46091 | AU85: 14.91 | BB85: 40.69 | BC85: 17.68 | BD85: 4.6 | BE85: 82.1 | BF85: 33.4
A86: 46092 | AU86: 14.31 | BB86: 38.87 | BC86: 18.45 | BD86: 4.58 | BE86: 86.07 | BF86: 33.57
A87: 46093 | AU87: 13.95 | BB87: 38.06 | BC87: 17.64 | BD87: 4.75 | BE87: 94.43 | BF87: 33.42 | BG87: 12.52
A88: 46094 | AU88: 13.49 | BB88: 37.78 | BC88: 17.6 | BD88: 4.66 | BE88: 96.84 | BF88: 30.5 | BG88: 12.03
A89: 46097 | AU89: 14.03 | BB89: 37.38 | BC89: 17.69 | BD89: 4.31 | BE89: 92.46 | BF89: 30.56 | BG89: 11.8 | BH89: 13.44
A90: 46098 | AU90: 13.44 | BB90: 37.95 | BC90: 18.9 | BD90: 4.71 | BE90: 95.53 | BF90: 31.19 | BG90: 12.21 | BH90: 13.48
A91: 46099 | AU91: 13.13 | BB91: 37.07 | BC91: 18.11 | BD91: 4.59 | BE91: 95.46 | BF91: 30.9 | BG91: 11.96 | BH91: 13.21
A92: 46100 | AU92: 13.08 | BB92: 37.45 | BC92: 16.81 | BD92: 4.52 | BE92: 95.55 | BF92: 31.17 | BG92: 11.38 | BH92: 12.86 | BI92: 38.15
A93: 46101 | AU93: 12.74 | BB93: 37.63 | BD93: 4.16 | BE93: 98.23 | BF93: 29.1 | BI93: 37.63
A94: 46104 | AU94: 12.84 | BB94: 38.64 | BD94: 4.13 | BE94: 88.13 | BF94: 30.1 | BI94: 38.64
A95: 46105 | AU95: 13.64 | BB95: 36.71 | BD95: 4.31 | BE95: 92.35 | BF95: 28.87 | BI95: 36.79
A96: 46106 | AU96: 14.06 | BB96: 35.69 | BD96: 4.38 | BE96: 90.32 | BF96: 29.9
A97: 46107 | AU97: 13.67 | BB97: 37.52 | BD97: 4.43 | BE97: 94.48 | BF97: 29.95
A98: 46108 | AU98: 12.85 | BB98: 35.36 | BD98: 4.51 | BE98: 99.64 | BF98: 28.9
A99: 46111 | AU99: 13.42 | BB99: 36.22 | BD99: 4.59 | BE99: 102.88 | BF99: 27.77
A100: 46112 | AU100: 14.21 | BB100: 37.19 | BD100: 4.84 | BE100: 101.38 | BF100: 30.4 | BJ100: 99.05 | BK100: 166.09 | BL100: 5.94
...

Sheet Cost
B1: =+Precios!A1 -> BUY | C1: =+Precios!B1 -> 45985 | D1: =+Precios!C1 -> 45993 | E1: =+Precios!D1 -> 46001 | F1: =+Precios!E1 -> 46003 | G1: =+Precios!F1 -> 46002 | H1: =+Precios!G1 -> 46000 | I1: =+Precios!H1 -> 45981 | ... AU1: =+Precios!AT1 -> 46065 | AV1: 46070 | AW1: =+Precios!AV1 -> 46071 | AX1: =+Precios!AW1 -> 46071 | AY1: =+Precios!AX1 -> 46071 | AZ1: =+Precios!AY1 -> 46072 | BA1: =+Precios!AZ1 -> 46072 | BB1: =+Precios!BA1 -> 46073 | BC1: =+Precios!BB1 -> 46079 | BD1: =+Precios!BC1 -> 46084 | ... BV1: =+Precios!BU1 -> 46127
B2: =+Precios!A2 -> SELL | C2: =+Precios!B2 -> 45995 | D2: =+Precios!C2 -> 45995 | E2: =+Precios!D2 -> 46003 | F2: =+Precios!E2 -> 46003 | G2: =+Precios!F2 -> 46003 | H2: =+Precios!G2 -> 46003 | I2: =+Precios!H2 -> 46006 | ... AU2: =+Precios!AT2 -> 46084 | AW2: =+Precios!AV2 -> 46084 | AX2: =+Precios!AW2 -> 46078 | AY2: =+Precios!AX2 -> 46084 | AZ2: =+Precios!AY2 -> 46084 | BA2: =+Precios!AZ2 -> 46084 | BB2: =+Precios!BA2 -> 46084 | BC2: =+Precios!BB2 -> 46121 | BD2: =+Precios!BC2 -> 46100 | ... BV2: =+Precios!BU2 -> 0
B3: =+Precios!A3 -> Shares | C3: =+Precios!B3 -> 0 | D3: =+Precios!C3 -> 0 | E3: =+Precios!D3 -> 0 | F3: =+Precios!E3 -> 0 | G3: =+Precios!F3 -> 0 | H3: =+Precios!G3 -> 0 | I3: =+Precios!H3 -> 0 | ... AU3: =+Precios!AT3 -> 0 | AV3: 4039 | AW3: =+Precios!AV3 -> 0 | AX3: =+Precios!AW3 -> 0 | AY3: =+Precios!AX3 -> 0 | AZ3: =+Precios!AY3 -> 0 | BA3: =+Precios!AZ3 -> 0 | BB3: =+Precios!BA3 -> 0 | BC3: =+Precios!BB3 -> 0 | BD3: =+Precios!BC3 -> 0 | ... BV3: =+Precios!BU3 -> 1027
AV4: 2019 | BE4: 12143 | BK4: =527-175 -> 352 | BL4: =+BL3-48 -> 273 | BO4: 2200 | BQ4: 2757 | BR4: 3603 | BS4: 6734
BK5: 289 | BL5: =+BL4-32 -> 241 | BS5: =+BS4-792 -> 5942
A6: COST | B6: =+Precios!A4 -> 0 | C6: =+Precios!B4 -> 0 | D6: =+Precios!C4 -> 0 | E6: =+Precios!D4 -> 0 | F6: =+Precios!E4 -> 0 | G6: =+Precios!F4 -> 0 | H6: =+Precios!G4 -> 0 | I6: =+Precios!H4 -> 0 | ... AU6: =+Precios!AT4 -> 0 | AV6: CGEM | AW6: =+Precios!AV4 -> 0 | AX6: =+Precios!AW4 -> 0 | AY6: =+Precios!AX4 -> 0 | AZ6: =+Precios!AY4 -> 0 | BA6: =+Precios!AZ4 -> 0 | BB6: =+Precios!BA4 -> 0 | BC6: =+Precios!BB4 -> 0 | BD6: =+Precios!BC4 -> 0 | ... BV6: =+Precios!BU4 -> YOU
A7: =+SUM(C7:XFD7) -> 0 | B7: =+Precios!A5 -> 45979 | C7: =+Precios!B5*Precios!B$3 -> 0 | D7: =+Precios!C5*Precios!C$3 -> 0 | E7: =+Precios!D5*Precios!D$3 -> 0 | F7: =+Precios!E5*Precios!E$3 -> 0 | G7: =+Precios!F5*Precios!F$3 -> 0 | H7: =+Precios!G5*Precios!G$3 -> 0 | I7: =+Precios!H5*Precios!H$3 -> 0 | J7: =+Precios!I5*Precios!I$3 -> 0 | ... AM7: =+Precios!AL5*Precios!AL$3 -> 0 | AP7: =+Precios!AO5*Precios!AO$3 -> 0 | AQ7: =+Precios!AP5*Precios!AP$3 -> 0 | AR7: =+Precios!AQ5*Precios!AQ$3 -> 0 | AS7: =+Precios!AR5*Precios!AR$3 -> 0 | AT7: =+Precios!AS5*Precios!AS$3 -> 0 | AU7: =+Precios!AT5*Precios!AT$3 -> 0 | AW7: =+Precios!AV5*Precios!AV$3 -> 0 | AX7: =+Precios!AW5*Precios!AW$3 -> 0 | AY7: =+Precios!AX5*Precios!AX$3 -> 0 | AZ7: =+Precios!AY5*Precios!AY$3 -> 0 | BA7: =+Precios!AZ5*Precios!AZ$3 -> 0 | BB7: =+Precios!BA5*Precios!BA$3 -> 0 | BC7: =+Precios!BB5*Precios!BB$3 -> 0 | BD7: =+Precios!BC5*Precios!BC$3 -> 0 | ... BM7: =+Precios!BL5*Precios!BL$3 -> 0
A8: =+SUM(C8:XFD8) -> 0 | B8: =+Precios!A6 -> 45980 | C8: =+Precios!B6*Precios!B$3 -> 0 | D8: =+Precios!C6*Precios!C$3 -> 0 | E8: =+Precios!D6*Precios!D$3 -> 0 | F8: =+Precios!E6*Precios!E$3 -> 0 | G8: =+Precios!F6*Precios!F$3 -> 0 | H8: =+Precios!G6*Precios!G$3 -> 0 | I8: =+Precios!H6*Precios!H$3 -> 0 | J8: =+J7 -> 0 | K8: =+Precios!J6*Precios!J$3 -> 0 | L8: =+Precios!K6*Precios!K$3 -> 0 | M8: =+Precios!L6*Precios!L$3 -> 0 | N8: =+Precios!M6*Precios!M$3 -> 0 | O8: =+O7 -> 0 | P8: =+Precios!O6*Precios!O$3 -> 0 | Q8: =+Precios!P6*Precios!P$3 -> 0 | R8: =+Precios!Q6*Precios!Q$3 -> 0 | S8: =+Precios!R6*Precios!R$3 -> 0 | T8: =+Precios!S6*Precios!S$3 -> 0 | U8: =+Precios!T6*Precios!T$3 -> 0 | V8: =+Precios!U6*Precios!U$3 -> 0 | W8: =+Precios!V6*Precios!V$3 -> 0 | ... AA8: =+Precios!Z6*Precios!Z$3 -> 0 | AB8: =+AB7 -> 0 | AC8: =+Precios!AB6*Precios!AB$3 -> 0 | AD8: =+Precios!AC6*Precios!AC$3 -> 0 | AE8: =+Precios!AD6*Precios!AD$3 -> 0 | AF8: =+Precios!AE6*Precios!AE$3 -> 0 | AG8: =+Precios!AF6*Precios!AF$3 -> 0 | AH8: =+Precios!AG6*Precios!AG$3 -> 0 | AI8: =+Precios!AH6*Precios!AH$3 -> 0 | AJ8: =+Precios!AI6*Precios!AI$3 -> 0 | ... AM8: =+Precios!AL6*Precios!AL$3 -> 0 | AP8: =+Precios!AO6*Precios!AO$3 -> 0 | AQ8: =+Precios!AP6*Precios!AP$3 -> 0 | AR8: =+Precios!AQ6*Precios!AQ$3 -> 0 | AS8: =+Precios!AR6*Precios!AR$3 -> 0 | AT8: =+Precios!AS6*Precios!AS$3 -> 0 | AU8: =+Precios!AT6*Precios!AT$3 -> 0 | AW8: =+Precios!AV6*Precios!AV$3 -> 0 | AX8: =+Precios!AW6*Precios!AW$3 -> 0 | AY8: =+Precios!AX6*Precios!AX$3 -> 0 | AZ8: =+Precios!AY6*Precios!AY$3 -> 0 | BA8: =+Precios!AZ6*Precios!AZ$3 -> 0 | BB8: =+Precios!BA6*Precios!BA$3 -> 0 | BC8: =+Precios!BB6*Precios!BB$3 -> 0 | BD8: =+Precios!BC6*Precios!BC$3 -> 0 | ... BM8: =+Precios!BL6*Precios!BL$3 -> 0
A9: =+SUM(C9:XFD9) -> 0 | B9: =+Precios!A7 -> 45981 | C9: =+Precios!B7*Precios!B$3 -> 0 | D9: =+Precios!C7*Precios!C$3 -> 0 | E9: =+Precios!D7*Precios!D$3 -> 0 | F9: =+Precios!E7*Precios!E$3 -> 0 | G9: =+Precios!F7*Precios!F$3 -> 0 | H9: =+Precios!G7*Precios!G$3 -> 0 | I9: =+Precios!H7*Precios!H$3 -> 0 | J9: =+J8 -> 0 | K9: =+Precios!J7*Precios!J$3 -> 0 | L9: =+Precios!K7*Precios!K$3 -> 0 | M9: =+M8 -> 0 | N9: =+Precios!M7*Precios!M$3 -> 0 | O9: =+O8 -> 0 | P9: =+Precios!O7*Precios!O$3 -> 0 | Q9: =+Precios!P7*Precios!P$3 -> 0 | R9: =+Precios!Q7*Precios!Q$3 -> 0 | S9: =+S8 -> 0 | T9: =+Precios!S7*Precios!S$3 -> 0 | U9: =+Precios!T7*Precios!T$3 -> 0 | V9: =+Precios!U7*Precios!U$3 -> 0 | W9: =+Precios!V7*Precios!V$3 -> 0 | X9: =+Precios!W7*Precios!W$3 -> 0 | Y9: =+Precios!X7*Precios!X$3 -> 0 | Z9: =+Precios!Y7*Precios!Y$3 -> 0 | AA9: =+Precios!Z7*Precios!Z$3 -> 0 | AB9: =+AB8 -> 0 | AC9: =+Precios!AB7*Precios!AB$3 -> 0 | AD9: =+Precios!AC7*Precios!AC$3 -> 0 | AE9: =+Precios!AD7*Precios!AD$3 -> 0 | AF9: =+Precios!AE7*Precios!AE$3 -> 0 | AG9: =+Precios!AF7*Precios!AF$3 -> 0 | AH9: =+Precios!AG7*Precios!AG$3 -> 0 | AI9: =+Precios!AH7*Precios!AH$3 -> 0 | AJ9: =+Precios!AI7*Precios!AI$3 -> 0 | ... AM9: =+Precios!AL7*Precios!AL$3 -> 0 | AP9: =+Precios!AO7*Precios!AO$3 -> 0 | AQ9: =+Precios!AP7*Precios!AP$3 -> 0 | AR9: =+Precios!AQ7*Precios!AQ$3 -> 0 | AS9: =+Precios!AR7*Precios!AR$3 -> 0 | AT9: =+Precios!AS7*Precios!AS$3 -> 0 | AU9: =+Precios!AT7*Precios!AT$3 -> 0 | AW9: =+Precios!AV7*Precios!AV$3 -> 0 | AX9: =+Precios!AW7*Precios!AW$3 -> 0 | AY9: =+Precios!AX7*Precios!AX$3 -> 0 | AZ9: =+Precios!AY7*Precios!AY$3 -> 0 | BA9: =+Precios!AZ7*Precios!AZ$3 -> 0 | BB9: =+Precios!BA7*Precios!BA$3 -> 0 | BC9: =+Precios!BB7*Precios!BB$3 -> 0 | BD9: =+Precios!BC7*Precios!BC$3 -> 0 | ... BM9: =+Precios!BL7*Precios!BL$3 -> 0
A10: =+SUM(C10:XFD10) -> 0 | B10: =+Precios!A8 -> 45982 | C10: =+Precios!B8*Precios!B$3 -> 0 | D10: =+Precios!C8*Precios!C$3 -> 0 | E10: =+Precios!D8*Precios!D$3 -> 0 | F10: =+Precios!E8*Precios!E$3 -> 0 | G10: =+Precios!F8*Precios!F$3 -> 0 | H10: =+Precios!G8*Precios!G$3 -> 0 | I10: =+I9 -> 0 | J10: =+J9 -> 0 | K10: =+Precios!J8*Precios!J$3 -> 0 | L10: =+L9 -> 0 | M10: =+M9 -> 0 | N10: =+Precios!M8*Precios!M$3 -> 0 | O10: =+O9 -> 0 | P10: =+Precios!O8*Precios!O$3 -> 0 | Q10: =+Precios!P8*Precios!P$3 -> 0 | R10: =+R9 -> 0 | S10: =+S9 -> 0 | T10: =+Precios!S8*Precios!S$3 -> 0 | U10: =+Precios!T8*Precios!T$3 -> 0 | V10: =+Precios!U8*Precios!U$3 -> 0 | W10: =+Precios!V8*Precios!V$3 -> 0 | X10: =+Precios!W8*Precios!W$3 -> 0 | Y10: =+Precios!X8*Precios!X$3 -> 0 | Z10: =+Precios!Y8*Precios!Y$3 -> 0 | AA10: =+Precios!Z8*Precios!Z$3 -> 0 | AB10: =+AB9 -> 0 | AC10: =+AC9 -> 0 | AD10: =+AD9 -> 0 | AE10: =+Precios!AD8*Precios!AD$3 -> 0 | AF10: =+Precios!AE8*Precios!AE$3 -> 0 | AG10: =+Precios!AF8*Precios!AF$3 -> 0 | AH10: =+Precios!AG8*Precios!AG$3 -> 0 | AI10: =+Precios!AH8*Precios!AH$3 -> 0 | AJ10: =+Precios!AI8*Precios!AI$3 -> 0 | AK10: =+Precios!AJ8*Precios!AJ$3 -> 0 | AL10: =+Precios!AK8*Precios!AK$3 -> 0 | AM10: =+Precios!AL8*Precios!AL$3 -> 0 | AP10: =+Precios!AO8*Precios!AO$3 -> 0 | AQ10: =+Precios!AP8*Precios!AP$3 -> 0 | AR10: =+Precios!AQ8*Precios!AQ$3 -> 0 | AS10: =+Precios!AR8*Precios!AR$3 -> 0 | AT10: =+Precios!AS8*Precios!AS$3 -> 0 | AU10: =+Precios!AT8*Precios!AT$3 -> 0 | AW10: =+Precios!AV8*Precios!AV$3 -> 0 | AX10: =+Precios!AW8*Precios!AW$3 -> 0 | AY10: =+Precios!AX8*Precios!AX$3 -> 0 | AZ10: =+Precios!AY8*Precios!AY$3 -> 0 | BA10: =+Precios!AZ8*Precios!AZ$3 -> 0 | BB10: =+Precios!BA8*Precios!BA$3 -> 0 | BC10: =+Precios!BB8*Precios!BB$3 -> 0 | BD10: =+Precios!BC8*Precios!BC$3 -> 0 | ... BM10: =+Precios!BL8*Precios!BL$3 -> 0
A11: =+SUM(C11:XFD11) -> 0 | B11: =+Precios!A9 -> 45985 | C11: =+Precios!B9*Precios!B$3 -> 0 | D11: =+Precios!C9*Precios!C$3 -> 0 | E11: =+Precios!D9*Precios!D$3 -> 0 | F11: =+Precios!E9*Precios!E$3 -> 0 | G11: =+Precios!F9*Precios!F$3 -> 0 | H11: =+Precios!G9*Precios!G$3 -> 0 | I11: =+I10 -> 0 | J11: =+J10 -> 0 | K11: =+K10 -> 0 | L11: =+L10 -> 0 | M11: =+M10 -> 0 | N11: =+Precios!M9*Precios!M$3 -> 0 | O11: =+O10 -> 0 | P11: =+Precios!O9*Precios!O$3 -> 0 | Q11: =+Precios!P9*Precios!P$3 -> 0 | R11: =+R10 -> 0 | S11: =+S10 -> 0 | T11: =+Precios!S9*Precios!S$3 -> 0 | U11: =+Precios!T9*Precios!T$3 -> 0 | V11: =+Precios!U9*Precios!U$3 -> 0 | W11: =+Precios!V9*Precios!V$3 -> 0 | X11: =+Precios!W9*Precios!W$3 -> 0 | Y11: =+Precios!X9*Precios!X$3 -> 0 | Z11: =+Precios!Y9*Precios!Y$3 -> 0 | AA11: =+Precios!Z9*Precios!Z$3 -> 0 | AB11: =+AB10 -> 0 | AC11: =+AC10 -> 0 | AD11: =+AD10 -> 0 | AE11: =+Precios!AD9*Precios!AD$3 -> 0 | AF11: =+Precios!AE9*Precios!AE$3 -> 0 | AG11: =+Precios!AF9*Precios!AF$3 -> 0 | AH11: =+Precios!AG9*Precios!AG$3 -> 0 | AI11: =+Precios!AH9*Precios!AH$3 -> 0 | AJ11: =+Precios!AI9*Precios!AI$3 -> 0 | AK11: =+Precios!AJ9*Precios!AJ$3 -> 0 | AL11: =+Precios!AK9*Precios!AK$3 -> 0 | AM11: =+Precios!AL9*Precios!AL$3 -> 0 | AP11: =+Precios!AO9*Precios!AO$3 -> 0 | AQ11: =+Precios!AP9*Precios!AP$3 -> 0 | AR11: =+Precios!AQ9*Precios!AQ$3 -> 0 | AS11: =+Precios!AR9*Precios!AR$3 -> 0 | AT11: =+Precios!AS9*Precios!AS$3 -> 0 | AU11: =+Precios!AT9*Precios!AT$3 -> 0 | AW11: =+Precios!AV9*Precios!AV$3 -> 0 | AX11: =+Precios!AW9*Precios!AW$3 -> 0 | AY11: =+Precios!AX9*Precios!AX$3 -> 0 | AZ11: =+Precios!AY9*Precios!AY$3 -> 0 | BA11: =+Precios!AZ9*Precios!AZ$3 -> 0 | BB11: =+Precios!BA9*Precios!BA$3 -> 0 | BC11: =+Precios!BB9*Precios!BB$3 -> 0 | BD11: =+Precios!BC9*Precios!BC$3 -> 0 | ... BM11: =+Precios!BL9*Precios!BL$3 -> 0
A12: =+SUM(C12:XFD12) -> 0 | B12: =+Precios!A10 -> 45986 | C12: =+C11 -> 0 | D12: =+Precios!C10*Precios!C$3 -> 0 | E12: =+Precios!D10*Precios!D$3 -> 0 | F12: =+Precios!E10*Precios!E$3 -> 0 | G12: =+Precios!F10*Precios!F$3 -> 0 | H12: =+Precios!G10*Precios!G$3 -> 0 | I12: =+I11 -> 0 | J12: =+J11 -> 0 | K12: =+K11 -> 0 | L12: =+L11 -> 0 | M12: =+M11 -> 0 | N12: =+N11 -> 0 | O12: =+O11 -> 0 | P12: =+Precios!O10*Precios!O$3 -> 0 | Q12: =+Precios!P10*Precios!P$3 -> 0 | R12: =+R11 -> 0 | S12: =+S11 -> 0 | T12: =+Precios!S10*Precios!S$3 -> 0 | U12: =+Precios!T10*Precios!T$3 -> 0 | V12: =+Precios!U10*Precios!U$3 -> 0 | W12: =+Precios!V10*Precios!V$3 -> 0 | X12: =+Precios!W10*Precios!W$3 -> 0 | Y12: =+Precios!X10*Precios!X$3 -> 0 | Z12: =+Precios!Y10*Precios!Y$3 -> 0 | AA12: =+Precios!Z10*Precios!Z$3 -> 0 | AB12: =+AB11 -> 0 | AC12: =+AC11 -> 0 | AD12: =+AD11 -> 0 | AE12: =+Precios!AD10*Precios!AD$3 -> 0 | AF12: =+Precios!AE10*Precios!AE$3 -> 0 | AG12: =+Precios!AF10*Precios!AF$3 -> 0 | AH12: =+Precios!AG10*Precios!AG$3 -> 0 | AI12: =+Precios!AH10*Precios!AH$3 -> 0 | AJ12: =+Precios!AI10*Precios!AI$3 -> 0 | AK12: =+Precios!AJ10*Precios!AJ$3 -> 0 | AL12: =+Precios!AK10*Precios!AK$3 -> 0 | AM12: =+Precios!AL10*Precios!AL$3 -> 0 | AP12: =+Precios!AO10*Precios!AO$3 -> 0 | AQ12: =+Precios!AP10*Precios!AP$3 -> 0 | AR12: =+Precios!AQ10*Precios!AQ$3 -> 0 | AS12: =+Precios!AR10*Precios!AR$3 -> 0 | AT12: =+Precios!AS10*Precios!AS$3 -> 0 | AU12: =+Precios!AT10*Precios!AT$3 -> 0 | AW12: =+Precios!AV10*Precios!AV$3 -> 0 | AX12: =+Precios!AW10*Precios!AW$3 -> 0 | AY12: =+Precios!AX10*Precios!AX$3 -> 0 | AZ12: =+Precios!AY10*Precios!AY$3 -> 0 | BA12: =+Precios!AZ10*Precios!AZ$3 -> 0 | BB12: =+Precios!BA10*Precios!BA$3 -> 0 | BC12: =+Precios!BB10*Precios!BB$3 -> 0 | BD12: =+Precios!BC10*Precios!BC$3 -> 0 | ... BM12: =+Precios!BL10*Precios!BL$3 -> 0
A13: =+SUM(C13:XFD13) -> 0 | B13: =+Precios!A11 -> 45987 | C13: =+C12 -> 0 | D13: =+Precios!C11*Precios!C$3 -> 0 | E13: =+Precios!D11*Precios!D$3 -> 0 | F13: =+Precios!E11*Precios!E$3 -> 0 | G13: =+Precios!F11*Precios!F$3 -> 0 | H13: =+Precios!G11*Precios!G$3 -> 0 | I13: =+I12 -> 0 | J13: =+J12 -> 0 | K13: =+K12 -> 0 | L13: =+L12 -> 0 | M13: =+M12 -> 0 | N13: =+N12 -> 0 | O13: =+O12 -> 0 | P13: =+Precios!O11*Precios!O$3 -> 0 | Q13: =+Precios!P11*Precios!P$3 -> 0 | R13: =+R12 -> 0 | S13: =+S12 -> 0 | T13: =+Precios!S11*Precios!S$3 -> 0 | U13: =+Precios!T11*Precios!T$3 -> 0 | V13: =+Precios!U11*Precios!U$3 -> 0 | W13: =+Precios!V11*Precios!V$3 -> 0 | X13: =+Precios!W11*Precios!W$3 -> 0 | Y13: =+Precios!X11*Precios!X$3 -> 0 | Z13: =+Precios!Y11*Precios!Y$3 -> 0 | AA13: =+Precios!Z11*Precios!Z$3 -> 0 | AB13: =+AB12 -> 0 | AC13: =+AC12 -> 0 | AD13: =+AD12 -> 0 | AE13: =+Precios!AD11*Precios!AD$3 -> 0 | AF13: =+Precios!AE11*Precios!AE$3 -> 0 | AG13: =+Precios!AF11*Precios!AF$3 -> 0 | AH13: =+Precios!AG11*Precios!AG$3 -> 0 | AI13: =+Precios!AH11*Precios!AH$3 -> 0 | AJ13: =+Precios!AI11*Precios!AI$3 -> 0 | AK13: =+Precios!AJ11*Precios!AJ$3 -> 0 | AL13: =+Precios!AK11*Precios!AK$3 -> 0 | AM13: =+Precios!AL11*Precios!AL$3 -> 0 | AP13: =+Precios!AO11*Precios!AO$3 -> 0 | AQ13: =+Precios!AP11*Precios!AP$3 -> 0 | AR13: =+Precios!AQ11*Precios!AQ$3 -> 0 | AS13: =+Precios!AR11*Precios!AR$3 -> 0 | AT13: =+Precios!AS11*Precios!AS$3 -> 0 | AU13: =+Precios!AT11*Precios!AT$3 -> 0 | AW13: =+Precios!AV11*Precios!AV$3 -> 0 | AX13: =+Precios!AW11*Precios!AW$3 -> 0 | AY13: =+Precios!AX11*Precios!AX$3 -> 0 | AZ13: =+Precios!AY11*Precios!AY$3 -> 0 | BA13: =+Precios!AZ11*Precios!AZ$3 -> 0 | BB13: =+Precios!BA11*Precios!BA$3 -> 0 | BC13: =+Precios!BB11*Precios!BB$3 -> 0 | BD13: =+Precios!BC11*Precios!BC$3 -> 0 | ... BM13: =+Precios!BL11*Precios!BL$3 -> 0
A14: =+SUM(C14:XFD14) -> 0 | B14: =+Precios!A12 -> 45988 | C14: =+C13 -> 0 | D14: =+Precios!C12*Precios!C$3 -> 0 | E14: =+Precios!D12*Precios!D$3 -> 0 | F14: =+Precios!E12*Precios!E$3 -> 0 | G14: =+Precios!F12*Precios!F$3 -> 0 | H14: =+Precios!G12*Precios!G$3 -> 0 | I14: =+I13 -> 0 | J14: =+J13 -> 0 | K14: =+K13 -> 0 | L14: =+L13 -> 0 | M14: =+M13 -> 0 | N14: =+N13 -> 0 | O14: =+O13 -> 0 | P14: =+Precios!O12*Precios!O$3 -> 0 | Q14: =+Precios!P12*Precios!P$3 -> 0 | R14: =+R13 -> 0 | S14: =+S13 -> 0 | T14: =+Precios!S12*Precios!S$3 -> 0 | U14: =+Precios!T12*Precios!T$3 -> 0 | V14: =+Precios!U12*Precios!U$3 -> 0 | W14: =+Precios!V12*Precios!V$3 -> 0 | X14: =+Precios!W12*Precios!W$3 -> 0 | Y14: =+Precios!X12*Precios!X$3 -> 0 | Z14: =+Precios!Y12*Precios!Y$3 -> 0 | AA14: =+Precios!Z12*Precios!Z$3 -> 0 | AB14: =+AB13 -> 0 | AC14: =+AC13 -> 0 | AD14: =+AD13 -> 0 | AE14: =+Precios!AD12*Precios!AD$3 -> 0 | AF14: =+Precios!AE12*Precios!AE$3 -> 0 | AG14: =+Precios!AF12*Precios!AF$3 -> 0 | AH14: =+Precios!AG12*Precios!AG$3 -> 0 | AI14: =+Precios!AH12*Precios!AH$3 -> 0 | AJ14: =+Precios!AI12*Precios!AI$3 -> 0 | AK14: =+Precios!AJ12*Precios!AJ$3 -> 0 | AL14: =+Precios!AK12*Precios!AK$3 -> 0 | AM14: =+Precios!AL12*Precios!AL$3 -> 0 | AP14: =+Precios!AO12*Precios!AO$3 -> 0 | AQ14: =+Precios!AP12*Precios!AP$3 -> 0 | AR14: =+Precios!AQ12*Precios!AQ$3 -> 0 | AS14: =+Precios!AR12*Precios!AR$3 -> 0 | AT14: =+Precios!AS12*Precios!AS$3 -> 0 | AU14: =+Precios!AT12*Precios!AT$3 -> 0 | AW14: =+Precios!AV12*Precios!AV$3 -> 0 | AX14: =+Precios!AW12*Precios!AW$3 -> 0 | AY14: =+Precios!AX12*Precios!AX$3 -> 0 | AZ14: =+Precios!AY12*Precios!AY$3 -> 0 | BA14: =+Precios!AZ12*Precios!AZ$3 -> 0 | BB14: =+Precios!BA12*Precios!BA$3 -> 0 | BC14: =+Precios!BB12*Precios!BB$3 -> 0 | BD14: =+Precios!BC12*Precios!BC$3 -> 0 | ... BM14: =+Precios!BL12*Precios!BL$3 -> 0
A15: =+SUM(C15:XFD15) -> 0 | B15: =+Precios!A13 -> 45989 | C15: =+C14 -> 0 | D15: =+Precios!C13*Precios!C$3 -> 0 | E15: =+Precios!D13*Precios!D$3 -> 0 | F15: =+Precios!E13*Precios!E$3 -> 0 | G15: =+Precios!F13*Precios!F$3 -> 0 | H15: =+Precios!G13*Precios!G$3 -> 0 | I15: =+I14 -> 0 | J15: =+J14 -> 0 | K15: =+K14 -> 0 | L15: =+L14 -> 0 | M15: =+M14 -> 0 | N15: =+N14 -> 0 | O15: =+O14 -> 0 | P15: =+Precios!O13*Precios!O$3 -> 0 | Q15: =+Precios!P13*Precios!P$3 -> 0 | R15: =+R14 -> 0 | S15: =+S14 -> 0 | T15: =+Precios!S13*Precios!S$3 -> 0 | U15: =+Precios!T13*Precios!T$3 -> 0 | V15: =+Precios!U13*Precios!U$3 -> 0 | W15: =+Precios!V13*Precios!V$3 -> 0 | X15: =+Precios!W13*Precios!W$3 -> 0 | Y15: =+Precios!X13*Precios!X$3 -> 0 | Z15: =+Precios!Y13*Precios!Y$3 -> 0 | AA15: =+Precios!Z13*Precios!Z$3 -> 0 | AB15: =+AB14 -> 0 | AC15: =+AC14 -> 0 | AD15: =+AD14 -> 0 | AE15: =+Precios!AD13*Precios!AD$3 -> 0 | AF15: =+Precios!AE13*Precios!AE$3 -> 0 | AG15: =+Precios!AF13*Precios!AF$3 -> 0 | AH15: =+Precios!AG13*Precios!AG$3 -> 0 | AI15: =+Precios!AH13*Precios!AH$3 -> 0 | AJ15: =+Precios!AI13*Precios!AI$3 -> 0 | AK15: =+Precios!AJ13*Precios!AJ$3 -> 0 | AL15: =+Precios!AK13*Precios!AK$3 -> 0 | AM15: =+Precios!AL13*Precios!AL$3 -> 0 | AP15: =+Precios!AO13*Precios!AO$3 -> 0 | AQ15: =+Precios!AP13*Precios!AP$3 -> 0 | AR15: =+Precios!AQ13*Precios!AQ$3 -> 0 | AS15: =+Precios!AR13*Precios!AR$3 -> 0 | AT15: =+Precios!AS13*Precios!AS$3 -> 0 | AU15: =+Precios!AT13*Precios!AT$3 -> 0 | AW15: =+Precios!AV13*Precios!AV$3 -> 0 | AX15: =+Precios!AW13*Precios!AW$3 -> 0 | AY15: =+Precios!AX13*Precios!AX$3 -> 0 | AZ15: =+Precios!AY13*Precios!AY$3 -> 0 | BA15: =+Precios!AZ13*Precios!AZ$3 -> 0 | BB15: =+Precios!BA13*Precios!BA$3 -> 0 | BC15: =+Precios!BB13*Precios!BB$3 -> 0 | BD15: =+Precios!BC13*Precios!BC$3 -> 0 | ... BM15: =+Precios!BL13*Precios!BL$3 -> 0
A16: =+SUM(C16:XFD16) -> 0 | B16: =+Precios!A14 -> 45992 | C16: =+C15 -> 0 | D16: =+Precios!C14*Precios!C$3 -> 0 | E16: =+Precios!D14*Precios!D$3 -> 0 | F16: =+Precios!E14*Precios!E$3 -> 0 | G16: =+Precios!F14*Precios!F$3 -> 0 | H16: =+Precios!G14*Precios!G$3 -> 0 | I16: =+I15 -> 0 | J16: =+J15 -> 0 | K16: =+K15 -> 0 | L16: =+L15 -> 0 | M16: =+M15 -> 0 | N16: =+N15 -> 0 | O16: =+O15 -> 0 | P16: =+Precios!O14*Precios!O$3 -> 0 | Q16: =+Precios!P14*Precios!P$3 -> 0 | R16: =+R15 -> 0 | S16: =+S15 -> 0 | T16: =+Precios!S14*Precios!S$3 -> 0 | U16: =+Precios!T14*Precios!T$3 -> 0 | V16: =+Precios!U14*Precios!U$3 -> 0 | W16: =+Precios!V14*Precios!V$3 -> 0 | X16: =+Precios!W14*Precios!W$3 -> 0 | Y16: =+Precios!X14*Precios!X$3 -> 0 | Z16: =+Precios!Y14*Precios!Y$3 -> 0 | AA16: =+Precios!Z14*Precios!Z$3 -> 0 | AB16: =+AB15 -> 0 | AC16: =+AC15 -> 0 | AD16: =+AD15 -> 0 | AE16: =+Precios!AD14*Precios!AD$3 -> 0 | AF16: =+Precios!AE14*Precios!AE$3 -> 0 | AG16: =+Precios!AF14*Precios!AF$3 -> 0 | AH16: =+Precios!AG14*Precios!AG$3 -> 0 | AI16: =+Precios!AH14*Precios!AH$3 -> 0 | AJ16: =+Precios!AI14*Precios!AI$3 -> 0 | AK16: =+Precios!AJ14*Precios!AJ$3 -> 0 | AL16: =+Precios!AK14*Precios!AK$3 -> 0 | AM16: =+Precios!AL14*Precios!AL$3 -> 0 | AP16: =+Precios!AO14*Precios!AO$3 -> 0 | AQ16: =+Precios!AP14*Precios!AP$3 -> 0 | AR16: =+Precios!AQ14*Precios!AQ$3 -> 0 | AS16: =+Precios!AR14*Precios!AR$3 -> 0 | AT16: =+Precios!AS14*Precios!AS$3 -> 0 | AU16: =+Precios!AT14*Precios!AT$3 -> 0 | AW16: =+Precios!AV14*Precios!AV$3 -> 0 | AX16: =+Precios!AW14*Precios!AW$3 -> 0 | AY16: =+Precios!AX14*Precios!AX$3 -> 0 | AZ16: =+Precios!AY14*Precios!AY$3 -> 0 | BA16: =+Precios!AZ14*Precios!AZ$3 -> 0 | BB16: =+Precios!BA14*Precios!BA$3 -> 0 | BC16: =+Precios!BB14*Precios!BB$3 -> 0 | BD16: =+Precios!BC14*Precios!BC$3 -> 0 | ... BM16: =+Precios!BL14*Precios!BL$3 -> 0
A17: =+SUM(C17:XFD17) -> 0 | B17: =+Precios!A15 -> 45993 | C17: =+C16 -> 0 | D17: =+Precios!C15*Precios!C$3 -> 0 | E17: =+Precios!D15*Precios!D$3 -> 0 | F17: =+Precios!E15*Precios!E$3 -> 0 | G17: =+Precios!F15*Precios!F$3 -> 0 | H17: =+Precios!G15*Precios!G$3 -> 0 | I17: =+I16 -> 0 | J17: =+J16 -> 0 | K17: =+K16 -> 0 | L17: =+L16 -> 0 | M17: =+M16 -> 0 | N17: =+N16 -> 0 | O17: =+O16 -> 0 | P17: =+Precios!O15*Precios!O$3 -> 0 | Q17: =+Precios!P15*Precios!P$3 -> 0 | R17: =+R16 -> 0 | S17: =+S16 -> 0 | T17: =+Precios!S15*Precios!S$3 -> 0 | U17: =+Precios!T15*Precios!T$3 -> 0 | V17: =+Precios!U15*Precios!U$3 -> 0 | W17: =+Precios!V15*Precios!V$3 -> 0 | X17: =+Precios!W15*Precios!W$3 -> 0 | Y17: =+Precios!X15*Precios!X$3 -> 0 | Z17: =+Precios!Y15*Precios!Y$3 -> 0 | AA17: =+Precios!Z15*Precios!Z$3 -> 0 | AB17: =+AB16 -> 0 | AC17: =+AC16 -> 0 | AD17: =+AD16 -> 0 | AE17: =+Precios!AD15*Precios!AD$3 -> 0 | AF17: =+Precios!AE15*Precios!AE$3 -> 0 | AG17: =+Precios!AF15*Precios!AF$3 -> 0 | AH17: =+Precios!AG15*Precios!AG$3 -> 0 | AI17: =+Precios!AH15*Precios!AH$3 -> 0 | AJ17: =+Precios!AI15*Precios!AI$3 -> 0 | AK17: =+Precios!AJ15*Precios!AJ$3 -> 0 | AL17: =+Precios!AK15*Precios!AK$3 -> 0 | AM17: =+Precios!AL15*Precios!AL$3 -> 0 | AP17: =+Precios!AO15*Precios!AO$3 -> 0 | AQ17: =+Precios!AP15*Precios!AP$3 -> 0 | AR17: =+Precios!AQ15*Precios!AQ$3 -> 0 | AS17: =+Precios!AR15*Precios!AR$3 -> 0 | AT17: =+Precios!AS15*Precios!AS$3 -> 0 | AU17: =+Precios!AT15*Precios!AT$3 -> 0 | AW17: =+Precios!AV15*Precios!AV$3 -> 0 | AX17: =+Precios!AW15*Precios!AW$3 -> 0 | AY17: =+Precios!AX15*Precios!AX$3 -> 0 | AZ17: =+Precios!AY15*Precios!AY$3 -> 0 | BA17: =+Precios!AZ15*Precios!AZ$3 -> 0 | BB17: =+Precios!BA15*Precios!BA$3 -> 0 | BC17: =+Precios!BB15*Precios!BB$3 -> 0 | BD17: =+Precios!BC15*Precios!BC$3 -> 0 | ... BM17: =+Precios!BL15*Precios!BL$3 -> 0
A18: =+SUM(C18:XFD18) -> 0 | B18: =+Precios!A16 -> 45994 | C18: =+C17 -> 0 | D18: =+D17 -> 0 | E18: =+Precios!D16*Precios!D$3 -> 0 | F18: =+Precios!E16*Precios!E$3 -> 0 | G18: =+Precios!F16*Precios!F$3 -> 0 | H18: =+Precios!G16*Precios!G$3 -> 0 | I18: =+I17 -> 0 | J18: =+J17 -> 0 | K18: =+K17 -> 0 | L18: =+L17 -> 0 | M18: =+M17 -> 0 | N18: =+N17 -> 0 | O18: =+O17 -> 0 | P18: =+Precios!O16*Precios!O$3 -> 0 | Q18: =+Precios!P16*Precios!P$3 -> 0 | R18: =+R17 -> 0 | S18: =+S17 -> 0 | T18: =+Precios!S16*Precios!S$3 -> 0 | U18: =+Precios!T16*Precios!T$3 -> 0 | V18: =+Precios!U16*Precios!U$3 -> 0 | W18: =+Precios!V16*Precios!V$3 -> 0 | X18: =+Precios!W16*Precios!W$3 -> 0 | Y18: =+Precios!X16*Precios!X$3 -> 0 | Z18: =+Precios!Y16*Precios!Y$3 -> 0 | AA18: =+Precios!Z16*Precios!Z$3 -> 0 | AB18: =+AB17 -> 0 | AC18: =+AC17 -> 0 | AD18: =+AD17 -> 0 | AE18: =+Precios!AD16*Precios!AD$3 -> 0 | AF18: =+Precios!AE16*Precios!AE$3 -> 0 | AG18: =+Precios!AF16*Precios!AF$3 -> 0 | AH18: =+Precios!AG16*Precios!AG$3 -> 0 | AI18: =+Precios!AH16*Precios!AH$3 -> 0 | AJ18: =+Precios!AI16*Precios!AI$3 -> 0 | AK18: =+Precios!AJ16*Precios!AJ$3 -> 0 | AL18: =+Precios!AK16*Precios!AK$3 -> 0 | AM18: =+Precios!AL16*Precios!AL$3 -> 0 | AP18: =+Precios!AO16*Precios!AO$3 -> 0 | AQ18: =+Precios!AP16*Precios!AP$3 -> 0 | AR18: =+Precios!AQ16*Precios!AQ$3 -> 0 | AS18: =+Precios!AR16*Precios!AR$3 -> 0 | AT18: =+Precios!AS16*Precios!AS$3 -> 0 | AU18: =+Precios!AT16*Precios!AT$3 -> 0 | AW18: =+Precios!AV16*Precios!AV$3 -> 0 | AX18: =+Precios!AW16*Precios!AW$3 -> 0 | AY18: =+Precios!AX16*Precios!AX$3 -> 0 | AZ18: =+Precios!AY16*Precios!AY$3 -> 0 | BA18: =+Precios!AZ16*Precios!AZ$3 -> 0 | BB18: =+Precios!BA16*Precios!BA$3 -> 0 | BC18: =+Precios!BB16*Precios!BB$3 -> 0 | BD18: =+Precios!BC16*Precios!BC$3 -> 0 | ... BM18: =+Precios!BL16*Precios!BL$3 -> 0
A19: =+SUM(C19:XFD19) -> 0 | B19: =+Precios!A17 -> 45995 | C19: =+C18 -> 0 | D19: =+D18 -> 0 | E19: =+Precios!D17*Precios!D$3 -> 0 | F19: =+Precios!E17*Precios!E$3 -> 0 | G19: =+Precios!F17*Precios!F$3 -> 0 | H19: =+Precios!G17*Precios!G$3 -> 0 | I19: =+I18 -> 0 | J19: =+J18 -> 0 | K19: =+K18 -> 0 | L19: =+L18 -> 0 | M19: =+M18 -> 0 | N19: =+N18 -> 0 | O19: =+O18 -> 0 | P19: =+Precios!O17*Precios!O$3 -> 0 | Q19: =+Precios!P17*Precios!P$3 -> 0 | R19: =+R18 -> 0 | S19: =+S18 -> 0 | T19: =+Precios!S17*Precios!S$3 -> 0 | U19: =+Precios!T17*Precios!T$3 -> 0 | V19: =+Precios!U17*Precios!U$3 -> 0 | W19: =+Precios!V17*Precios!V$3 -> 0 | X19: =+Precios!W17*Precios!W$3 -> 0 | Y19: =+Precios!X17*Precios!X$3 -> 0 | Z19: =+Precios!Y17*Precios!Y$3 -> 0 | AA19: =+Precios!Z17*Precios!Z$3 -> 0 | AB19: =+AB18 -> 0 | AC19: =+AC18 -> 0 | AD19: =+AD18 -> 0 | AE19: =+Precios!AD17*Precios!AD$3 -> 0 | AF19: =+Precios!AE17*Precios!AE$3 -> 0 | AG19: =+Precios!AF17*Precios!AF$3 -> 0 | AH19: =+Precios!AG17*Precios!AG$3 -> 0 | AI19: =+Precios!AH17*Precios!AH$3 -> 0 | AJ19: =+Precios!AI17*Precios!AI$3 -> 0 | AK19: =+Precios!AJ17*Precios!AJ$3 -> 0 | AL19: =+Precios!AK17*Precios!AK$3 -> 0 | AM19: =+Precios!AL17*Precios!AL$3 -> 0 | AP19: =+Precios!AO17*Precios!AO$3 -> 0 | AQ19: =+Precios!AP17*Precios!AP$3 -> 0 | AR19: =+Precios!AQ17*Precios!AQ$3 -> 0 | AS19: =+Precios!AR17*Precios!AR$3 -> 0 | AT19: =+Precios!AS17*Precios!AS$3 -> 0 | AU19: =+Precios!AT17*Precios!AT$3 -> 0 | AW19: =+Precios!AV17*Precios!AV$3 -> 0 | AX19: =+Precios!AW17*Precios!AW$3 -> 0 | AY19: =+Precios!AX17*Precios!AX$3 -> 0 | AZ19: =+Precios!AY17*Precios!AY$3 -> 0 | BA19: =+Precios!AZ17*Precios!AZ$3 -> 0 | BB19: =+Precios!BA17*Precios!BA$3 -> 0 | BC19: =+Precios!BB17*Precios!BB$3 -> 0 | BD19: =+Precios!BC17*Precios!BC$3 -> 0 | ... BM19: =+Precios!BL17*Precios!BL$3 -> 0
A20: =+SUM(C20:XFD20) -> 0 | B20: =+Precios!A18 -> 45996 | C20: =+Precios!B18*Precios!B$3 -> 0 | D20: =+Precios!C18*Precios!C$3 -> 0 | E20: =+Precios!D18*Precios!D$3 -> 0 | F20: =+Precios!E18*Precios!E$3 -> 0 | G20: =+Precios!F18*Precios!F$3 -> 0 | H20: =+Precios!G18*Precios!G$3 -> 0 | I20: =+I19 -> 0 | J20: =+J19 -> 0 | K20: =+K19 -> 0 | L20: =+L19 -> 0 | M20: =+M19 -> 0 | N20: =+N19 -> 0 | O20: =+O19 -> 0 | P20: =+Precios!O18*Precios!O$3 -> 0 | Q20: =+Precios!P18*Precios!P$3 -> 0 | R20: =+R19 -> 0 | S20: =+S19 -> 0 | T20: =+Precios!S18*Precios!S$3 -> 0 | U20: =+Precios!T18*Precios!T$3 -> 0 | V20: =+Precios!U18*Precios!U$3 -> 0 | W20: =+Precios!V18*Precios!V$3 -> 0 | X20: =+Precios!W18*Precios!W$3 -> 0 | Y20: =+Precios!X18*Precios!X$3 -> 0 | Z20: =+Precios!Y18*Precios!Y$3 -> 0 | AA20: =+Precios!Z18*Precios!Z$3 -> 0 | AB20: =+AB19 -> 0 | AC20: =+AC19 -> 0 | AD20: =+AD19 -> 0 | AE20: =+Precios!AD18*Precios!AD$3 -> 0 | AF20: =+Precios!AE18*Precios!AE$3 -> 0 | AG20: =+Precios!AF18*Precios!AF$3 -> 0 | AH20: =+Precios!AG18*Precios!AG$3 -> 0 | AI20: =+Precios!AH18*Precios!AH$3 -> 0 | AJ20: =+Precios!AI18*Precios!AI$3 -> 0 | AK20: =+Precios!AJ18*Precios!AJ$3 -> 0 | AL20: =+Precios!AK18*Precios!AK$3 -> 0 | AM20: =+Precios!AL18*Precios!AL$3 -> 0 | AP20: =+Precios!AO18*Precios!AO$3 -> 0 | AQ20: =+Precios!AP18*Precios!AP$3 -> 0 | AR20: =+Precios!AQ18*Precios!AQ$3 -> 0 | AS20: =+Precios!AR18*Precios!AR$3 -> 0 | AT20: =+Precios!AS18*Precios!AS$3 -> 0 | AU20: =+Precios!AT18*Precios!AT$3 -> 0 | AW20: =+Precios!AV18*Precios!AV$3 -> 0 | AX20: =+Precios!AW18*Precios!AW$3 -> 0 | AY20: =+Precios!AX18*Precios!AX$3 -> 0 | AZ20: =+Precios!AY18*Precios!AY$3 -> 0 | BA20: =+Precios!AZ18*Precios!AZ$3 -> 0 | BB20: =+Precios!BA18*Precios!BA$3 -> 0 | BC20: =+Precios!BB18*Precios!BB$3 -> 0 | BD20: =+Precios!BC18*Precios!BC$3 -> 0 | ... BM20: =+Precios!BL18*Precios!BL$3 -> 0
A21: =+SUM(C21:XFD21) -> 0 | B21: =+Precios!A19 -> 45999 | C21: =+Precios!B19*Precios!B$3 -> 0 | D21: =+Precios!C19*Precios!C$3 -> 0 | E21: =+Precios!D19*Precios!D$3 -> 0 | F21: =+Precios!E19*Precios!E$3 -> 0 | G21: =+Precios!F19*Precios!F$3 -> 0 | H21: =+Precios!G19*Precios!G$3 -> 0 | I21: =+I20 -> 0 | J21: =+J20 -> 0 | K21: =+K20 -> 0 | L21: =+L20 -> 0 | M21: =+M20 -> 0 | N21: =+N20 -> 0 | O21: =+O20 -> 0 | P21: =+Precios!O19*Precios!O$3 -> 0 | Q21: =+Precios!P19*Precios!P$3 -> 0 | R21: =+R20 -> 0 | S21: =+S20 -> 0 | T21: =+Precios!S19*Precios!S$3 -> 0 | U21: =+Precios!T19*Precios!T$3 -> 0 | V21: =+Precios!U19*Precios!U$3 -> 0 | W21: =+Precios!V19*Precios!V$3 -> 0 | X21: =+Precios!W19*Precios!W$3 -> 0 | Y21: =+Precios!X19*Precios!X$3 -> 0 | Z21: =+Precios!Y19*Precios!Y$3 -> 0 | AA21: =+Precios!Z19*Precios!Z$3 -> 0 | AB21: =+AB20 -> 0 | AC21: =+AC20 -> 0 | AD21: =+AD20 -> 0 | AE21: =+Precios!AD19*Precios!AD$3 -> 0 | AF21: =+Precios!AE19*Precios!AE$3 -> 0 | AG21: =+Precios!AF19*Precios!AF$3 -> 0 | AH21: =+Precios!AG19*Precios!AG$3 -> 0 | AI21: =+Precios!AH19*Precios!AH$3 -> 0 | AJ21: =+Precios!AI19*Precios!AI$3 -> 0 | AK21: =+Precios!AJ19*Precios!AJ$3 -> 0 | AL21: =+Precios!AK19*Precios!AK$3 -> 0 | AM21: =+Precios!AL19*Precios!AL$3 -> 0 | AP21: =+Precios!AO19*Precios!AO$3 -> 0 | AQ21: =+Precios!AP19*Precios!AP$3 -> 0 | AR21: =+Precios!AQ19*Precios!AQ$3 -> 0 | AS21: =+Precios!AR19*Precios!AR$3 -> 0 | AT21: =+Precios!AS19*Precios!AS$3 -> 0 | AU21: =+Precios!AT19*Precios!AT$3 -> 0 | AW21: =+Precios!AV19*Precios!AV$3 -> 0 | AX21: =+Precios!AW19*Precios!AW$3 -> 0 | AY21: =+Precios!AX19*Precios!AX$3 -> 0 | AZ21: =+Precios!AY19*Precios!AY$3 -> 0 | BA21: =+Precios!AZ19*Precios!AZ$3 -> 0 | BB21: =+Precios!BA19*Precios!BA$3 -> 0 | BC21: =+Precios!BB19*Precios!BB$3 -> 0 | BD21: =+Precios!BC19*Precios!BC$3 -> 0 | ... BM21: =+Precios!BL19*Precios!BL$3 -> 0
A22: =+SUM(C22:XFD22) -> 0 | B22: =+Precios!A20 -> 46000 | C22: =+Precios!B20*Precios!B$3 -> 0 | D22: =+Precios!C20*Precios!C$3 -> 0 | E22: =+Precios!D20*Precios!D$3 -> 0 | F22: =+Precios!E20*Precios!E$3 -> 0 | G22: =+Precios!F20*Precios!F$3 -> 0 | H22: =+Precios!G20*Precios!G$3 -> 0 | I22: =+I21 -> 0 | J22: =+J21 -> 0 | K22: =+K21 -> 0 | L22: =+L21 -> 0 | M22: =+M21 -> 0 | N22: =+N21 -> 0 | O22: =+O21 -> 0 | P22: =+Precios!O20*Precios!O$3 -> 0 | Q22: =+Precios!P20*Precios!P$3 -> 0 | R22: =+R21 -> 0 | S22: =+S21 -> 0 | T22: =+Precios!S20*Precios!S$3 -> 0 | U22: =+Precios!T20*Precios!T$3 -> 0 | V22: =+Precios!U20*Precios!U$3 -> 0 | W22: =+Precios!V20*Precios!V$3 -> 0 | X22: =+Precios!W20*Precios!W$3 -> 0 | Y22: =+Precios!X20*Precios!X$3 -> 0 | Z22: =+Precios!Y20*Precios!Y$3 -> 0 | AA22: =+Precios!Z20*Precios!Z$3 -> 0 | AB22: =+AB21 -> 0 | AC22: =+AC21 -> 0 | AD22: =+AD21 -> 0 | AE22: =+Precios!AD20*Precios!AD$3 -> 0 | AF22: =+Precios!AE20*Precios!AE$3 -> 0 | AG22: =+Precios!AF20*Precios!AF$3 -> 0 | AH22: =+Precios!AG20*Precios!AG$3 -> 0 | AI22: =+Precios!AH20*Precios!AH$3 -> 0 | AJ22: =+Precios!AI20*Precios!AI$3 -> 0 | AK22: =+Precios!AJ20*Precios!AJ$3 -> 0 | AL22: =+Precios!AK20*Precios!AK$3 -> 0 | AM22: =+Precios!AL20*Precios!AL$3 -> 0 | AP22: =+Precios!AO20*Precios!AO$3 -> 0 | AQ22: =+Precios!AP20*Precios!AP$3 -> 0 | AR22: =+Precios!AQ20*Precios!AQ$3 -> 0 | AS22: =+Precios!AR20*Precios!AR$3 -> 0 | AT22: =+Precios!AS20*Precios!AS$3 -> 0 | AU22: =+Precios!AT20*Precios!AT$3 -> 0 | AW22: =+Precios!AV20*Precios!AV$3 -> 0 | AX22: =+Precios!AW20*Precios!AW$3 -> 0 | AY22: =+Precios!AX20*Precios!AX$3 -> 0 | AZ22: =+Precios!AY20*Precios!AY$3 -> 0 | BA22: =+Precios!AZ20*Precios!AZ$3 -> 0 | BB22: =+Precios!BA20*Precios!BA$3 -> 0 | BC22: =+Precios!BB20*Precios!BB$3 -> 0 | BD22: =+Precios!BC20*Precios!BC$3 -> 0 | ... BM22: =+Precios!BL20*Precios!BL$3 -> 0
A23: =+SUM(C23:XFD23) -> 0 | B23: =+Precios!A21 -> 46001 | C23: =+Precios!B21*Precios!B$3 -> 0 | D23: =+Precios!C21*Precios!C$3 -> 0 | E23: =+Precios!D21*Precios!D$3 -> 0 | F23: =+Precios!E21*Precios!E$3 -> 0 | G23: =+Precios!F21*Precios!F$3 -> 0 | H23: =+H22 -> 0 | I23: =+I22 -> 0 | J23: =+J22 -> 0 | K23: =+K22 -> 0 | L23: =+L22 -> 0 | M23: =+M22 -> 0 | N23: =+N22 -> 0 | O23: =+O22 -> 0 | P23: =+Precios!O21*Precios!O$3 -> 0 | Q23: =+Precios!P21*Precios!P$3 -> 0 | R23: =+R22 -> 0 | S23: =+S22 -> 0 | T23: =+Precios!S21*Precios!S$3 -> 0 | U23: =+Precios!T21*Precios!T$3 -> 0 | V23: =+Precios!U21*Precios!U$3 -> 0 | W23: =+Precios!V21*Precios!V$3 -> 0 | X23: =+Precios!W21*Precios!W$3 -> 0 | Y23: =+Precios!X21*Precios!X$3 -> 0 | Z23: =+Precios!Y21*Precios!Y$3 -> 0 | AA23: =+Precios!Z21*Precios!Z$3 -> 0 | AB23: =+AB22 -> 0 | AC23: =+AC22 -> 0 | AD23: =+AD22 -> 0 | AE23: =+Precios!AD21*Precios!AD$3 -> 0 | AF23: =+Precios!AE21*Precios!AE$3 -> 0 | AG23: =+Precios!AF21*Precios!AF$3 -> 0 | AH23: =+Precios!AG21*Precios!AG$3 -> 0 | AI23: =+Precios!AH21*Precios!AH$3 -> 0 | AJ23: =+Precios!AI21*Precios!AI$3 -> 0 | AK23: =+Precios!AJ21*Precios!AJ$3 -> 0 | AL23: =+Precios!AK21*Precios!AK$3 -> 0 | AM23: =+Precios!AL21*Precios!AL$3 -> 0 | AP23: =+Precios!AO21*Precios!AO$3 -> 0 | AQ23: =+Precios!AP21*Precios!AP$3 -> 0 | AR23: =+Precios!AQ21*Precios!AQ$3 -> 0 | AS23: =+Precios!AR21*Precios!AR$3 -> 0 | AT23: =+Precios!AS21*Precios!AS$3 -> 0 | AU23: =+Precios!AT21*Precios!AT$3 -> 0 | AW23: =+Precios!AV21*Precios!AV$3 -> 0 | AX23: =+Precios!AW21*Precios!AW$3 -> 0 | AY23: =+Precios!AX21*Precios!AX$3 -> 0 | AZ23: =+Precios!AY21*Precios!AY$3 -> 0 | BA23: =+Precios!AZ21*Precios!AZ$3 -> 0 | BB23: =+Precios!BA21*Precios!BA$3 -> 0 | BC23: =+Precios!BB21*Precios!BB$3 -> 0 | BD23: =+Precios!BC21*Precios!BC$3 -> 0 | ... BM23: =+Precios!BL21*Precios!BL$3 -> 0
A24: =+SUM(C24:XFD24) -> 0 | B24: =+Precios!A22 -> 46002 | C24: =+Precios!B22*Precios!B$3 -> 0 | D24: =+Precios!C22*Precios!C$3 -> 0 | E24: =+E23 -> 0 | F24: =+Precios!E22*Precios!E$3 -> 0 | G24: =+Precios!F22*Precios!F$3 -> 0 | H24: =+H23 -> 0 | I24: =+I23 -> 0 | J24: =+J23 -> 0 | K24: =+K23 -> 0 | L24: =+L23 -> 0 | M24: =+M23 -> 0 | N24: =+N23 -> 0 | O24: =+O23 -> 0 | P24: =+Precios!O22*Precios!O$3 -> 0 | Q24: =+Precios!P22*Precios!P$3 -> 0 | R24: =+R23 -> 0 | S24: =+S23 -> 0 | T24: =+Precios!S22*Precios!S$3 -> 0 | U24: =+Precios!T22*Precios!T$3 -> 0 | V24: =+Precios!U22*Precios!U$3 -> 0 | W24: =+Precios!V22*Precios!V$3 -> 0 | X24: =+Precios!W22*Precios!W$3 -> 0 | Y24: =+Precios!X22*Precios!X$3 -> 0 | Z24: =+Precios!Y22*Precios!Y$3 -> 0 | AA24: =+Precios!Z22*Precios!Z$3 -> 0 | AB24: =+AB23 -> 0 | AC24: =+AC23 -> 0 | AD24: =+AD23 -> 0 | AE24: =+AE23 -> 0 | AF24: =+Precios!AE22*Precios!AE$3 -> 0 | AG24: =+Precios!AF22*Precios!AF$3 -> 0 | AH24: =+Precios!AG22*Precios!AG$3 -> 0 | AI24: =+Precios!AH22*Precios!AH$3 -> 0 | AJ24: =+Precios!AI22*Precios!AI$3 -> 0 | AK24: =+Precios!AJ22*Precios!AJ$3 -> 0 | AL24: =+Precios!AK22*Precios!AK$3 -> 0 | AM24: =+Precios!AL22*Precios!AL$3 -> 0 | AP24: =+Precios!AO22*Precios!AO$3 -> 0 | AQ24: =+Precios!AP22*Precios!AP$3 -> 0 | AR24: =+Precios!AQ22*Precios!AQ$3 -> 0 | AS24: =+Precios!AR22*Precios!AR$3 -> 0 | AT24: =+Precios!AS22*Precios!AS$3 -> 0 | AU24: =+Precios!AT22*Precios!AT$3 -> 0 | AW24: =+Precios!AV22*Precios!AV$3 -> 0 | AX24: =+Precios!AW22*Precios!AW$3 -> 0 | AY24: =+Precios!AX22*Precios!AX$3 -> 0 | AZ24: =+Precios!AY22*Precios!AY$3 -> 0 | BA24: =+Precios!AZ22*Precios!AZ$3 -> 0 | BB24: =+Precios!BA22*Precios!BA$3 -> 0 | BC24: =+Precios!BB22*Precios!BB$3 -> 0 | BD24: =+Precios!BC22*Precios!BC$3 -> 0 | ... BM24: =+Precios!BL22*Precios!BL$3 -> 0
A25: =+SUM(C25:XFD25) -> 0 | B25: =+Precios!A23 -> 46003 | C25: =+Precios!B23*Precios!B$3 -> 0 | D25: =+Precios!C23*Precios!C$3 -> 0 | E25: =+E24 -> 0 | F25: =+Precios!E23*Precios!E$3 -> 0 | G25: =+G24 -> 0 | H25: =+H24 -> 0 | I25: =+I24 -> 0 | J25: =+J24 -> 0 | K25: =+K24 -> 0 | L25: =+L24 -> 0 | M25: =+M24 -> 0 | N25: =+N24 -> 0 | O25: =+O24 -> 0 | P25: =+Precios!O23*Precios!O$3 -> 0 | Q25: =+Precios!P23*Precios!P$3 -> 0 | R25: =+R24 -> 0 | S25: =+S24 -> 0 | T25: =+Precios!S23*Precios!S$3 -> 0 | U25: =+Precios!T23*Precios!T$3 -> 0 | V25: =+V24 -> 0 | W25: =+Precios!V23*Precios!V$3 -> 0 | X25: =+Precios!W23*Precios!W$3 -> 0 | Y25: =+Precios!X23*Precios!X$3 -> 0 | Z25: =+Precios!Y23*Precios!Y$3 -> 0 | AA25: =+Precios!Z23*Precios!Z$3 -> 0 | AB25: =+AB24 -> 0 | AC25: =+AC24 -> 0 | AD25: =+AD24 -> 0 | AE25: =+AE24 -> 0 | AF25: =+AF24 -> 0 | AG25: =+AG24 -> 0 | AH25: =+Precios!AG23*Precios!AG$3 -> 0 | AI25: =+Precios!AH23*Precios!AH$3 -> 0 | AJ25: =+Precios!AI23*Precios!AI$3 -> 0 | AK25: =+Precios!AJ23*Precios!AJ$3 -> 0 | AL25: =+Precios!AK23*Precios!AK$3 -> 0 | AM25: =+Precios!AL23*Precios!AL$3 -> 0 | AP25: =+Precios!AO23*Precios!AO$3 -> 0 | AQ25: =+Precios!AP23*Precios!AP$3 -> 0 | AR25: =+Precios!AQ23*Precios!AQ$3 -> 0 | AS25: =+Precios!AR23*Precios!AR$3 -> 0 | AT25: =+Precios!AS23*Precios!AS$3 -> 0 | AU25: =+Precios!AT23*Precios!AT$3 -> 0 | AW25: =+Precios!AV23*Precios!AV$3 -> 0 | AX25: =+Precios!AW23*Precios!AW$3 -> 0 | AY25: =+Precios!AX23*Precios!AX$3 -> 0 | AZ25: =+Precios!AY23*Precios!AY$3 -> 0 | BA25: =+Precios!AZ23*Precios!AZ$3 -> 0 | BB25: =+Precios!BA23*Precios!BA$3 -> 0 | BC25: =+Precios!BB23*Precios!BB$3 -> 0 | BD25: =+Precios!BC23*Precios!BC$3 -> 0 | ... BM25: =+Precios!BL23*Precios!BL$3 -> 0
A26: =+SUM(C26:XFD26) -> 0 | B26: =+Precios!A24 -> 46006 | C26: =+Precios!B24*Precios!B$3 -> 0 | D26: =+Precios!C24*Precios!C$3 -> 0 | E26: =+Precios!D24*Precios!D$3 -> 0 | F26: =+Precios!E24*Precios!E$3 -> 0 | G26: =+Precios!F24*Precios!F$3 -> 0 | H26: =+Precios!G24*Precios!G$3 -> 0 | I26: =+I25 -> 0 | J26: =+J25 -> 0 | K26: =+K25 -> 0 | L26: =+L25 -> 0 | M26: =+M25 -> 0 | N26: =+N25 -> 0 | O26: =+O25 -> 0 | P26: =+Precios!O24*Precios!O$3 -> 0 | Q26: =+Precios!P24*Precios!P$3 -> 0 | R26: =+R25 -> 0 | S26: =+S25 -> 0 | T26: =+Precios!S24*Precios!S$3 -> 0 | U26: =+Precios!T24*Precios!T$3 -> 0 | V26: =+V25 -> 0 | W26: =+Precios!V24*Precios!V$3 -> 0 | X26: =+Precios!W24*Precios!W$3 -> 0 | Y26: =+Precios!X24*Precios!X$3 -> 0 | Z26: =+Precios!Y24*Precios!Y$3 -> 0 | AA26: =+Precios!Z24*Precios!Z$3 -> 0 | AB26: =+AB25 -> 0 | AC26: =+AC25 -> 0 | AD26: =+AD25 -> 0 | AE26: =+AE25 -> 0 | AF26: =+AF25 -> 0 | AG26: =+AG25 -> 0 | AH26: =+Precios!AG24*Precios!AG$3 -> 0 | AI26: =+Precios!AH24*Precios!AH$3 -> 0 | AJ26: =+Precios!AI24*Precios!AI$3 -> 0 | AK26: =+Precios!AJ24*Precios!AJ$3 -> 0 | AL26: =+Precios!AK24*Precios!AK$3 -> 0 | AM26: =+Precios!AL24*Precios!AL$3 -> 0 | AP26: =+Precios!AO24*Precios!AO$3 -> 0 | AQ26: =+Precios!AP24*Precios!AP$3 -> 0 | AR26: =+Precios!AQ24*Precios!AQ$3 -> 0 | AS26: =+Precios!AR24*Precios!AR$3 -> 0 | AT26: =+Precios!AS24*Precios!AS$3 -> 0 | AU26: =+Precios!AT24*Precios!AT$3 -> 0 | AW26: =+Precios!AV24*Precios!AV$3 -> 0 | AX26: =+Precios!AW24*Precios!AW$3 -> 0 | AY26: =+Precios!AX24*Precios!AX$3 -> 0 | AZ26: =+Precios!AY24*Precios!AY$3 -> 0 | BA26: =+Precios!AZ24*Precios!AZ$3 -> 0 | BB26: =+Precios!BA24*Precios!BA$3 -> 0 | BC26: =+Precios!BB24*Precios!BB$3 -> 0 | BD26: =+Precios!BC24*Precios!BC$3 -> 0 | ... BM26: =+Precios!BL24*Precios!BL$3 -> 0
A27: =+SUM(C27:XFD27) -> 0 | B27: =+Precios!A25 -> 46007 | C27: =+Precios!B25*Precios!B$3 -> 0 | D27: =+Precios!C25*Precios!C$3 -> 0 | E27: =+Precios!D25*Precios!D$3 -> 0 | F27: =+Precios!E25*Precios!E$3 -> 0 | G27: =+Precios!F25*Precios!F$3 -> 0 | H27: =+Precios!G25*Precios!G$3 -> 0 | I27: =+Precios!H25*Precios!H$3 -> 0 | J27: =+Precios!I25*Precios!I$3 -> 0 | K27: =+K26 -> 0 | L27: =+L26 -> 0 | M27: =+M26 -> 0 | N27: =+N26 -> 0 | O27: =+O26 -> 0 | P27: =+P26 -> 0 | Q27: =+Precios!P25*Precios!P$3 -> 0 | R27: =+R26 -> 0 | S27: =+S26 -> 0 | T27: =+Precios!S25*Precios!S$3 -> 0 | U27: =+Precios!T25*Precios!T$3 -> 0 | V27: =+V26 -> 0 | W27: =+Precios!V25*Precios!V$3 -> 0 | X27: =+Precios!W25*Precios!W$3 -> 0 | Y27: =+Precios!X25*Precios!X$3 -> 0 | Z27: =+Precios!Y25*Precios!Y$3 -> 0 | AA27: =+Precios!Z25*Precios!Z$3 -> 0 | AB27: =+AB26 -> 0 | AC27: =+AC26 -> 0 | AD27: =+AD26 -> 0 | AE27: =+AE26 -> 0 | AF27: =+AF26 -> 0 | AG27: =+AG26 -> 0 | AH27: =+Precios!AG25*Precios!AG$3 -> 0 | AI27: =+Precios!AH25*Precios!AH$3 -> 0 | AJ27: =+Precios!AI25*Precios!AI$3 -> 0 | AK27: =+Precios!AJ25*Precios!AJ$3 -> 0 | AL27: =+Precios!AK25*Precios!AK$3 -> 0 | AM27: =+Precios!AL25*Precios!AL$3 -> 0 | AP27: =+Precios!AO25*Precios!AO$3 -> 0 | AQ27: =+Precios!AP25*Precios!AP$3 -> 0 | AR27: =+Precios!AQ25*Precios!AQ$3 -> 0 | AS27: =+Precios!AR25*Precios!AR$3 -> 0 | AT27: =+Precios!AS25*Precios!AS$3 -> 0 | AU27: =+Precios!AT25*Precios!AT$3 -> 0 | AW27: =+Precios!AV25*Precios!AV$3 -> 0 | AX27: =+Precios!AW25*Precios!AW$3 -> 0 | AY27: =+Precios!AX25*Precios!AX$3 -> 0 | AZ27: =+Precios!AY25*Precios!AY$3 -> 0 | BA27: =+Precios!AZ25*Precios!AZ$3 -> 0 | BB27: =+Precios!BA25*Precios!BA$3 -> 0 | BC27: =+Precios!BB25*Precios!BB$3 -> 0 | BD27: =+Precios!BC25*Precios!BC$3 -> 0 | ... BM27: =+Precios!BL25*Precios!BL$3 -> 0
A28: =+SUM(C28:XFD28) -> 0 | B28: =+Precios!A26 -> 46008 | C28: =+Precios!B26*Precios!B$3 -> 0 | D28: =+Precios!C26*Precios!C$3 -> 0 | E28: =+Precios!D26*Precios!D$3 -> 0 | F28: =+Precios!E26*Precios!E$3 -> 0 | G28: =+Precios!F26*Precios!F$3 -> 0 | H28: =+Precios!G26*Precios!G$3 -> 0 | I28: =+Precios!H26*Precios!H$3 -> 0 | J28: =+Precios!I26*Precios!I$3 -> 0 | ... M28: =+Precios!L26*Precios!L$3 -> 0 | N28: =+N27 -> 0 | O28: =+O27 -> 0 | P28: =+P27 -> 0 | Q28: =+Precios!P26*Precios!P$3 -> 0 | R28: =+R27 -> 0 | S28: =+S27 -> 0 | T28: =+Precios!S26*Precios!S$3 -> 0 | U28: =+Precios!T26*Precios!T$3 -> 0 | V28: =+V27 -> 0 | W28: =+Precios!V26*Precios!V$3 -> 0 | X28: =+Precios!W26*Precios!W$3 -> 0 | Y28: =+Precios!X26*Precios!X$3 -> 0 | Z28: =+Precios!Y26*Precios!Y$3 -> 0 | AA28: =+Precios!Z26*Precios!Z$3 -> 0 | AB28: =+AB27 -> 0 | AC28: =+AC27 -> 0 | AD28: =+AD27 -> 0 | AE28: =+AE27 -> 0 | AF28: =+AF27 -> 0 | AG28: =+AG27 -> 0 | AH28: =+Precios!AG26*Precios!AG$3 -> 0 | AI28: =+Precios!AH26*Precios!AH$3 -> 0 | AJ28: =+Precios!AI26*Precios!AI$3 -> 0 | AK28: =+Precios!AJ26*Precios!AJ$3 -> 0 | AL28: =+Precios!AK26*Precios!AK$3 -> 0 | AM28: =+Precios!AL26*Precios!AL$3 -> 0 | AP28: =+Precios!AO26*Precios!AO$3 -> 0 | AQ28: =+Precios!AP26*Precios!AP$3 -> 0 | AR28: =+Precios!AQ26*Precios!AQ$3 -> 0 | AS28: =+Precios!AR26*Precios!AR$3 -> 0 | AT28: =+Precios!AS26*Precios!AS$3 -> 0 | AU28: =+Precios!AT26*Precios!AT$3 -> 0 | AW28: =+Precios!AV26*Precios!AV$3 -> 0 | AX28: =+Precios!AW26*Precios!AW$3 -> 0 | AY28: =+Precios!AX26*Precios!AX$3 -> 0 | AZ28: =+Precios!AY26*Precios!AY$3 -> 0 | BA28: =+Precios!AZ26*Precios!AZ$3 -> 0 | BB28: =+Precios!BA26*Precios!BA$3 -> 0 | BC28: =+Precios!BB26*Precios!BB$3 -> 0 | BD28: =+Precios!BC26*Precios!BC$3 -> 0 | ... BM28: =+Precios!BL26*Precios!BL$3 -> 0
A29: =+SUM(C29:XFD29) -> 0 | B29: =+Precios!A27 -> 46009 | C29: =+Precios!B27*Precios!B$3 -> 0 | D29: =+Precios!C27*Precios!C$3 -> 0 | E29: =+Precios!D27*Precios!D$3 -> 0 | F29: =+Precios!E27*Precios!E$3 -> 0 | G29: =+Precios!F27*Precios!F$3 -> 0 | H29: =+Precios!G27*Precios!G$3 -> 0 | I29: =+Precios!H27*Precios!H$3 -> 0 | J29: =+Precios!I27*Precios!I$3 -> 0 | ... O29: =+Precios!N27*Precios!N$3 -> 0 | P29: =+P28 -> 0 | Q29: =+Precios!P27*Precios!P$3 -> 0 | R29: =+R28 -> 0 | S29: =+S28 -> 0 | T29: =+T28 -> 0 | U29: =+Precios!T27*Precios!T$3 -> 0 | V29: =+V28 -> 0 | W29: =+Precios!V27*Precios!V$3 -> 0 | X29: =+Precios!W27*Precios!W$3 -> 0 | Y29: =+Precios!X27*Precios!X$3 -> 0 | Z29: =+Precios!Y27*Precios!Y$3 -> 0 | AA29: =+Precios!Z27*Precios!Z$3 -> 0 | AB29: =+AB28 -> 0 | AC29: =+AC28 -> 0 | AD29: =+AD28 -> 0 | AE29: =+AE28 -> 0 | AF29: =+AF28 -> 0 | AG29: =+AG28 -> 0 | AH29: =+Precios!AG27*Precios!AG$3 -> 0 | AI29: =+Precios!AH27*Precios!AH$3 -> 0 | AJ29: =+Precios!AI27*Precios!AI$3 -> 0 | AK29: =+Precios!AJ27*Precios!AJ$3 -> 0 | AL29: =+Precios!AK27*Precios!AK$3 -> 0 | AM29: =+Precios!AL27*Precios!AL$3 -> 0 | AP29: =+Precios!AO27*Precios!AO$3 -> 0 | AQ29: =+Precios!AP27*Precios!AP$3 -> 0 | AR29: =+Precios!AQ27*Precios!AQ$3 -> 0 | AS29: =+Precios!AR27*Precios!AR$3 -> 0 | AT29: =+Precios!AS27*Precios!AS$3 -> 0 | AU29: =+Precios!AT27*Precios!AT$3 -> 0 | AW29: =+Precios!AV27*Precios!AV$3 -> 0 | AX29: =+Precios!AW27*Precios!AW$3 -> 0 | AY29: =+Precios!AX27*Precios!AX$3 -> 0 | AZ29: =+Precios!AY27*Precios!AY$3 -> 0 | BA29: =+Precios!AZ27*Precios!AZ$3 -> 0 | BB29: =+Precios!BA27*Precios!BA$3 -> 0 | BC29: =+Precios!BB27*Precios!BB$3 -> 0 | BD29: =+Precios!BC27*Precios!BC$3 -> 0 | ... BM29: =+Precios!BL27*Precios!BL$3 -> 0
A30: =+SUM(C30:XFD30) -> 0 | B30: =+Precios!A28 -> 46010 | C30: =+Precios!B28*Precios!B$3 -> 0 | D30: =+Precios!C28*Precios!C$3 -> 0 | E30: =+Precios!D28*Precios!D$3 -> 0 | F30: =+Precios!E28*Precios!E$3 -> 0 | G30: =+Precios!F28*Precios!F$3 -> 0 | H30: =+Precios!G28*Precios!G$3 -> 0 | I30: =+Precios!H28*Precios!H$3 -> 0 | J30: =+Precios!I28*Precios!I$3 -> 0 | ... O30: =+Precios!N28*Precios!N$3 -> 0 | P30: =+P29 -> 0 | Q30: =+Q29 -> 0 | R30: =+R29 -> 0 | S30: =+S29 -> 0 | T30: =+T29 -> 0 | U30: =+Precios!T28*Precios!T$3 -> 0 | V30: =+V29 -> 0 | W30: =+Precios!V28*Precios!V$3 -> 0 | X30: =+Precios!W28*Precios!W$3 -> 0 | Y30: =+Precios!X28*Precios!X$3 -> 0 | Z30: =+Precios!Y28*Precios!Y$3 -> 0 | AA30: =+Precios!Z28*Precios!Z$3 -> 0 | AB30: =+AB29 -> 0 | AC30: =+AC29 -> 0 | AD30: =+AD29 -> 0 | AE30: =+AE29 -> 0 | AF30: =+AF29 -> 0 | AG30: =+AG29 -> 0 | AH30: =+Precios!AG28*Precios!AG$3 -> 0 | AI30: =+Precios!AH28*Precios!AH$3 -> 0 | AJ30: =+Precios!AI28*Precios!AI$3 -> 0 | AK30: =+Precios!AJ28*Precios!AJ$3 -> 0 | AL30: =+Precios!AK28*Precios!AK$3 -> 0 | AM30: =+Precios!AL28*Precios!AL$3 -> 0 | AP30: =+Precios!AO28*Precios!AO$3 -> 0 | AQ30: =+Precios!AP28*Precios!AP$3 -> 0 | AR30: =+Precios!AQ28*Precios!AQ$3 -> 0 | AS30: =+Precios!AR28*Precios!AR$3 -> 0 | AT30: =+Precios!AS28*Precios!AS$3 -> 0 | AU30: =+Precios!AT28*Precios!AT$3 -> 0 | AW30: =+Precios!AV28*Precios!AV$3 -> 0 | AX30: =+Precios!AW28*Precios!AW$3 -> 0 | AY30: =+Precios!AX28*Precios!AX$3 -> 0 | AZ30: =+Precios!AY28*Precios!AY$3 -> 0 | BA30: =+Precios!AZ28*Precios!AZ$3 -> 0 | BB30: =+Precios!BA28*Precios!BA$3 -> 0 | BC30: =+Precios!BB28*Precios!BB$3 -> 0 | BD30: =+Precios!BC28*Precios!BC$3 -> 0 | ... BM30: =+Precios!BL28*Precios!BL$3 -> 0
A31: =+SUM(C31:XFD31) -> 0 | B31: =+Precios!A29 -> 46013 | C31: =+Precios!B29*Precios!B$3 -> 0 | D31: =+Precios!C29*Precios!C$3 -> 0 | E31: =+Precios!D29*Precios!D$3 -> 0 | F31: =+Precios!E29*Precios!E$3 -> 0 | G31: =+Precios!F29*Precios!F$3 -> 0 | H31: =+Precios!G29*Precios!G$3 -> 0 | I31: =+Precios!H29*Precios!H$3 -> 0 | J31: =+Precios!I29*Precios!I$3 -> 0 | ... O31: =+Precios!N29*Precios!N$3 -> 0 | P31: =+P30 -> 0 | Q31: =+Q30 -> 0 | R31: =+R30 -> 0 | S31: =+S30 -> 0 | T31: =+T30 -> 0 | U31: =+Precios!T29*Precios!T$3 -> 0 | V31: =+V30 -> 0 | W31: =+Precios!V29*Precios!V$3 -> 0 | X31: =+Precios!W29*Precios!W$3 -> 0 | Y31: =+Precios!X29*Precios!X$3 -> 0 | Z31: =+Precios!Y29*Precios!Y$3 -> 0 | AA31: =+Precios!Z29*Precios!Z$3 -> 0 | AB31: =+AB30 -> 0 | AC31: =+AC30 -> 0 | AD31: =+AD30 -> 0 | AE31: =+AE30 -> 0 | AF31: =+AF30 -> 0 | AG31: =+AG30 -> 0 | AH31: =+Precios!AG29*Precios!AG$3 -> 0 | AI31: =+Precios!AH29*Precios!AH$3 -> 0 | AJ31: =+Precios!AI29*Precios!AI$3 -> 0 | AK31: =+Precios!AJ29*Precios!AJ$3 -> 0 | AL31: =+Precios!AK29*Precios!AK$3 -> 0 | AM31: =+Precios!AL29*Precios!AL$3 -> 0 | AP31: =+Precios!AO29*Precios!AO$3 -> 0 | AQ31: =+Precios!AP29*Precios!AP$3 -> 0 | AR31: =+Precios!AQ29*Precios!AQ$3 -> 0 | AS31: =+Precios!AR29*Precios!AR$3 -> 0 | AT31: =+Precios!AS29*Precios!AS$3 -> 0 | AU31: =+Precios!AT29*Precios!AT$3 -> 0 | AW31: =+Precios!AV29*Precios!AV$3 -> 0 | AX31: =+Precios!AW29*Precios!AW$3 -> 0 | AY31: =+Precios!AX29*Precios!AX$3 -> 0 | AZ31: =+Precios!AY29*Precios!AY$3 -> 0 | BA31: =+Precios!AZ29*Precios!AZ$3 -> 0 | BB31: =+Precios!BA29*Precios!BA$3 -> 0 | BC31: =+Precios!BB29*Precios!BB$3 -> 0 | BD31: =+Precios!BC29*Precios!BC$3 -> 0 | ... BM31: =+Precios!BL29*Precios!BL$3 -> 0
A32: =+SUM(C32:XFD32) -> 0 | B32: =+Precios!A30 -> 46014 | C32: =+Precios!B30*Precios!B$3 -> 0 | D32: =+Precios!C30*Precios!C$3 -> 0 | E32: =+Precios!D30*Precios!D$3 -> 0 | F32: =+Precios!E30*Precios!E$3 -> 0 | G32: =+Precios!F30*Precios!F$3 -> 0 | H32: =+Precios!G30*Precios!G$3 -> 0 | I32: =+Precios!H30*Precios!H$3 -> 0 | J32: =+Precios!I30*Precios!I$3 -> 0 | ... O32: =+Precios!N30*Precios!N$3 -> 0 | P32: =+P31 -> 0 | Q32: =+Q31 -> 0 | R32: =+R31 -> 0 | S32: =+S31 -> 0 | T32: =+T31 -> 0 | U32: =+Precios!T30*Precios!T$3 -> 0 | V32: =+V31 -> 0 | W32: =+Precios!V30*Precios!V$3 -> 0 | X32: =+Precios!W30*Precios!W$3 -> 0 | Y32: =+Precios!X30*Precios!X$3 -> 0 | Z32: =+Precios!Y30*Precios!Y$3 -> 0 | AA32: =+Precios!Z30*Precios!Z$3 -> 0 | AB32: =+AB31 -> 0 | AC32: =+AC31 -> 0 | AD32: =+AD31 -> 0 | AE32: =+AE31 -> 0 | AF32: =+AF31 -> 0 | AG32: =+AG31 -> 0 | AH32: =+Precios!AG30*Precios!AG$3 -> 0 | AI32: =+Precios!AH30*Precios!AH$3 -> 0 | AJ32: =+Precios!AI30*Precios!AI$3 -> 0 | AK32: =+Precios!AJ30*Precios!AJ$3 -> 0 | AL32: =+Precios!AK30*Precios!AK$3 -> 0 | AM32: =+Precios!AL30*Precios!AL$3 -> 0 | AP32: =+Precios!AO30*Precios!AO$3 -> 0 | AQ32: =+Precios!AP30*Precios!AP$3 -> 0 | AR32: =+Precios!AQ30*Precios!AQ$3 -> 0 | AS32: =+Precios!AR30*Precios!AR$3 -> 0 | AT32: =+Precios!AS30*Precios!AS$3 -> 0 | AU32: =+Precios!AT30*Precios!AT$3 -> 0 | AW32: =+Precios!AV30*Precios!AV$3 -> 0 | AX32: =+Precios!AW30*Precios!AW$3 -> 0 | AY32: =+Precios!AX30*Precios!AX$3 -> 0 | AZ32: =+Precios!AY30*Precios!AY$3 -> 0 | BA32: =+Precios!AZ30*Precios!AZ$3 -> 0 | BB32: =+Precios!BA30*Precios!BA$3 -> 0 | BC32: =+Precios!BB30*Precios!BB$3 -> 0 | BD32: =+Precios!BC30*Precios!BC$3 -> 0 | ... BM32: =+Precios!BL30*Precios!BL$3 -> 0
A33: =+SUM(C33:XFD33) -> 0 | B33: =+Precios!A31 -> 46015 | C33: =+Precios!B31*Precios!B$3 -> 0 | D33: =+Precios!C31*Precios!C$3 -> 0 | E33: =+Precios!D31*Precios!D$3 -> 0 | F33: =+Precios!E31*Precios!E$3 -> 0 | G33: =+Precios!F31*Precios!F$3 -> 0 | H33: =+Precios!G31*Precios!G$3 -> 0 | I33: =+Precios!H31*Precios!H$3 -> 0 | J33: =+Precios!I31*Precios!I$3 -> 0 | ... O33: =+Precios!N31*Precios!N$3 -> 0 | P33: =+P32 -> 0 | Q33: =+Q32 -> 0 | R33: =+R32 -> 0 | S33: =+S32 -> 0 | T33: =+T32 -> 0 | U33: =+Precios!T31*Precios!T$3 -> 0 | V33: =+V32 -> 0 | W33: =+Precios!V31*Precios!V$3 -> 0 | X33: =+Precios!W31*Precios!W$3 -> 0 | Y33: =+Precios!X31*Precios!X$3 -> 0 | Z33: =+Precios!Y31*Precios!Y$3 -> 0 | AA33: =+Precios!Z31*Precios!Z$3 -> 0 | AB33: =+AB32 -> 0 | AC33: =+AC32 -> 0 | AD33: =+AD32 -> 0 | AE33: =+AE32 -> 0 | AF33: =+AF32 -> 0 | AG33: =+AG32 -> 0 | AH33: =+Precios!AG31*Precios!AG$3 -> 0 | AI33: =+Precios!AH31*Precios!AH$3 -> 0 | AJ33: =+Precios!AI31*Precios!AI$3 -> 0 | AK33: =+Precios!AJ31*Precios!AJ$3 -> 0 | AL33: =+Precios!AK31*Precios!AK$3 -> 0 | AM33: =+Precios!AL31*Precios!AL$3 -> 0 | AP33: =+Precios!AO31*Precios!AO$3 -> 0 | AQ33: =+Precios!AP31*Precios!AP$3 -> 0 | AR33: =+Precios!AQ31*Precios!AQ$3 -> 0 | AS33: =+Precios!AR31*Precios!AR$3 -> 0 | AT33: =+Precios!AS31*Precios!AS$3 -> 0 | AU33: =+Precios!AT31*Precios!AT$3 -> 0 | AW33: =+Precios!AV31*Precios!AV$3 -> 0 | AX33: =+Precios!AW31*Precios!AW$3 -> 0 | AY33: =+Precios!AX31*Precios!AX$3 -> 0 | AZ33: =+Precios!AY31*Precios!AY$3 -> 0 | BA33: =+Precios!AZ31*Precios!AZ$3 -> 0 | BB33: =+Precios!BA31*Precios!BA$3 -> 0 | BC33: =+Precios!BB31*Precios!BB$3 -> 0 | BD33: =+Precios!BC31*Precios!BC$3 -> 0 | ... BM33: =+Precios!BL31*Precios!BL$3 -> 0
A34: =+SUM(C34:XFD34) -> 0 | B34: =+Precios!A32 -> 46016 | C34: =+Precios!B32*Precios!B$3 -> 0 | D34: =+Precios!C32*Precios!C$3 -> 0 | E34: =+Precios!D32*Precios!D$3 -> 0 | F34: =+Precios!E32*Precios!E$3 -> 0 | G34: =+Precios!F32*Precios!F$3 -> 0 | H34: =+Precios!G32*Precios!G$3 -> 0 | I34: =+Precios!H32*Precios!H$3 -> 0 | J34: =+Precios!I32*Precios!I$3 -> 0 | ... O34: =+Precios!N32*Precios!N$3 -> 0 | P34: =+P33 -> 0 | Q34: =+Q33 -> 0 | R34: =+R33 -> 0 | S34: =+S33 -> 0 | T34: =+T33 -> 0 | U34: =+Precios!T32*Precios!T$3 -> 0 | V34: =+V33 -> 0 | W34: =+Precios!V32*Precios!V$3 -> 0 | X34: =+Precios!W32*Precios!W$3 -> 0 | Y34: =+Precios!X32*Precios!X$3 -> 0 | Z34: =+Precios!Y32*Precios!Y$3 -> 0 | AA34: =+Precios!Z32*Precios!Z$3 -> 0 | AB34: =+AB33 -> 0 | AC34: =+AC33 -> 0 | AD34: =+AD33 -> 0 | AE34: =+AE33 -> 0 | AF34: =+AF33 -> 0 | AG34: =+AG33 -> 0 | AH34: =+Precios!AG32*Precios!AG$3 -> 0 | AI34: =+Precios!AH32*Precios!AH$3 -> 0 | AJ34: =+Precios!AI32*Precios!AI$3 -> 0 | AK34: =+Precios!AJ32*Precios!AJ$3 -> 0 | AL34: =+Precios!AK32*Precios!AK$3 -> 0 | AM34: =+Precios!AL32*Precios!AL$3 -> 0 | AP34: =+Precios!AO32*Precios!AO$3 -> 0 | AQ34: =+Precios!AP32*Precios!AP$3 -> 0 | AR34: =+Precios!AQ32*Precios!AQ$3 -> 0 | AS34: =+Precios!AR32*Precios!AR$3 -> 0 | AT34: =+Precios!AS32*Precios!AS$3 -> 0 | AU34: =+Precios!AT32*Precios!AT$3 -> 0 | AW34: =+Precios!AV32*Precios!AV$3 -> 0 | AX34: =+Precios!AW32*Precios!AW$3 -> 0 | AY34: =+Precios!AX32*Precios!AX$3 -> 0 | AZ34: =+Precios!AY32*Precios!AY$3 -> 0 | BA34: =+Precios!AZ32*Precios!AZ$3 -> 0 | BB34: =+Precios!BA32*Precios!BA$3 -> 0 | BC34: =+Precios!BB32*Precios!BB$3 -> 0 | BD34: =+Precios!BC32*Precios!BC$3 -> 0 | ... BM34: =+Precios!BL32*Precios!BL$3 -> 0
A35: =+SUM(C35:XFD35) -> 0 | B35: =+Precios!A33 -> 46017 | C35: =+Precios!B33*Precios!B$3 -> 0 | D35: =+Precios!C33*Precios!C$3 -> 0 | E35: =+Precios!D33*Precios!D$3 -> 0 | F35: =+Precios!E33*Precios!E$3 -> 0 | G35: =+Precios!F33*Precios!F$3 -> 0 | H35: =+Precios!G33*Precios!G$3 -> 0 | I35: =+Precios!H33*Precios!H$3 -> 0 | J35: =+Precios!I33*Precios!I$3 -> 0 | ... O35: =+Precios!N33*Precios!N$3 -> 0 | P35: =+P34 -> 0 | Q35: =+Q34 -> 0 | R35: =+R34 -> 0 | S35: =+S34 -> 0 | T35: =+T34 -> 0 | U35: =+Precios!T33*Precios!T$3 -> 0 | V35: =+V34 -> 0 | W35: =+Precios!V33*Precios!V$3 -> 0 | X35: =+Precios!W33*Precios!W$3 -> 0 | Y35: =+Precios!X33*Precios!X$3 -> 0 | Z35: =+Precios!Y33*Precios!Y$3 -> 0 | AA35: =+Precios!Z33*Precios!Z$3 -> 0 | AB35: =+AB34 -> 0 | AC35: =+AC34 -> 0 | AD35: =+AD34 -> 0 | AE35: =+AE34 -> 0 | AF35: =+AF34 -> 0 | AG35: =+AG34 -> 0 | AH35: =+Precios!AG33*Precios!AG$3 -> 0 | AI35: =+Precios!AH33*Precios!AH$3 -> 0 | AJ35: =+Precios!AI33*Precios!AI$3 -> 0 | AK35: =+Precios!AJ33*Precios!AJ$3 -> 0 | AL35: =+Precios!AK33*Precios!AK$3 -> 0 | AM35: =+Precios!AL33*Precios!AL$3 -> 0 | AP35: =+Precios!AO33*Precios!AO$3 -> 0 | AQ35: =+Precios!AP33*Precios!AP$3 -> 0 | AR35: =+Precios!AQ33*Precios!AQ$3 -> 0 | AS35: =+Precios!AR33*Precios!AR$3 -> 0 | AT35: =+Precios!AS33*Precios!AS$3 -> 0 | AU35: =+Precios!AT33*Precios!AT$3 -> 0 | AW35: =+Precios!AV33*Precios!AV$3 -> 0 | AX35: =+Precios!AW33*Precios!AW$3 -> 0 | AY35: =+Precios!AX33*Precios!AX$3 -> 0 | AZ35: =+Precios!AY33*Precios!AY$3 -> 0 | BA35: =+Precios!AZ33*Precios!AZ$3 -> 0 | BB35: =+Precios!BA33*Precios!BA$3 -> 0 | BC35: =+Precios!BB33*Precios!BB$3 -> 0 | BD35: =+Precios!BC33*Precios!BC$3 -> 0 | ... BM35: =+Precios!BL33*Precios!BL$3 -> 0
A36: =+SUM(C36:XFD36) -> 0 | B36: =+Precios!A34 -> 46020 | C36: =+Precios!B34*Precios!B$3 -> 0 | D36: =+Precios!C34*Precios!C$3 -> 0 | E36: =+Precios!D34*Precios!D$3 -> 0 | F36: =+Precios!E34*Precios!E$3 -> 0 | G36: =+Precios!F34*Precios!F$3 -> 0 | H36: =+Precios!G34*Precios!G$3 -> 0 | I36: =+Precios!H34*Precios!H$3 -> 0 | J36: =+Precios!I34*Precios!I$3 -> 0 | ... O36: =+Precios!N34*Precios!N$3 -> 0 | P36: =+P35 -> 0 | Q36: =+Q35 -> 0 | R36: =+R35 -> 0 | S36: =+S35 -> 0 | T36: =+T35 -> 0 | U36: =+Precios!T34*Precios!T$3 -> 0 | V36: =+V35 -> 0 | W36: =+Precios!V34*Precios!V$3 -> 0 | X36: =+Precios!W34*Precios!W$3 -> 0 | Y36: =+Precios!X34*Precios!X$3 -> 0 | Z36: =+Precios!Y34*Precios!Y$3 -> 0 | AA36: =+Precios!Z34*Precios!Z$3 -> 0 | AB36: =+AB35 -> 0 | AC36: =+AC35 -> 0 | AD36: =+AD35 -> 0 | AE36: =+AE35 -> 0 | AF36: =+AF35 -> 0 | AG36: =+AG35 -> 0 | AH36: =+Precios!AG34*Precios!AG$3 -> 0 | AI36: =+Precios!AH34*Precios!AH$3 -> 0 | AJ36: =+Precios!AI34*Precios!AI$3 -> 0 | AK36: =+Precios!AJ34*Precios!AJ$3 -> 0 | AL36: =+Precios!AK34*Precios!AK$3 -> 0 | AM36: =+Precios!AL34*Precios!AL$3 -> 0 | AP36: =+Precios!AO34*Precios!AO$3 -> 0 | AQ36: =+Precios!AP34*Precios!AP$3 -> 0 | AR36: =+Precios!AQ34*Precios!AQ$3 -> 0 | AS36: =+Precios!AR34*Precios!AR$3 -> 0 | AT36: =+Precios!AS34*Precios!AS$3 -> 0 | AU36: =+Precios!AT34*Precios!AT$3 -> 0 | AW36: =+Precios!AV34*Precios!AV$3 -> 0 | AX36: =+Precios!AW34*Precios!AW$3 -> 0 | AY36: =+Precios!AX34*Precios!AX$3 -> 0 | AZ36: =+Precios!AY34*Precios!AY$3 -> 0 | BA36: =+Precios!AZ34*Precios!AZ$3 -> 0 | BB36: =+Precios!BA34*Precios!BA$3 -> 0 | BC36: =+Precios!BB34*Precios!BB$3 -> 0 | BD36: =+Precios!BC34*Precios!BC$3 -> 0 | ... BM36: =+Precios!BL34*Precios!BL$3 -> 0
A37: =+SUM(C37:XFD37) -> 0 | B37: =+Precios!A35 -> 46021 | C37: =+Precios!B35*Precios!B$3 -> 0 | D37: =+Precios!C35*Precios!C$3 -> 0 | E37: =+Precios!D35*Precios!D$3 -> 0 | F37: =+Precios!E35*Precios!E$3 -> 0 | G37: =+Precios!F35*Precios!F$3 -> 0 | H37: =+Precios!G35*Precios!G$3 -> 0 | I37: =+Precios!H35*Precios!H$3 -> 0 | J37: =+Precios!I35*Precios!I$3 -> 0 | ... O37: =+Precios!N35*Precios!N$3 -> 0 | P37: =+P36 -> 0 | Q37: =+Q36 -> 0 | R37: =+R36 -> 0 | S37: =+S36 -> 0 | T37: =+T36 -> 0 | U37: =+Precios!T35*Precios!T$3 -> 0 | V37: =+V36 -> 0 | W37: =+Precios!V35*Precios!V$3 -> 0 | X37: =+Precios!W35*Precios!W$3 -> 0 | Y37: =+Precios!X35*Precios!X$3 -> 0 | Z37: =+Precios!Y35*Precios!Y$3 -> 0 | AA37: =+Precios!Z35*Precios!Z$3 -> 0 | AB37: =+AB36 -> 0 | AC37: =+AC36 -> 0 | AD37: =+AD36 -> 0 | AE37: =+AE36 -> 0 | AF37: =+AF36 -> 0 | AG37: =+AG36 -> 0 | AH37: =+Precios!AG35*Precios!AG$3 -> 0 | AI37: =+Precios!AH35*Precios!AH$3 -> 0 | AJ37: =+Precios!AI35*Precios!AI$3 -> 0 | AK37: =+Precios!AJ35*Precios!AJ$3 -> 0 | AL37: =+Precios!AK35*Precios!AK$3 -> 0 | AM37: =+Precios!AL35*Precios!AL$3 -> 0 | AP37: =+Precios!AO35*Precios!AO$3 -> 0 | AQ37: =+Precios!AP35*Precios!AP$3 -> 0 | AR37: =+Precios!AQ35*Precios!AQ$3 -> 0 | AS37: =+Precios!AR35*Precios!AR$3 -> 0 | AT37: =+Precios!AS35*Precios!AS$3 -> 0 | AU37: =+Precios!AT35*Precios!AT$3 -> 0 | AW37: =+Precios!AV35*Precios!AV$3 -> 0 | AX37: =+Precios!AW35*Precios!AW$3 -> 0 | AY37: =+Precios!AX35*Precios!AX$3 -> 0 | AZ37: =+Precios!AY35*Precios!AY$3 -> 0 | BA37: =+Precios!AZ35*Precios!AZ$3 -> 0 | BB37: =+Precios!BA35*Precios!BA$3 -> 0 | BC37: =+Precios!BB35*Precios!BB$3 -> 0 | BD37: =+Precios!BC35*Precios!BC$3 -> 0 | ... BM37: =+Precios!BL35*Precios!BL$3 -> 0
A38: =+SUM(C38:XFD38) -> 0 | B38: =+Precios!A36 -> 46022 | C38: =+Precios!B36*Precios!B$3 -> 0 | D38: =+Precios!C36*Precios!C$3 -> 0 | E38: =+Precios!D36*Precios!D$3 -> 0 | F38: =+Precios!E36*Precios!E$3 -> 0 | G38: =+Precios!F36*Precios!F$3 -> 0 | H38: =+Precios!G36*Precios!G$3 -> 0 | I38: =+Precios!H36*Precios!H$3 -> 0 | J38: =+Precios!I36*Precios!I$3 -> 0 | ... O38: =+Precios!N36*Precios!N$3 -> 0 | P38: =+P37 -> 0 | Q38: =+Q37 -> 0 | R38: =+R37 -> 0 | S38: =+S37 -> 0 | T38: =+T37 -> 0 | U38: =+Precios!T36*Precios!T$3 -> 0 | V38: =+V37 -> 0 | W38: =+Precios!V36*Precios!V$3 -> 0 | X38: =+Precios!W36*Precios!W$3 -> 0 | Y38: =+Precios!X36*Precios!X$3 -> 0 | Z38: =+Precios!Y36*Precios!Y$3 -> 0 | AA38: =+Precios!Z36*Precios!Z$3 -> 0 | AB38: =+AB37 -> 0 | AC38: =+AC37 -> 0 | AD38: =+AD37 -> 0 | AE38: =+AE37 -> 0 | AF38: =+AF37 -> 0 | AG38: =+AG37 -> 0 | AH38: =+Precios!AG36*Precios!AG$3 -> 0 | AI38: =+Precios!AH36*Precios!AH$3 -> 0 | AJ38: =+Precios!AI36*Precios!AI$3 -> 0 | AK38: =+Precios!AJ36*Precios!AJ$3 -> 0 | AL38: =+Precios!AK36*Precios!AK$3 -> 0 | AM38: =+Precios!AL36*Precios!AL$3 -> 0 | AP38: =+Precios!AO36*Precios!AO$3 -> 0 | AQ38: =+Precios!AP36*Precios!AP$3 -> 0 | AR38: =+Precios!AQ36*Precios!AQ$3 -> 0 | AS38: =+Precios!AR36*Precios!AR$3 -> 0 | AT38: =+Precios!AS36*Precios!AS$3 -> 0 | AU38: =+Precios!AT36*Precios!AT$3 -> 0 | AW38: =+Precios!AV36*Precios!AV$3 -> 0 | AX38: =+Precios!AW36*Precios!AW$3 -> 0 | AY38: =+Precios!AX36*Precios!AX$3 -> 0 | AZ38: =+Precios!AY36*Precios!AY$3 -> 0 | BA38: =+Precios!AZ36*Precios!AZ$3 -> 0 | BB38: =+Precios!BA36*Precios!BA$3 -> 0 | BC38: =+Precios!BB36*Precios!BB$3 -> 0 | BD38: =+Precios!BC36*Precios!BC$3 -> 0 | ... BM38: =+Precios!BL36*Precios!BL$3 -> 0
A39: =+SUM(C39:XFD39) -> 0 | B39: =+Precios!A37 -> 46023 | C39: =+Precios!B37*Precios!B$3 -> 0 | D39: =+Precios!C37*Precios!C$3 -> 0 | E39: =+Precios!D37*Precios!D$3 -> 0 | F39: =+Precios!E37*Precios!E$3 -> 0 | G39: =+Precios!F37*Precios!F$3 -> 0 | H39: =+Precios!G37*Precios!G$3 -> 0 | I39: =+Precios!H37*Precios!H$3 -> 0 | J39: =+Precios!I37*Precios!I$3 -> 0 | ... O39: =+Precios!N37*Precios!N$3 -> 0 | P39: =+P38 -> 0 | Q39: =+Q38 -> 0 | R39: =+R38 -> 0 | S39: =+S38 -> 0 | T39: =+T38 -> 0 | U39: =+Precios!T37*Precios!T$3 -> 0 | V39: =+V38 -> 0 | W39: =+Precios!V37*Precios!V$3 -> 0 | X39: =+Precios!W37*Precios!W$3 -> 0 | Y39: =+Precios!X37*Precios!X$3 -> 0 | Z39: =+Precios!Y37*Precios!Y$3 -> 0 | AA39: =+Precios!Z37*Precios!Z$3 -> 0 | AB39: =+AB38 -> 0 | AC39: =+AC38 -> 0 | AD39: =+AD38 -> 0 | AE39: =+AE38 -> 0 | AF39: =+AF38 -> 0 | AG39: =+AG38 -> 0 | AH39: =+Precios!AG37*Precios!AG$3 -> 0 | AI39: =+Precios!AH37*Precios!AH$3 -> 0 | AJ39: =+Precios!AI37*Precios!AI$3 -> 0 | AK39: =+Precios!AJ37*Precios!AJ$3 -> 0 | AL39: =+Precios!AK37*Precios!AK$3 -> 0 | AM39: =+Precios!AL37*Precios!AL$3 -> 0 | AP39: =+Precios!AO37*Precios!AO$3 -> 0 | AQ39: =+Precios!AP37*Precios!AP$3 -> 0 | AR39: =+Precios!AQ37*Precios!AQ$3 -> 0 | AS39: =+Precios!AR37*Precios!AR$3 -> 0 | AT39: =+Precios!AS37*Precios!AS$3 -> 0 | AU39: =+Precios!AT37*Precios!AT$3 -> 0 | AW39: =+Precios!AV37*Precios!AV$3 -> 0 | AX39: =+Precios!AW37*Precios!AW$3 -> 0 | AY39: =+Precios!AX37*Precios!AX$3 -> 0 | AZ39: =+Precios!AY37*Precios!AY$3 -> 0 | BA39: =+Precios!AZ37*Precios!AZ$3 -> 0 | BB39: =+Precios!BA37*Precios!BA$3 -> 0 | BC39: =+Precios!BB37*Precios!BB$3 -> 0 | BD39: =+Precios!BC37*Precios!BC$3 -> 0 | ... BM39: =+Precios!BL37*Precios!BL$3 -> 0
A40: =+SUM(C40:XFD40) -> 0 | B40: =+Precios!A38 -> 46024 | C40: =+Precios!B38*Precios!B$3 -> 0 | D40: =+Precios!C38*Precios!C$3 -> 0 | E40: =+Precios!D38*Precios!D$3 -> 0 | F40: =+Precios!E38*Precios!E$3 -> 0 | G40: =+Precios!F38*Precios!F$3 -> 0 | H40: =+Precios!G38*Precios!G$3 -> 0 | I40: =+Precios!H38*Precios!H$3 -> 0 | J40: =+Precios!I38*Precios!I$3 -> 0 | ... O40: =+Precios!N38*Precios!N$3 -> 0 | P40: =+P39 -> 0 | Q40: =+Q39 -> 0 | R40: =+R39 -> 0 | S40: =+S39 -> 0 | T40: =+T39 -> 0 | U40: =+Precios!T38*Precios!T$3 -> 0 | V40: =+V39 -> 0 | W40: =+Precios!V38*Precios!V$3 -> 0 | X40: =+Precios!W38*Precios!W$3 -> 0 | Y40: =+Precios!X38*Precios!X$3 -> 0 | Z40: =+Precios!Y38*Precios!Y$3 -> 0 | AA40: =+Precios!Z38*Precios!Z$3 -> 0 | AB40: =+AB39 -> 0 | AC40: =+AC39 -> 0 | AD40: =+AD39 -> 0 | AE40: =+AE39 -> 0 | AF40: =+AF39 -> 0 | AG40: =+AG39 -> 0 | AH40: =+Precios!AG38*Precios!AG$3 -> 0 | AI40: =+Precios!AH38*Precios!AH$3 -> 0 | AJ40: =+Precios!AI38*Precios!AI$3 -> 0 | AK40: =+Precios!AJ38*Precios!AJ$3 -> 0 | AL40: =+Precios!AK38*Precios!AK$3 -> 0 | AM40: =+Precios!AL38*Precios!AL$3 -> 0 | AP40: =+Precios!AO38*Precios!AO$3 -> 0 | AQ40: =+Precios!AP38*Precios!AP$3 -> 0 | AR40: =+Precios!AQ38*Precios!AQ$3 -> 0 | AS40: =+Precios!AR38*Precios!AR$3 -> 0 | AT40: =+Precios!AS38*Precios!AS$3 -> 0 | AU40: =+Precios!AT38*Precios!AT$3 -> 0 | AW40: =+Precios!AV38*Precios!AV$3 -> 0 | AX40: =+Precios!AW38*Precios!AW$3 -> 0 | AY40: =+Precios!AX38*Precios!AX$3 -> 0 | AZ40: =+Precios!AY38*Precios!AY$3 -> 0 | BA40: =+Precios!AZ38*Precios!AZ$3 -> 0 | BB40: =+Precios!BA38*Precios!BA$3 -> 0 | BC40: =+Precios!BB38*Precios!BB$3 -> 0 | BD40: =+Precios!BC38*Precios!BC$3 -> 0 | ... BM40: =+Precios!BL38*Precios!BL$3 -> 0
A41: =+SUM(C41:XFD41) -> 0 | B41: =+Precios!A39 -> 46027 | C41: =+Precios!B39*Precios!B$3 -> 0 | D41: =+Precios!C39*Precios!C$3 -> 0 | E41: =+Precios!D39*Precios!D$3 -> 0 | F41: =+Precios!E39*Precios!E$3 -> 0 | G41: =+Precios!F39*Precios!F$3 -> 0 | H41: =+Precios!G39*Precios!G$3 -> 0 | I41: =+Precios!H39*Precios!H$3 -> 0 | J41: =+Precios!I39*Precios!I$3 -> 0 | ... P41: =+Precios!O39*Precios!O$3 -> 0 | Q41: =+Q40 -> 0 | R41: =+R40 -> 0 | S41: =+S40 -> 0 | T41: =+T40 -> 0 | U41: =+Precios!T39*Precios!T$3 -> 0 | V41: =+V40 -> 0 | W41: =+Precios!V39*Precios!V$3 -> 0 | X41: =+Precios!W39*Precios!W$3 -> 0 | Y41: =+Precios!X39*Precios!X$3 -> 0 | Z41: =+Precios!Y39*Precios!Y$3 -> 0 | AA41: =+Precios!Z39*Precios!Z$3 -> 0 | AB41: =+AB40 -> 0 | AC41: =+AC40 -> 0 | AD41: =+AD40 -> 0 | AE41: =+AE40 -> 0 | AF41: =+AF40 -> 0 | AG41: =+AG40 -> 0 | AH41: =+Precios!AG39*Precios!AG$3 -> 0 | AI41: =+Precios!AH39*Precios!AH$3 -> 0 | AJ41: =+Precios!AI39*Precios!AI$3 -> 0 | AK41: =+Precios!AJ39*Precios!AJ$3 -> 0 | AL41: =+Precios!AK39*Precios!AK$3 -> 0 | AM41: =+Precios!AL39*Precios!AL$3 -> 0 | AP41: =+Precios!AO39*Precios!AO$3 -> 0 | AQ41: =+Precios!AP39*Precios!AP$3 -> 0 | AR41: =+Precios!AQ39*Precios!AQ$3 -> 0 | AS41: =+Precios!AR39*Precios!AR$3 -> 0 | AT41: =+Precios!AS39*Precios!AS$3 -> 0 | AU41: =+Precios!AT39*Precios!AT$3 -> 0 | AW41: =+Precios!AV39*Precios!AV$3 -> 0 | AX41: =+Precios!AW39*Precios!AW$3 -> 0 | AY41: =+Precios!AX39*Precios!AX$3 -> 0 | AZ41: =+Precios!AY39*Precios!AY$3 -> 0 | BA41: =+Precios!AZ39*Precios!AZ$3 -> 0 | BB41: =+Precios!BA39*Precios!BA$3 -> 0 | BC41: =+Precios!BB39*Precios!BB$3 -> 0 | BD41: =+Precios!BC39*Precios!BC$3 -> 0 | ... BM41: =+Precios!BL39*Precios!BL$3 -> 0
A42: =+SUM(C42:XFD42) -> 0 | B42: =+Precios!A40 -> 46028 | C42: =+Precios!B40*Precios!B$3 -> 0 | D42: =+Precios!C40*Precios!C$3 -> 0 | E42: =+Precios!D40*Precios!D$3 -> 0 | F42: =+Precios!E40*Precios!E$3 -> 0 | G42: =+Precios!F40*Precios!F$3 -> 0 | H42: =+Precios!G40*Precios!G$3 -> 0 | I42: =+Precios!H40*Precios!H$3 -> 0 | J42: =+Precios!I40*Precios!I$3 -> 0 | ... P42: =+Precios!O40*Precios!O$3 -> 0 | Q42: =+Q41 -> 0 | R42: =+R41 -> 0 | S42: =+S41 -> 0 | T42: =+T41 -> 0 | U42: =+Precios!T40*Precios!T$3 -> 0 | V42: =+V41 -> 0 | W42: =+Precios!V40*Precios!V$3 -> 0 | X42: =+Precios!W40*Precios!W$3 -> 0 | Y42: =+Precios!X40*Precios!X$3 -> 0 | Z42: =+Precios!Y40*Precios!Y$3 -> 0 | AA42: =+Precios!Z40*Precios!Z$3 -> 0 | AB42: =+AB41 -> 0 | AC42: =+AC41 -> 0 | AD42: =+AD41 -> 0 | AE42: =+AE41 -> 0 | AF42: =+AF41 -> 0 | AG42: =+AG41 -> 0 | AH42: =+Precios!AG40*Precios!AG$3 -> 0 | AI42: =+Precios!AH40*Precios!AH$3 -> 0 | AJ42: =+Precios!AI40*Precios!AI$3 -> 0 | AK42: =+Precios!AJ40*Precios!AJ$3 -> 0 | AL42: =+Precios!AK40*Precios!AK$3 -> 0 | AM42: =+Precios!AL40*Precios!AL$3 -> 0 | AP42: =+Precios!AO40*Precios!AO$3 -> 0 | AQ42: =+Precios!AP40*Precios!AP$3 -> 0 | AR42: =+Precios!AQ40*Precios!AQ$3 -> 0 | AS42: =+Precios!AR40*Precios!AR$3 -> 0 | AT42: =+Precios!AS40*Precios!AS$3 -> 0 | AU42: =+Precios!AT40*Precios!AT$3 -> 0 | AW42: =+Precios!AV40*Precios!AV$3 -> 0 | AX42: =+Precios!AW40*Precios!AW$3 -> 0 | AY42: =+Precios!AX40*Precios!AX$3 -> 0 | AZ42: =+Precios!AY40*Precios!AY$3 -> 0 | BA42: =+Precios!AZ40*Precios!AZ$3 -> 0 | BB42: =+Precios!BA40*Precios!BA$3 -> 0 | BC42: =+Precios!BB40*Precios!BB$3 -> 0 | BD42: =+Precios!BC40*Precios!BC$3 -> 0 | ... BM42: =+Precios!BL40*Precios!BL$3 -> 0
A43: =+SUM(C43:XFD43) -> 0 | B43: =+Precios!A41 -> 46029 | C43: =+Precios!B41*Precios!B$3 -> 0 | D43: =+Precios!C41*Precios!C$3 -> 0 | E43: =+Precios!D41*Precios!D$3 -> 0 | F43: =+Precios!E41*Precios!E$3 -> 0 | G43: =+Precios!F41*Precios!F$3 -> 0 | H43: =+Precios!G41*Precios!G$3 -> 0 | I43: =+Precios!H41*Precios!H$3 -> 0 | J43: =+Precios!I41*Precios!I$3 -> 0 | ... P43: =+Precios!O41*Precios!O$3 -> 0 | Q43: =+Q42 -> 0 | R43: =+R42 -> 0 | S43: =+S42 -> 0 | T43: =+T42 -> 0 | U43: =+Precios!T41*Precios!T$3 -> 0 | V43: =+V42 -> 0 | W43: =+Precios!V41*Precios!V$3 -> 0 | X43: =+Precios!W41*Precios!W$3 -> 0 | Y43: =+Precios!X41*Precios!X$3 -> 0 | Z43: =+Precios!Y41*Precios!Y$3 -> 0 | AA43: =+Precios!Z41*Precios!Z$3 -> 0 | AB43: =+AB42 -> 0 | AC43: =+AC42 -> 0 | AD43: =+AD42 -> 0 | AE43: =+AE42 -> 0 | AF43: =+AF42 -> 0 | AG43: =+AG42 -> 0 | AH43: =+Precios!AG41*Precios!AG$3 -> 0 | AI43: =+Precios!AH41*Precios!AH$3 -> 0 | AJ43: =+Precios!AI41*Precios!AI$3 -> 0 | AK43: =+Precios!AJ41*Precios!AJ$3 -> 0 | AL43: =+Precios!AK41*Precios!AK$3 -> 0 | AM43: =+Precios!AL41*Precios!AL$3 -> 0 | AP43: =+Precios!AO41*Precios!AO$3 -> 0 | AQ43: =+Precios!AP41*Precios!AP$3 -> 0 | AR43: =+Precios!AQ41*Precios!AQ$3 -> 0 | AS43: =+Precios!AR41*Precios!AR$3 -> 0 | AT43: =+Precios!AS41*Precios!AS$3 -> 0 | AU43: =+Precios!AT41*Precios!AT$3 -> 0 | AW43: =+Precios!AV41*Precios!AV$3 -> 0 | AX43: =+Precios!AW41*Precios!AW$3 -> 0 | AY43: =+Precios!AX41*Precios!AX$3 -> 0 | AZ43: =+Precios!AY41*Precios!AY$3 -> 0 | BA43: =+Precios!AZ41*Precios!AZ$3 -> 0 | BB43: =+Precios!BA41*Precios!BA$3 -> 0 | BC43: =+Precios!BB41*Precios!BB$3 -> 0 | BD43: =+Precios!BC41*Precios!BC$3 -> 0 | ... BM43: =+Precios!BL41*Precios!BL$3 -> 0
A44: =+SUM(C44:XFD44) -> 0 | B44: =+Precios!A42 -> 46030 | C44: =+Precios!B42*Precios!B$3 -> 0 | D44: =+Precios!C42*Precios!C$3 -> 0 | E44: =+Precios!D42*Precios!D$3 -> 0 | F44: =+Precios!E42*Precios!E$3 -> 0 | G44: =+Precios!F42*Precios!F$3 -> 0 | H44: =+Precios!G42*Precios!G$3 -> 0 | I44: =+Precios!H42*Precios!H$3 -> 0 | J44: =+Precios!I42*Precios!I$3 -> 0 | ... Q44: =+Precios!P42*Precios!P$3 -> 0 | R44: =+R43 -> 0 | S44: =+S43 -> 0 | T44: =+T43 -> 0 | U44: =+Precios!T42*Precios!T$3 -> 0 | V44: =+V43 -> 0 | W44: =+Precios!V42*Precios!V$3 -> 0 | X44: =+Precios!W42*Precios!W$3 -> 0 | Y44: =+Precios!X42*Precios!X$3 -> 0 | Z44: =+Precios!Y42*Precios!Y$3 -> 0 | AA44: =+Precios!Z42*Precios!Z$3 -> 0 | AB44: =+AB43 -> 0 | AC44: =+AC43 -> 0 | AD44: =+AD43 -> 0 | AE44: =+AE43 -> 0 | AF44: =+AF43 -> 0 | AG44: =+AG43 -> 0 | AH44: =+Precios!AG42*Precios!AG$3 -> 0 | AI44: =+Precios!AH42*Precios!AH$3 -> 0 | AJ44: =+Precios!AI42*Precios!AI$3 -> 0 | AK44: =+Precios!AJ42*Precios!AJ$3 -> 0 | AL44: =+Precios!AK42*Precios!AK$3 -> 0 | AM44: =+Precios!AL42*Precios!AL$3 -> 0 | AP44: =+Precios!AO42*Precios!AO$3 -> 0 | AQ44: =+Precios!AP42*Precios!AP$3 -> 0 | AR44: =+Precios!AQ42*Precios!AQ$3 -> 0 | AS44: =+Precios!AR42*Precios!AR$3 -> 0 | AT44: =+Precios!AS42*Precios!AS$3 -> 0 | AU44: =+Precios!AT42*Precios!AT$3 -> 0 | AW44: =+Precios!AV42*Precios!AV$3 -> 0 | AX44: =+Precios!AW42*Precios!AW$3 -> 0 | AY44: =+Precios!AX42*Precios!AX$3 -> 0 | AZ44: =+Precios!AY42*Precios!AY$3 -> 0 | BA44: =+Precios!AZ42*Precios!AZ$3 -> 0 | BB44: =+Precios!BA42*Precios!BA$3 -> 0 | BC44: =+Precios!BB42*Precios!BB$3 -> 0 | BD44: =+Precios!BC42*Precios!BC$3 -> 0 | ... BM44: =+Precios!BL42*Precios!BL$3 -> 0
A45: =+SUM(C45:XFD45) -> 0 | B45: =+Precios!A43 -> 46031 | C45: =+Precios!B43*Precios!B$3 -> 0 | D45: =+Precios!C43*Precios!C$3 -> 0 | E45: =+Precios!D43*Precios!D$3 -> 0 | F45: =+Precios!E43*Precios!E$3 -> 0 | G45: =+Precios!F43*Precios!F$3 -> 0 | H45: =+Precios!G43*Precios!G$3 -> 0 | I45: =+Precios!H43*Precios!H$3 -> 0 | J45: =+Precios!I43*Precios!I$3 -> 0 | ... Q45: =+Precios!P43*Precios!P$3 -> 0 | R45: =+R44 -> 0 | S45: =+S44 -> 0 | T45: =+T44 -> 0 | U45: =+Precios!T43*Precios!T$3 -> 0 | V45: =+V44 -> 0 | W45: =+Precios!V43*Precios!V$3 -> 0 | X45: =+Precios!W43*Precios!W$3 -> 0 | Y45: =+Precios!X43*Precios!X$3 -> 0 | Z45: =+Precios!Y43*Precios!Y$3 -> 0 | AA45: =+Precios!Z43*Precios!Z$3 -> 0 | AB45: =+AB44 -> 0 | AC45: =+AC44 -> 0 | AD45: =+AD44 -> 0 | AE45: =+AE44 -> 0 | AF45: =+AF44 -> 0 | AG45: =+AG44 -> 0 | AH45: =+AH44 -> 0 | AI45: =+Precios!AH43*Precios!AH$3 -> 0 | AJ45: =+Precios!AI43*Precios!AI$3 -> 0 | AK45: =+Precios!AJ43*Precios!AJ$3 -> 0 | AL45: =+Precios!AK43*Precios!AK$3 -> 0 | AM45: =+Precios!AL43*Precios!AL$3 -> 0 | AP45: =+Precios!AO43*Precios!AO$3 -> 0 | AQ45: =+Precios!AP43*Precios!AP$3 -> 0 | AR45: =+Precios!AQ43*Precios!AQ$3 -> 0 | AS45: =+Precios!AR43*Precios!AR$3 -> 0 | AT45: =+Precios!AS43*Precios!AS$3 -> 0 | AU45: =+Precios!AT43*Precios!AT$3 -> 0 | AW45: =+Precios!AV43*Precios!AV$3 -> 0 | AX45: =+Precios!AW43*Precios!AW$3 -> 0 | AY45: =+Precios!AX43*Precios!AX$3 -> 0 | AZ45: =+Precios!AY43*Precios!AY$3 -> 0 | BA45: =+Precios!AZ43*Precios!AZ$3 -> 0 | BB45: =+Precios!BA43*Precios!BA$3 -> 0 | BC45: =+Precios!BB43*Precios!BB$3 -> 0 | BD45: =+Precios!BC43*Precios!BC$3 -> 0 | ... BM45: =+Precios!BL43*Precios!BL$3 -> 0
A46: =+SUM(C46:XFD46) -> 0 | B46: =+Precios!A44 -> 46034 | C46: =+Precios!B44*Precios!B$3 -> 0 | D46: =+Precios!C44*Precios!C$3 -> 0 | E46: =+Precios!D44*Precios!D$3 -> 0 | F46: =+Precios!E44*Precios!E$3 -> 0 | G46: =+Precios!F44*Precios!F$3 -> 0 | H46: =+Precios!G44*Precios!G$3 -> 0 | I46: =+Precios!H44*Precios!H$3 -> 0 | J46: =+Precios!I44*Precios!I$3 -> 0 | ... S46: =+Precios!R44*Precios!R$3 -> 0 | T46: =+T45 -> 0 | U46: =+Precios!T44*Precios!T$3 -> 0 | V46: =+V45 -> 0 | W46: =+Precios!V44*Precios!V$3 -> 0 | X46: =+Precios!W44*Precios!W$3 -> 0 | Y46: =+Precios!X44*Precios!X$3 -> 0 | Z46: =+Precios!Y44*Precios!Y$3 -> 0 | AA46: =+AA45 -> 0 | AB46: =+AB45 -> 0 | AC46: =+AC45 -> 0 | AD46: =+AD45 -> 0 | AE46: =+AE45 -> 0 | AF46: =+AF45 -> 0 | AG46: =+AG45 -> 0 | AH46: =+AH45 -> 0 | AI46: =+Precios!AH44*Precios!AH$3 -> 0 | AJ46: =+AJ45 -> 0 | AK46: =+Precios!AJ44*Precios!AJ$3 -> 0 | AL46: =+Precios!AK44*Precios!AK$3 -> 0 | AM46: =+Precios!AL44*Precios!AL$3 -> 0 | AP46: =+Precios!AO44*Precios!AO$3 -> 0 | AQ46: =+Precios!AP44*Precios!AP$3 -> 0 | AR46: =+Precios!AQ44*Precios!AQ$3 -> 0 | AS46: =+Precios!AR44*Precios!AR$3 -> 0 | AT46: =+Precios!AS44*Precios!AS$3 -> 0 | AU46: =+Precios!AT44*Precios!AT$3 -> 0 | AW46: =+Precios!AV44*Precios!AV$3 -> 0 | AX46: =+Precios!AW44*Precios!AW$3 -> 0 | AY46: =+Precios!AX44*Precios!AX$3 -> 0 | AZ46: =+Precios!AY44*Precios!AY$3 -> 0 | BA46: =+Precios!AZ44*Precios!AZ$3 -> 0 | BB46: =+Precios!BA44*Precios!BA$3 -> 0 | BC46: =+Precios!BB44*Precios!BB$3 -> 0 | BD46: =+Precios!BC44*Precios!BC$3 -> 0 | ... BM46: =+Precios!BL44*Precios!BL$3 -> 0
A47: =+SUM(C47:XFD47) -> 0 | B47: =+Precios!A45 -> 46035 | C47: =+Precios!B45*Precios!B$3 -> 0 | D47: =+Precios!C45*Precios!C$3 -> 0 | E47: =+Precios!D45*Precios!D$3 -> 0 | F47: =+Precios!E45*Precios!E$3 -> 0 | G47: =+Precios!F45*Precios!F$3 -> 0 | H47: =+Precios!G45*Precios!G$3 -> 0 | I47: =+Precios!H45*Precios!H$3 -> 0 | J47: =+Precios!I45*Precios!I$3 -> 0 | ... S47: =+Precios!R45*Precios!R$3 -> 0 | T47: =+T46 -> 0 | U47: =+Precios!T45*Precios!T$3 -> 0 | V47: =+V46 -> 0 | W47: =+W46 -> 0 | X47: =+Precios!W45*Precios!W$3 -> 0 | Y47: =+Precios!X45*Precios!X$3 -> 0 | Z47: =+Precios!Y45*Precios!Y$3 -> 0 | AA47: =+AA46 -> 0 | AB47: =+AB46 -> 0 | AC47: =+AC46 -> 0 | AD47: =+AD46 -> 0 | AE47: =+AE46 -> 0 | AF47: =+AF46 -> 0 | AG47: =+AG46 -> 0 | AH47: =+AH46 -> 0 | AI47: =+Precios!AH45*Precios!AH$3 -> 0 | AJ47: =+AJ46 -> 0 | AK47: =+Precios!AJ45*Precios!AJ$3 -> 0 | AL47: =+Precios!AK45*Precios!AK$3 -> 0 | AM47: =+Precios!AL45*Precios!AL$3 -> 0 | AP47: =+Precios!AO45*Precios!AO$3 -> 0 | AQ47: =+Precios!AP45*Precios!AP$3 -> 0 | AR47: =+Precios!AQ45*Precios!AQ$3 -> 0 | AS47: =+Precios!AR45*Precios!AR$3 -> 0 | AT47: =+Precios!AS45*Precios!AS$3 -> 0 | AU47: =+Precios!AT45*Precios!AT$3 -> 0 | AW47: =+Precios!AV45*Precios!AV$3 -> 0 | AX47: =+Precios!AW45*Precios!AW$3 -> 0 | AY47: =+Precios!AX45*Precios!AX$3 -> 0 | AZ47: =+Precios!AY45*Precios!AY$3 -> 0 | BA47: =+Precios!AZ45*Precios!AZ$3 -> 0 | BB47: =+Precios!BA45*Precios!BA$3 -> 0 | BC47: =+Precios!BB45*Precios!BB$3 -> 0 | BD47: =+Precios!BC45*Precios!BC$3 -> 0 | ... BM47: =+Precios!BL45*Precios!BL$3 -> 0
A48: =+SUM(C48:XFD48) -> 0 | B48: =+Precios!A46 -> 46036 | C48: =+Precios!B46*Precios!B$3 -> 0 | D48: =+Precios!C46*Precios!C$3 -> 0 | E48: =+Precios!D46*Precios!D$3 -> 0 | F48: =+Precios!E46*Precios!E$3 -> 0 | G48: =+Precios!F46*Precios!F$3 -> 0 | H48: =+Precios!G46*Precios!G$3 -> 0 | I48: =+Precios!H46*Precios!H$3 -> 0 | J48: =+Precios!I46*Precios!I$3 -> 0 | ... S48: =+Precios!R46*Precios!R$3 -> 0 | U48: =+Precios!T46*Precios!T$3 -> 0 | V48: =+V47 -> 0 | W48: =+W47 -> 0 | X48: =+Precios!W46*Precios!W$3 -> 0 | Y48: =+Precios!X46*Precios!X$3 -> 0 | Z48: =+Precios!Y46*Precios!Y$3 -> 0 | AA48: =+AA47 -> 0 | AB48: =+AB47 -> 0 | AC48: =+AC47 -> 0 | AD48: =+AD47 -> 0 | AE48: =+AE47 -> 0 | AF48: =+AF47 -> 0 | AG48: =+AG47 -> 0 | AH48: =+AH47 -> 0 | AI48: =+Precios!AH46*Precios!AH$3 -> 0 | AJ48: =+AJ47 -> 0 | AK48: =+Precios!AJ46*Precios!AJ$3 -> 0 | AL48: =+Precios!AK46*Precios!AK$3 -> 0 | AM48: =+Precios!AL46*Precios!AL$3 -> 0 | AP48: =+Precios!AO46*Precios!AO$3 -> 0 | AQ48: =+Precios!AP46*Precios!AP$3 -> 0 | AR48: =+Precios!AQ46*Precios!AQ$3 -> 0 | AS48: =+Precios!AR46*Precios!AR$3 -> 0 | AT48: =+Precios!AS46*Precios!AS$3 -> 0 | AU48: =+Precios!AT46*Precios!AT$3 -> 0 | AW48: =+Precios!AV46*Precios!AV$3 -> 0 | AX48: =+Precios!AW46*Precios!AW$3 -> 0 | AY48: =+Precios!AX46*Precios!AX$3 -> 0 | AZ48: =+Precios!AY46*Precios!AY$3 -> 0 | BA48: =+Precios!AZ46*Precios!AZ$3 -> 0 | BB48: =+Precios!BA46*Precios!BA$3 -> 0 | BC48: =+Precios!BB46*Precios!BB$3 -> 0 | BD48: =+Precios!BC46*Precios!BC$3 -> 0 | ... BM48: =+Precios!BL46*Precios!BL$3 -> 0
A49: =+SUM(C49:XFD49) -> 0 | B49: =+Precios!A47 -> 46037 | C49: =+Precios!B47*Precios!B$3 -> 0 | D49: =+Precios!C47*Precios!C$3 -> 0 | E49: =+Precios!D47*Precios!D$3 -> 0 | F49: =+Precios!E47*Precios!E$3 -> 0 | G49: =+Precios!F47*Precios!F$3 -> 0 | H49: =+Precios!G47*Precios!G$3 -> 0 | I49: =+Precios!H47*Precios!H$3 -> 0 | J49: =+Precios!I47*Precios!I$3 -> 0 | ... S49: =+Precios!R47*Precios!R$3 -> 0 | U49: =+U48 -> 0 | V49: =+V48 -> 0 | W49: =+W48 -> 0 | X49: =+X48 -> 0 | Y49: =+Precios!X47*Precios!X$3 -> 0 | Z49: =+Precios!Y47*Precios!Y$3 -> 0 | AA49: =+AA48 -> 0 | AB49: =+AB48 -> 0 | AC49: =+AC48 -> 0 | AD49: =+AD48 -> 0 | AE49: =+AE48 -> 0 | AF49: =+AF48 -> 0 | AG49: =+AG48 -> 0 | AH49: =+AH48 -> 0 | ... AJ49: =+AJ48 -> 0 | AK49: =+Precios!AJ47*Precios!AJ$3 -> 0 | AL49: =+Precios!AK47*Precios!AK$3 -> 0 | AM49: =+Precios!AL47*Precios!AL$3 -> 0 | AP49: =+Precios!AO47*Precios!AO$3 -> 0 | AQ49: =+Precios!AP47*Precios!AP$3 -> 0 | AR49: =+Precios!AQ47*Precios!AQ$3 -> 0 | AS49: =+Precios!AR47*Precios!AR$3 -> 0 | AT49: =+Precios!AS47*Precios!AS$3 -> 0 | AU49: =+Precios!AT47*Precios!AT$3 -> 0 | AW49: =+Precios!AV47*Precios!AV$3 -> 0 | AX49: =+Precios!AW47*Precios!AW$3 -> 0 | AY49: =+Precios!AX47*Precios!AX$3 -> 0 | AZ49: =+Precios!AY47*Precios!AY$3 -> 0 | BA49: =+Precios!AZ47*Precios!AZ$3 -> 0 | BB49: =+Precios!BA47*Precios!BA$3 -> 0 | BC49: =+Precios!BB47*Precios!BB$3 -> 0 | BD49: =+Precios!BC47*Precios!BC$3 -> 0 | ... BM49: =+Precios!BL47*Precios!BL$3 -> 0
A50: =+SUM(C50:XFD50) -> 0 | B50: =+Precios!A48 -> 46038 | C50: =+Precios!B48*Precios!B$3 -> 0 | D50: =+Precios!C48*Precios!C$3 -> 0 | E50: =+Precios!D48*Precios!D$3 -> 0 | F50: =+Precios!E48*Precios!E$3 -> 0 | G50: =+Precios!F48*Precios!F$3 -> 0 | H50: =+Precios!G48*Precios!G$3 -> 0 | I50: =+Precios!H48*Precios!H$3 -> 0 | J50: =+Precios!I48*Precios!I$3 -> 0 | ... S50: =+Precios!R48*Precios!R$3 -> 0 | U50: =+U49 -> 0 | V50: =+V49 -> 0 | W50: =+W49 -> 0 | X50: =+X49 -> 0 | Y50: =+Precios!X48*Precios!X$3 -> 0 | Z50: =+Precios!Y48*Precios!Y$3 -> 0 | AA50: =+AA49 -> 0 | AB50: =+AB49 -> 0 | AC50: =+AC49 -> 0 | AD50: =+AD49 -> 0 | AE50: =+AE49 -> 0 | AF50: =+AF49 -> 0 | AG50: =+AG49 -> 0 | AH50: =+AH49 -> 0 | ... AJ50: =+AJ49 -> 0 | AK50: =+Precios!AJ48*Precios!AJ$3 -> 0 | AL50: =+Precios!AK48*Precios!AK$3 -> 0 | AM50: =+Precios!AL48*Precios!AL$3 -> 0 | AP50: =+Precios!AO48*Precios!AO$3 -> 0 | AQ50: =+Precios!AP48*Precios!AP$3 -> 0 | AR50: =+Precios!AQ48*Precios!AQ$3 -> 0 | AS50: =+Precios!AR48*Precios!AR$3 -> 0 | AT50: =+Precios!AS48*Precios!AS$3 -> 0 | AU50: =+Precios!AT48*Precios!AT$3 -> 0 | AW50: =+Precios!AV48*Precios!AV$3 -> 0 | AX50: =+Precios!AW48*Precios!AW$3 -> 0 | AY50: =+Precios!AX48*Precios!AX$3 -> 0 | AZ50: =+Precios!AY48*Precios!AY$3 -> 0 | BA50: =+Precios!AZ48*Precios!AZ$3 -> 0 | BB50: =+Precios!BA48*Precios!BA$3 -> 0 | BC50: =+Precios!BB48*Precios!BB$3 -> 0 | BD50: =+Precios!BC48*Precios!BC$3 -> 0 | ... BM50: =+Precios!BL48*Precios!BL$3 -> 0
A51: =+SUM(C51:XFD51) -> 0 | B51: =+Precios!A49 -> 46041 | C51: =+Precios!B49*Precios!B$3 -> 0 | D51: =+Precios!C49*Precios!C$3 -> 0 | E51: =+Precios!D49*Precios!D$3 -> 0 | F51: =+Precios!E49*Precios!E$3 -> 0 | G51: =+Precios!F49*Precios!F$3 -> 0 | H51: =+Precios!G49*Precios!G$3 -> 0 | I51: =+Precios!H49*Precios!H$3 -> 0 | J51: =+Precios!I49*Precios!I$3 -> 0 | ... S51: =+Precios!R49*Precios!R$3 -> 0 | U51: =+U50 -> 0 | V51: =+V50 -> 0 | W51: =+W50 -> 0 | X51: =+X50 -> 0 | Y51: =+Precios!X49*Precios!X$3 -> 0 | Z51: =+Precios!Y49*Precios!Y$3 -> 0 | AA51: =+AA50 -> 0 | AB51: =+AB50 -> 0 | AC51: =+AC50 -> 0 | AD51: =+AD50 -> 0 | AE51: =+AE50 -> 0 | AF51: =+AF50 -> 0 | AG51: =+AG50 -> 0 | AH51: =+AH50 -> 0 | ... AJ51: =+AJ50 -> 0 | AK51: =+Precios!AJ49*Precios!AJ$3 -> 0 | AL51: =+Precios!AK49*Precios!AK$3 -> 0 | AM51: =+Precios!AL49*Precios!AL$3 -> 0 | AP51: =+Precios!AO49*Precios!AO$3 -> 0 | AQ51: =+Precios!AP49*Precios!AP$3 -> 0 | AR51: =+Precios!AQ49*Precios!AQ$3 -> 0 | AS51: =+Precios!AR49*Precios!AR$3 -> 0 | AT51: =+Precios!AS49*Precios!AS$3 -> 0 | AU51: =+Precios!AT49*Precios!AT$3 -> 0 | AW51: =+Precios!AV49*Precios!AV$3 -> 0 | AX51: =+Precios!AW49*Precios!AW$3 -> 0 | AY51: =+Precios!AX49*Precios!AX$3 -> 0 | AZ51: =+Precios!AY49*Precios!AY$3 -> 0 | BA51: =+Precios!AZ49*Precios!AZ$3 -> 0 | BB51: =+Precios!BA49*Precios!BA$3 -> 0 | BC51: =+Precios!BB49*Precios!BB$3 -> 0 | BD51: =+Precios!BC49*Precios!BC$3 -> 0 | ... BM51: =+Precios!BL49*Precios!BL$3 -> 0
A52: =+SUM(C52:XFD52) -> 0 | B52: =+Precios!A50 -> 46042 | C52: =+Precios!B50*Precios!B$3 -> 0 | D52: =+Precios!C50*Precios!C$3 -> 0 | E52: =+Precios!D50*Precios!D$3 -> 0 | F52: =+Precios!E50*Precios!E$3 -> 0 | G52: =+Precios!F50*Precios!F$3 -> 0 | H52: =+Precios!G50*Precios!G$3 -> 0 | I52: =+Precios!H50*Precios!H$3 -> 0 | J52: =+Precios!I50*Precios!I$3 -> 0 | ... S52: =+Precios!R50*Precios!R$3 -> 0 | U52: =+U51 -> 0 | V52: =+V51 -> 0 | W52: =+W51 -> 0 | X52: =+X51 -> 0 | Y52: =+Precios!X50*Precios!X$3 -> 0 | Z52: =+Precios!Y50*Precios!Y$3 -> 0 | AA52: =+AA51 -> 0 | AB52: =+AB51 -> 0 | AC52: =+AC51 -> 0 | AD52: =+AD51 -> 0 | AE52: =+AE51 -> 0 | AF52: =+AF51 -> 0 | AG52: =+AG51 -> 0 | AH52: =+AH51 -> 0 | ... AJ52: =+AJ51 -> 0 | AK52: =+Precios!AJ50*Precios!AJ$3 -> 0 | AL52: =+Precios!AK50*Precios!AK$3 -> 0 | AM52: =+Precios!AL50*Precios!AL$3 -> 0 | AP52: =+Precios!AO50*Precios!AO$3 -> 0 | AQ52: =+Precios!AP50*Precios!AP$3 -> 0 | AR52: =+Precios!AQ50*Precios!AQ$3 -> 0 | AS52: =+Precios!AR50*Precios!AR$3 -> 0 | AT52: =+Precios!AS50*Precios!AS$3 -> 0 | AU52: =+Precios!AT50*Precios!AT$3 -> 0 | AW52: =+Precios!AV50*Precios!AV$3 -> 0 | AX52: =+Precios!AW50*Precios!AW$3 -> 0 | AY52: =+Precios!AX50*Precios!AX$3 -> 0 | AZ52: =+Precios!AY50*Precios!AY$3 -> 0 | BA52: =+Precios!AZ50*Precios!AZ$3 -> 0 | BB52: =+Precios!BA50*Precios!BA$3 -> 0 | BC52: =+Precios!BB50*Precios!BB$3 -> 0 | BD52: =+Precios!BC50*Precios!BC$3 -> 0 | ... BM52: =+Precios!BL50*Precios!BL$3 -> 0
A53: =+SUM(C53:XFD53) -> 0 | B53: =+Precios!A51 -> 46043 | C53: =+Precios!B51*Precios!B$3 -> 0 | D53: =+Precios!C51*Precios!C$3 -> 0 | E53: =+Precios!D51*Precios!D$3 -> 0 | F53: =+Precios!E51*Precios!E$3 -> 0 | G53: =+Precios!F51*Precios!F$3 -> 0 | H53: =+Precios!G51*Precios!G$3 -> 0 | I53: =+Precios!H51*Precios!H$3 -> 0 | J53: =+Precios!I51*Precios!I$3 -> 0 | ... S53: =+Precios!R51*Precios!R$3 -> 0 | V53: =+V52 -> 0 | W53: =+W52 -> 0 | X53: =+X52 -> 0 | Y53: =+Precios!X51*Precios!X$3 -> 0 | Z53: =+Z52 -> 0 | AA53: =+AA52 -> 0 | AB53: =+AB52 -> 0 | AC53: =+AC52 -> 0 | AD53: =+AD52 -> 0 | AE53: =+AE52 -> 0 | AF53: =+AF52 -> 0 | AG53: =+AG52 -> 0 | ... AK53: =+AK52 -> 0 | AL53: =+Precios!AK51*Precios!AK$3 -> 0 | AM53: =+Precios!AL51*Precios!AL$3 -> 0 | AP53: =+Precios!AO51*Precios!AO$3 -> 0 | AQ53: =+Precios!AP51*Precios!AP$3 -> 0 | AR53: =+Precios!AQ51*Precios!AQ$3 -> 0 | AS53: =+Precios!AR51*Precios!AR$3 -> 0 | AT53: =+Precios!AS51*Precios!AS$3 -> 0 | AU53: =+Precios!AT51*Precios!AT$3 -> 0 | AW53: =+Precios!AV51*Precios!AV$3 -> 0 | AX53: =+Precios!AW51*Precios!AW$3 -> 0 | AY53: =+Precios!AX51*Precios!AX$3 -> 0 | AZ53: =+Precios!AY51*Precios!AY$3 -> 0 | BA53: =+Precios!AZ51*Precios!AZ$3 -> 0 | BB53: =+Precios!BA51*Precios!BA$3 -> 0 | BC53: =+Precios!BB51*Precios!BB$3 -> 0 | BD53: =+Precios!BC51*Precios!BC$3 -> 0 | ... BM53: =+Precios!BL51*Precios!BL$3 -> 0
A54: =+SUM(C54:XFD54) -> 0 | B54: =+Precios!A52 -> 46044 | C54: =+Precios!B52*Precios!B$3 -> 0 | D54: =+Precios!C52*Precios!C$3 -> 0 | E54: =+Precios!D52*Precios!D$3 -> 0 | F54: =+Precios!E52*Precios!E$3 -> 0 | G54: =+Precios!F52*Precios!F$3 -> 0 | H54: =+Precios!G52*Precios!G$3 -> 0 | I54: =+Precios!H52*Precios!H$3 -> 0 | J54: =+Precios!I52*Precios!I$3 -> 0 | ... S54: =+Precios!R52*Precios!R$3 -> 0 | W54: =+W53 -> 0 | X54: =+X53 -> 0 | Y54: =+Precios!X52*Precios!X$3 -> 0 | Z54: =+Z53 -> 0 | AA54: =+AA53 -> 0 | AB54: =+AB53 -> 0 | AC54: =+AC53 -> 0 | AD54: =+AD53 -> 0 | AE54: =+AE53 -> 0 | AF54: =+AF53 -> 0 | AG54: =+AG53 -> 0 | ... AM54: =+AM53 -> 0 | AP54: =+Precios!AO52*Precios!AO$3 -> 0 | AQ54: =+Precios!AP52*Precios!AP$3 -> 0 | AR54: =+Precios!AQ52*Precios!AQ$3 -> 0 | AS54: =+Precios!AR52*Precios!AR$3 -> 0 | AT54: =+Precios!AS52*Precios!AS$3 -> 0 | AU54: =+Precios!AT52*Precios!AT$3 -> 0 | AW54: =+Precios!AV52*Precios!AV$3 -> 0 | AX54: =+Precios!AW52*Precios!AW$3 -> 0 | AY54: =+Precios!AX52*Precios!AX$3 -> 0 | AZ54: =+Precios!AY52*Precios!AY$3 -> 0 | BA54: =+Precios!AZ52*Precios!AZ$3 -> 0 | BB54: =+Precios!BA52*Precios!BA$3 -> 0 | BC54: =+Precios!BB52*Precios!BB$3 -> 0 | BD54: =+Precios!BC52*Precios!BC$3 -> 0 | ... BM54: =+Precios!BL52*Precios!BL$3 -> 0
A55: =+SUM(C55:XFD55) -> 0 | B55: =+Precios!A53 -> 46045 | C55: =+Precios!B53*Precios!B$3 -> 0 | D55: =+Precios!C53*Precios!C$3 -> 0 | E55: =+Precios!D53*Precios!D$3 -> 0 | F55: =+Precios!E53*Precios!E$3 -> 0 | G55: =+Precios!F53*Precios!F$3 -> 0 | H55: =+Precios!G53*Precios!G$3 -> 0 | I55: =+Precios!H53*Precios!H$3 -> 0 | J55: =+Precios!I53*Precios!I$3 -> 0 | ... S55: =+Precios!R53*Precios!R$3 -> 0 | W55: =+W54 -> 0 | X55: =+X54 -> 0 | Y55: =+Precios!X53*Precios!X$3 -> 0 | Z55: =+Z54 -> 0 | AA55: =+AA54 -> 0 | AB55: =+AB54 -> 0 | AC55: =+AC54 -> 0 | AD55: =+AD54 -> 0 | AE55: =+AE54 -> 0 | AF55: =+AF54 -> 0 | AG55: =+AG54 -> 0 | ... AM55: =+AM54 -> 0 | AP55: =+Precios!AO53*Precios!AO$3 -> 0 | AQ55: =+Precios!AP53*Precios!AP$3 -> 0 | AR55: =+Precios!AQ53*Precios!AQ$3 -> 0 | AS55: =+Precios!AR53*Precios!AR$3 -> 0 | AT55: =+Precios!AS53*Precios!AS$3 -> 0 | AU55: =+Precios!AT53*Precios!AT$3 -> 0 | AW55: =+Precios!AV53*Precios!AV$3 -> 0 | AX55: =+Precios!AW53*Precios!AW$3 -> 0 | AY55: =+Precios!AX53*Precios!AX$3 -> 0 | AZ55: =+Precios!AY53*Precios!AY$3 -> 0 | BA55: =+Precios!AZ53*Precios!AZ$3 -> 0 | BB55: =+Precios!BA53*Precios!BA$3 -> 0 | BC55: =+Precios!BB53*Precios!BB$3 -> 0 | BD55: =+Precios!BC53*Precios!BC$3 -> 0 | ... BM55: =+Precios!BL53*Precios!BL$3 -> 0
A56: =+SUM(C56:XFD56) -> 0 | B56: =+Precios!A54 -> 46048 | C56: =+Precios!B54*Precios!B$3 -> 0 | D56: =+Precios!C54*Precios!C$3 -> 0 | E56: =+Precios!D54*Precios!D$3 -> 0 | F56: =+Precios!E54*Precios!E$3 -> 0 | G56: =+Precios!F54*Precios!F$3 -> 0 | H56: =+Precios!G54*Precios!G$3 -> 0 | I56: =+Precios!H54*Precios!H$3 -> 0 | J56: =+Precios!I54*Precios!I$3 -> 0 | ... S56: =+Precios!R54*Precios!R$3 -> 0 | W56: =+W55 -> 0 | X56: =+X55 -> 0 | Y56: =+Precios!X54*Precios!X$3 -> 0 | Z56: =+Z55 -> 0 | AA56: =+AA55 -> 0 | AB56: =+AB55 -> 0 | AC56: =+AC55 -> 0 | AD56: =+AD55 -> 0 | AE56: =+AE55 -> 0 | AF56: =+AF55 -> 0 | AG56: =+AG55 -> 0 | ... AM56: =+AM55 -> 0 | AP56: =+Precios!AO54*Precios!AO$3 -> 0 | AQ56: =+Precios!AP54*Precios!AP$3 -> 0 | AR56: =+Precios!AQ54*Precios!AQ$3 -> 0 | AS56: =+Precios!AR54*Precios!AR$3 -> 0 | AT56: =+Precios!AS54*Precios!AS$3 -> 0 | AU56: =+Precios!AT54*Precios!AT$3 -> 0 | AW56: =+Precios!AV54*Precios!AV$3 -> 0 | AX56: =+Precios!AW54*Precios!AW$3 -> 0 | AY56: =+Precios!AX54*Precios!AX$3 -> 0 | AZ56: =+Precios!AY54*Precios!AY$3 -> 0 | BA56: =+Precios!AZ54*Precios!AZ$3 -> 0 | BB56: =+Precios!BA54*Precios!BA$3 -> 0 | BC56: =+Precios!BB54*Precios!BB$3 -> 0 | BD56: =+Precios!BC54*Precios!BC$3 -> 0 | ... BM56: =+Precios!BL54*Precios!BL$3 -> 0
A57: =+SUM(C57:XFD57) -> 0 | B57: =+Precios!A55 -> 46049 | C57: =+Precios!B55*Precios!B$3 -> 0 | D57: =+Precios!C55*Precios!C$3 -> 0 | E57: =+Precios!D55*Precios!D$3 -> 0 | F57: =+Precios!E55*Precios!E$3 -> 0 | G57: =+Precios!F55*Precios!F$3 -> 0 | H57: =+Precios!G55*Precios!G$3 -> 0 | I57: =+Precios!H55*Precios!H$3 -> 0 | J57: =+Precios!I55*Precios!I$3 -> 0 | ... S57: =+Precios!R55*Precios!R$3 -> 0 | W57: =+W56 -> 0 | X57: =+X56 -> 0 | Y57: =+Precios!X55*Precios!X$3 -> 0 | Z57: =+Z56 -> 0 | AA57: =+AA56 -> 0 | AB57: =+AB56 -> 0 | AC57: =+AC56 -> 0 | AD57: =+AD56 -> 0 | AE57: =+AE56 -> 0 | AF57: =+AF56 -> 0 | AG57: =+AG56 -> 0 | ... AM57: =+AM56 -> 0 | AP57: =+Precios!AO55*Precios!AO$3 -> 0 | AQ57: =+Precios!AP55*Precios!AP$3 -> 0 | AR57: =+Precios!AQ55*Precios!AQ$3 -> 0 | AS57: =+Precios!AR55*Precios!AR$3 -> 0 | AT57: =+Precios!AS55*Precios!AS$3 -> 0 | AU57: =+Precios!AT55*Precios!AT$3 -> 0 | AW57: =+Precios!AV55*Precios!AV$3 -> 0 | AX57: =+Precios!AW55*Precios!AW$3 -> 0 | AY57: =+Precios!AX55*Precios!AX$3 -> 0 | AZ57: =+Precios!AY55*Precios!AY$3 -> 0 | BA57: =+Precios!AZ55*Precios!AZ$3 -> 0 | BB57: =+Precios!BA55*Precios!BA$3 -> 0 | BC57: =+Precios!BB55*Precios!BB$3 -> 0 | BD57: =+Precios!BC55*Precios!BC$3 -> 0 | ... BM57: =+Precios!BL55*Precios!BL$3 -> 0
A58: =+SUM(C58:XFD58) -> 0 | B58: =+Precios!A56 -> 46050 | C58: =+Precios!B56*Precios!B$3 -> 0 | D58: =+Precios!C56*Precios!C$3 -> 0 | E58: =+Precios!D56*Precios!D$3 -> 0 | F58: =+Precios!E56*Precios!E$3 -> 0 | G58: =+Precios!F56*Precios!F$3 -> 0 | H58: =+Precios!G56*Precios!G$3 -> 0 | I58: =+Precios!H56*Precios!H$3 -> 0 | J58: =+Precios!I56*Precios!I$3 -> 0 | ... S58: =+Precios!R56*Precios!R$3 -> 0 | X58: =+X57 -> 0 | Y58: =+Precios!X56*Precios!X$3 -> 0 | Z58: =+Z57 -> 0 | AA58: =+AA57 -> 0 | AB58: =+AB57 -> 0 | AC58: =+AC57 -> 0 | AD58: =+AD57 -> 0 | AE58: =+AE57 -> 0 | AF58: =+AF57 -> 0 | AG58: =+AG57 -> 0 | ... AM58: =+AM57 -> 0 | AN58: =+Precios!AM56*Precios!AM$3 -> 0 | AP58: =+Precios!AO56*Precios!AO$3 -> 0 | AQ58: =+Precios!AP56*Precios!AP$3 -> 0 | AR58: =+Precios!AQ56*Precios!AQ$3 -> 0 | AS58: =+Precios!AR56*Precios!AR$3 -> 0 | AT58: =+Precios!AS56*Precios!AS$3 -> 0 | AU58: =+Precios!AT56*Precios!AT$3 -> 0 | AW58: =+Precios!AV56*Precios!AV$3 -> 0 | AX58: =+Precios!AW56*Precios!AW$3 -> 0 | AY58: =+Precios!AX56*Precios!AX$3 -> 0 | AZ58: =+Precios!AY56*Precios!AY$3 -> 0 | BA58: =+Precios!AZ56*Precios!AZ$3 -> 0 | BB58: =+Precios!BA56*Precios!BA$3 -> 0 | BC58: =+Precios!BB56*Precios!BB$3 -> 0 | BD58: =+Precios!BC56*Precios!BC$3 -> 0 | ... BM58: =+Precios!BL56*Precios!BL$3 -> 0
A59: =+SUM(C59:XFD59) -> 0 | B59: =+Precios!A57 -> 46051 | C59: =+Precios!B57*Precios!B$3 -> 0 | D59: =+Precios!C57*Precios!C$3 -> 0 | E59: =+Precios!D57*Precios!D$3 -> 0 | F59: =+Precios!E57*Precios!E$3 -> 0 | G59: =+Precios!F57*Precios!F$3 -> 0 | H59: =+Precios!G57*Precios!G$3 -> 0 | I59: =+Precios!H57*Precios!H$3 -> 0 | J59: =+Precios!I57*Precios!I$3 -> 0 | ... S59: =+Precios!R57*Precios!R$3 -> 0 | Z59: =+Z58 -> 0 | AA59: =+AA58 -> 0 | AB59: =+AB58 -> 0 | AC59: =+AC58 -> 0 | AD59: =+AD58 -> 0 | AE59: =+AE58 -> 0 | AF59: =+AF58 -> 0 | AG59: =+AG58 -> 0 | ... AN59: =+AN58 -> 0 | AP59: =+Precios!AO57*Precios!AO$3 -> 0 | AQ59: =+Precios!AP57*Precios!AP$3 -> 0 | AR59: =+Precios!AQ57*Precios!AQ$3 -> 0 | AS59: =+Precios!AR57*Precios!AR$3 -> 0 | AT59: =+Precios!AS57*Precios!AS$3 -> 0 | AU59: =+Precios!AT57*Precios!AT$3 -> 0 | AW59: =+Precios!AV57*Precios!AV$3 -> 0 | AX59: =+Precios!AW57*Precios!AW$3 -> 0 | AY59: =+Precios!AX57*Precios!AX$3 -> 0 | AZ59: =+Precios!AY57*Precios!AY$3 -> 0 | BA59: =+Precios!AZ57*Precios!AZ$3 -> 0 | BB59: =+Precios!BA57*Precios!BA$3 -> 0 | BC59: =+Precios!BB57*Precios!BB$3 -> 0 | BD59: =+Precios!BC57*Precios!BC$3 -> 0 | ... BM59: =+Precios!BL57*Precios!BL$3 -> 0
A60: =+SUM(C60:XFD60) -> 0 | B60: =+Precios!A58 -> 46052 | C60: =+Precios!B58*Precios!B$3 -> 0 | D60: =+Precios!C58*Precios!C$3 -> 0 | E60: =+Precios!D58*Precios!D$3 -> 0 | F60: =+Precios!E58*Precios!E$3 -> 0 | G60: =+Precios!F58*Precios!F$3 -> 0 | H60: =+Precios!G58*Precios!G$3 -> 0 | I60: =+Precios!H58*Precios!H$3 -> 0 | J60: =+Precios!I58*Precios!I$3 -> 0 | ... S60: =+Precios!R58*Precios!R$3 -> 0 | Z60: =+Z59 -> 0 | AA60: =+AA59 -> 0 | AB60: =+AB59 -> 0 | AC60: =+AC59 -> 0 | AD60: =+AD59 -> 0 | AE60: =+AE59 -> 0 | AF60: =+AF59 -> 0 | AG60: =+AG59 -> 0 | ... AN60: =+AN59 -> 0 | AP60: =+Precios!AO58*Precios!AO$3 -> 0 | AQ60: =+Precios!AP58*Precios!AP$3 -> 0 | AR60: =+Precios!AQ58*Precios!AQ$3 -> 0 | AS60: =+Precios!AR58*Precios!AR$3 -> 0 | AT60: =+Precios!AS58*Precios!AS$3 -> 0 | AU60: =+Precios!AT58*Precios!AT$3 -> 0 | AW60: =+Precios!AV58*Precios!AV$3 -> 0 | AX60: =+Precios!AW58*Precios!AW$3 -> 0 | AY60: =+Precios!AX58*Precios!AX$3 -> 0 | AZ60: =+Precios!AY58*Precios!AY$3 -> 0 | BA60: =+Precios!AZ58*Precios!AZ$3 -> 0 | BB60: =+Precios!BA58*Precios!BA$3 -> 0 | BC60: =+Precios!BB58*Precios!BB$3 -> 0 | BD60: =+Precios!BC58*Precios!BC$3 -> 0 | ... BM60: =+Precios!BL58*Precios!BL$3 -> 0
A61: =+SUM(C61:XFD61) -> 0 | B61: =+Precios!A59 -> 46055 | C61: =+Precios!B59*Precios!B$3 -> 0 | D61: =+Precios!C59*Precios!C$3 -> 0 | E61: =+Precios!D59*Precios!D$3 -> 0 | F61: =+Precios!E59*Precios!E$3 -> 0 | G61: =+Precios!F59*Precios!F$3 -> 0 | H61: =+Precios!G59*Precios!G$3 -> 0 | I61: =+Precios!H59*Precios!H$3 -> 0 | J61: =+Precios!I59*Precios!I$3 -> 0 | ... S61: =+Precios!R59*Precios!R$3 -> 0 | AB61: =+AB60 -> 0 | AC61: =+AC60 -> 0 | AD61: =+AD60 -> 0 | AE61: =+AE60 -> 0 | AF61: =+AF60 -> 0 | AG61: =+AG60 -> 0 | AH61: =+AH60 -> 0 | AI61: =+AI60 -> 0 | ... AN61: =+AN60 -> 0 | AP61: =+Precios!AO59*Precios!AO$3 -> 0 | AQ61: =+Precios!AP59*Precios!AP$3 -> 0 | AR61: =+Precios!AQ59*Precios!AQ$3 -> 0 | AS61: =+Precios!AR59*Precios!AR$3 -> 0 | AT61: =+Precios!AS59*Precios!AS$3 -> 0 | AU61: =+Precios!AT59*Precios!AT$3 -> 0 | AW61: =+Precios!AV59*Precios!AV$3 -> 0 | AX61: =+Precios!AW59*Precios!AW$3 -> 0 | AY61: =+Precios!AX59*Precios!AX$3 -> 0 | AZ61: =+Precios!AY59*Precios!AY$3 -> 0 | BA61: =+Precios!AZ59*Precios!AZ$3 -> 0 | BB61: =+Precios!BA59*Precios!BA$3 -> 0 | BC61: =+Precios!BB59*Precios!BB$3 -> 0 | BD61: =+Precios!BC59*Precios!BC$3 -> 0 | ... BM61: =+Precios!BL59*Precios!BL$3 -> 0
A62: =+SUM(C62:XFD62) -> 0 | B62: =+Precios!A60 -> 46056 | C62: =+Precios!B60*Precios!B$3 -> 0 | D62: =+Precios!C60*Precios!C$3 -> 0 | E62: =+Precios!D60*Precios!D$3 -> 0 | F62: =+Precios!E60*Precios!E$3 -> 0 | G62: =+Precios!F60*Precios!F$3 -> 0 | H62: =+Precios!G60*Precios!G$3 -> 0 | I62: =+Precios!H60*Precios!H$3 -> 0 | J62: =+Precios!I60*Precios!I$3 -> 0 | ... S62: =+Precios!R60*Precios!R$3 -> 0 | AB62: =+AB61 -> 0 | AC62: =+AC61 -> 0 | AD62: =+AD61 -> 0 | AE62: =+AE61 -> 0 | AF62: =+AF61 -> 0 | AG62: =+AG61 -> 0 | AH62: =+AH61 -> 0 | AI62: =+AI61 -> 0 | ... AN62: =+AN61 -> 0 | AO62: =+Precios!AN60*Precios!AN$3 -> 0 | AP62: =+Precios!AO60*Precios!AO$3 -> 0 | AQ62: =+Precios!AP60*Precios!AP$3 -> 0 | AR62: =+Precios!AQ60*Precios!AQ$3 -> 0 | AS62: =+Precios!AR60*Precios!AR$3 -> 0 | AT62: =+Precios!AS60*Precios!AS$3 -> 0 | AU62: =+Precios!AT60*Precios!AT$3 -> 0 | AW62: =+Precios!AV60*Precios!AV$3 -> 0 | AX62: =+Precios!AW60*Precios!AW$3 -> 0 | AY62: =+Precios!AX60*Precios!AX$3 -> 0 | AZ62: =+Precios!AY60*Precios!AY$3 -> 0 | BA62: =+Precios!AZ60*Precios!AZ$3 -> 0 | BB62: =+Precios!BA60*Precios!BA$3 -> 0 | BC62: =+Precios!BB60*Precios!BB$3 -> 0 | BD62: =+Precios!BC60*Precios!BC$3 -> 0 | ... BM62: =+Precios!BL60*Precios!BL$3 -> 0
A63: =+SUM(C63:XFD63) -> 0 | B63: =+Precios!A61 -> 46057 | C63: =+Precios!B61*Precios!B$3 -> 0 | D63: =+Precios!C61*Precios!C$3 -> 0 | E63: =+Precios!D61*Precios!D$3 -> 0 | F63: =+Precios!E61*Precios!E$3 -> 0 | G63: =+Precios!F61*Precios!F$3 -> 0 | H63: =+Precios!G61*Precios!G$3 -> 0 | I63: =+Precios!H61*Precios!H$3 -> 0 | J63: =+Precios!I61*Precios!I$3 -> 0 | ... S63: =+Precios!R61*Precios!R$3 -> 0 | AB63: =+AB62 -> 0 | AC63: =+AC62 -> 0 | AD63: =+AD62 -> 0 | AE63: =+AE62 -> 0 | AF63: =+AF62 -> 0 | AG63: =+AG62 -> 0 | AH63: =+AH62 -> 0 | AI63: =+AI62 -> 0 | ... AO63: =+AO62 -> 0 | AP63: =+Precios!AO61*Precios!AO$3 -> 0 | AQ63: =+Precios!AP61*Precios!AP$3 -> 0 | AR63: =+Precios!AQ61*Precios!AQ$3 -> 0 | AS63: =+Precios!AR61*Precios!AR$3 -> 0 | AT63: =+Precios!AS61*Precios!AS$3 -> 0 | AU63: =+Precios!AT61*Precios!AT$3 -> 0 | AW63: =+Precios!AV61*Precios!AV$3 -> 0 | AX63: =+Precios!AW61*Precios!AW$3 -> 0 | AY63: =+Precios!AX61*Precios!AX$3 -> 0 | AZ63: =+Precios!AY61*Precios!AY$3 -> 0 | BA63: =+Precios!AZ61*Precios!AZ$3 -> 0 | BB63: =+Precios!BA61*Precios!BA$3 -> 0 | BC63: =+Precios!BB61*Precios!BB$3 -> 0 | BD63: =+Precios!BC61*Precios!BC$3 -> 0 | ... BM63: =+Precios!BL61*Precios!BL$3 -> 0
A64: =+SUM(C64:XFD64) -> 0 | B64: =+Precios!A62 -> 46058 | C64: =+Precios!B62*Precios!B$3 -> 0 | D64: =+Precios!C62*Precios!C$3 -> 0 | E64: =+Precios!D62*Precios!D$3 -> 0 | F64: =+Precios!E62*Precios!E$3 -> 0 | G64: =+Precios!F62*Precios!F$3 -> 0 | H64: =+Precios!G62*Precios!G$3 -> 0 | I64: =+Precios!H62*Precios!H$3 -> 0 | J64: =+Precios!I62*Precios!I$3 -> 0 | ... S64: =+Precios!R62*Precios!R$3 -> 0 | AM64: =+AM63 -> 0 | AO64: =+AO63 -> 0 | AP64: =+Precios!AO62*Precios!AO$3 -> 0 | AQ64: =+Precios!AP62*Precios!AP$3 -> 0 | AR64: =+Precios!AQ62*Precios!AQ$3 -> 0 | AS64: =+Precios!AR62*Precios!AR$3 -> 0 | AT64: =+Precios!AS62*Precios!AS$3 -> 0 | AU64: =+Precios!AT62*Precios!AT$3 -> 0 | AW64: =+Precios!AV62*Precios!AV$3 -> 0 | AX64: =+Precios!AW62*Precios!AW$3 -> 0 | AY64: =+Precios!AX62*Precios!AX$3 -> 0 | AZ64: =+Precios!AY62*Precios!AY$3 -> 0 | BA64: =+Precios!AZ62*Precios!AZ$3 -> 0 | BB64: =+Precios!BA62*Precios!BA$3 -> 0 | BC64: =+Precios!BB62*Precios!BB$3 -> 0 | BD64: =+Precios!BC62*Precios!BC$3 -> 0 | ... BM64: =+Precios!BL62*Precios!BL$3 -> 0
A65: =+SUM(C65:XFD65) -> 0 | B65: =+Precios!A63 -> 46059 | C65: =+Precios!B63*Precios!B$3 -> 0 | D65: =+Precios!C63*Precios!C$3 -> 0 | E65: =+Precios!D63*Precios!D$3 -> 0 | F65: =+Precios!E63*Precios!E$3 -> 0 | G65: =+Precios!F63*Precios!F$3 -> 0 | H65: =+Precios!G63*Precios!G$3 -> 0 | I65: =+Precios!H63*Precios!H$3 -> 0 | J65: =+Precios!I63*Precios!I$3 -> 0 | ... S65: =+Precios!R63*Precios!R$3 -> 0 | AO65: =+AO64 -> 0 | AP65: =+AP64 -> 0 | AQ65: =+Precios!AP63*Precios!AP$3 -> 0 | AR65: =+Precios!AQ63*Precios!AQ$3 -> 0 | AS65: =+Precios!AR63*Precios!AR$3 -> 0 | AT65: =+Precios!AS63*Precios!AS$3 -> 0 | AU65: =+Precios!AT63*Precios!AT$3 -> 0 | AW65: =+Precios!AV63*Precios!AV$3 -> 0 | AX65: =+Precios!AW63*Precios!AW$3 -> 0 | AY65: =+Precios!AX63*Precios!AX$3 -> 0 | AZ65: =+Precios!AY63*Precios!AY$3 -> 0 | BA65: =+Precios!AZ63*Precios!AZ$3 -> 0 | BB65: =+Precios!BA63*Precios!BA$3 -> 0 | BC65: =+Precios!BB63*Precios!BB$3 -> 0 | BD65: =+Precios!BC63*Precios!BC$3 -> 0 | ... BM65: =+Precios!BL63*Precios!BL$3 -> 0
A66: =+SUM(C66:XFD66) -> 0 | B66: =+Precios!A64 -> 46062 | C66: =+Precios!B64*Precios!B$3 -> 0 | D66: =+Precios!C64*Precios!C$3 -> 0 | E66: =+Precios!D64*Precios!D$3 -> 0 | F66: =+Precios!E64*Precios!E$3 -> 0 | G66: =+Precios!F64*Precios!F$3 -> 0 | H66: =+Precios!G64*Precios!G$3 -> 0 | I66: =+Precios!H64*Precios!H$3 -> 0 | J66: =+Precios!I64*Precios!I$3 -> 0 | ... S66: =+Precios!R64*Precios!R$3 -> 0 | AO66: =+AO65 -> 0 | AQ66: =+AQ65 -> 0 | AR66: =+AR65 -> 0 | AS66: =+Precios!AR64*Precios!AR$3 -> 0 | AT66: =+Precios!AS64*Precios!AS$3 -> 0 | AU66: =+Precios!AT64*Precios!AT$3 -> 0 | AW66: =+Precios!AV64*Precios!AV$3 -> 0 | AX66: =+Precios!AW64*Precios!AW$3 -> 0 | AY66: =+Precios!AX64*Precios!AX$3 -> 0 | AZ66: =+Precios!AY64*Precios!AY$3 -> 0 | BA66: =+Precios!AZ64*Precios!AZ$3 -> 0 | BB66: =+Precios!BA64*Precios!BA$3 -> 0 | BC66: =+Precios!BB64*Precios!BB$3 -> 0 | BD66: =+Precios!BC64*Precios!BC$3 -> 0 | ... BM66: =+Precios!BL64*Precios!BL$3 -> 0
A67: =+SUM(C67:XFD67) -> 0 | B67: =+Precios!A65 -> 46063 | C67: =+Precios!B65*Precios!B$3 -> 0 | D67: =+Precios!C65*Precios!C$3 -> 0 | E67: =+Precios!D65*Precios!D$3 -> 0 | F67: =+Precios!E65*Precios!E$3 -> 0 | G67: =+Precios!F65*Precios!F$3 -> 0 | H67: =+Precios!G65*Precios!G$3 -> 0 | I67: =+Precios!H65*Precios!H$3 -> 0 | J67: =+Precios!I65*Precios!I$3 -> 0 | ... S67: =+Precios!R65*Precios!R$3 -> 0 | AO67: =+AO66 -> 0 | AQ67: =+AQ66 -> 0 | AR67: =+AR66 -> 0 | AS67: =+Precios!AR65*Precios!AR$3 -> 0 | AT67: =+Precios!AS65*Precios!AS$3 -> 0 | AU67: =+Precios!AT65*Precios!AT$3 -> 0 | AW67: =+Precios!AV65*Precios!AV$3 -> 0 | AX67: =+Precios!AW65*Precios!AW$3 -> 0 | AY67: =+Precios!AX65*Precios!AX$3 -> 0 | AZ67: =+Precios!AY65*Precios!AY$3 -> 0 | BA67: =+Precios!AZ65*Precios!AZ$3 -> 0 | BB67: =+Precios!BA65*Precios!BA$3 -> 0 | BC67: =+Precios!BB65*Precios!BB$3 -> 0 | BD67: =+Precios!BC65*Precios!BC$3 -> 0 | ... BM67: =+Precios!BL65*Precios!BL$3 -> 0
A68: =+SUM(C68:XFD68) -> 0 | B68: =+Precios!A66 -> 46064 | C68: =+Precios!B66*Precios!B$3 -> 0 | D68: =+Precios!C66*Precios!C$3 -> 0 | E68: =+Precios!D66*Precios!D$3 -> 0 | F68: =+Precios!E66*Precios!E$3 -> 0 | G68: =+Precios!F66*Precios!F$3 -> 0 | H68: =+Precios!G66*Precios!G$3 -> 0 | I68: =+Precios!H66*Precios!H$3 -> 0 | J68: =+Precios!I66*Precios!I$3 -> 0 | ... S68: =+Precios!R66*Precios!R$3 -> 0 | AO68: =+AO67 -> 0 | AQ68: =+AQ67 -> 0 | AR68: =+AR67 -> 0 | AS68: =+AS67 -> 0 | AT68: =+Precios!AS66*Precios!AS$3 -> 0 | AU68: =+Precios!AT66*Precios!AT$3 -> 0 | AW68: =+Precios!AV66*Precios!AV$3 -> 0 | AX68: =+Precios!AW66*Precios!AW$3 -> 0 | AY68: =+Precios!AX66*Precios!AX$3 -> 0 | AZ68: =+Precios!AY66*Precios!AY$3 -> 0 | BA68: =+Precios!AZ66*Precios!AZ$3 -> 0 | BB68: =+Precios!BA66*Precios!BA$3 -> 0 | BC68: =+Precios!BB66*Precios!BB$3 -> 0 | BD68: =+Precios!BC66*Precios!BC$3 -> 0 | ... BM68: =+Precios!BL66*Precios!BL$3 -> 0
A69: =+SUM(C69:XFD69) -> 0 | B69: =+Precios!A67 -> 46065 | C69: =+Precios!B67*Precios!B$3 -> 0 | D69: =+Precios!C67*Precios!C$3 -> 0 | E69: =+Precios!D67*Precios!D$3 -> 0 | F69: =+Precios!E67*Precios!E$3 -> 0 | G69: =+Precios!F67*Precios!F$3 -> 0 | H69: =+Precios!G67*Precios!G$3 -> 0 | I69: =+Precios!H67*Precios!H$3 -> 0 | J69: =+Precios!I67*Precios!I$3 -> 0 | ... S69: =+Precios!R67*Precios!R$3 -> 0 | AO69: =+AO68 -> 0 | AQ69: =+AQ68 -> 0 | AT69: =+AT68 -> 0 | AU69: =+Precios!AT67*Precios!AT$3 -> 0 | AW69: =+Precios!AV67*Precios!AV$3 -> 0 | AX69: =+Precios!AW67*Precios!AW$3 -> 0 | AY69: =+Precios!AX67*Precios!AX$3 -> 0 | AZ69: =+Precios!AY67*Precios!AY$3 -> 0 | BA69: =+Precios!AZ67*Precios!AZ$3 -> 0 | BB69: =+Precios!BA67*Precios!BA$3 -> 0 | BC69: =+Precios!BB67*Precios!BB$3 -> 0 | BD69: =+Precios!BC67*Precios!BC$3 -> 0 | ... BM69: =+Precios!BL67*Precios!BL$3 -> 0
A70: =+SUM(C70:XFD70) -> 0 | B70: =+Precios!A68 -> 46066 | C70: =+Precios!B68*Precios!B$3 -> 0 | D70: =+Precios!C68*Precios!C$3 -> 0 | E70: =+Precios!D68*Precios!D$3 -> 0 | F70: =+Precios!E68*Precios!E$3 -> 0 | G70: =+Precios!F68*Precios!F$3 -> 0 | H70: =+Precios!G68*Precios!G$3 -> 0 | I70: =+Precios!H68*Precios!H$3 -> 0 | J70: =+Precios!I68*Precios!I$3 -> 0 | ... S70: =+Precios!R68*Precios!R$3 -> 0 | AO70: =+AO69 -> 0 | AQ70: =+AQ69 -> 0 | AT70: =+AT69 -> 0 | AU70: =+AU69 -> 0 | AW70: =+Precios!AV68*Precios!AV$3 -> 0 | AX70: =+Precios!AW68*Precios!AW$3 -> 0 | AY70: =+Precios!AX68*Precios!AX$3 -> 0 | AZ70: =+Precios!AY68*Precios!AY$3 -> 0 | BA70: =+Precios!AZ68*Precios!AZ$3 -> 0 | BB70: =+Precios!BA68*Precios!BA$3 -> 0 | BC70: =+Precios!BB68*Precios!BB$3 -> 0 | BD70: =+Precios!BC68*Precios!BC$3 -> 0 | ... BM70: =+Precios!BL68*Precios!BL$3 -> 0
A71: =+SUM(C71:XFD71) -> 0 | B71: =+Precios!A69 -> 46069 | C71: =+Precios!B69*Precios!B$3 -> 0 | D71: =+Precios!C69*Precios!C$3 -> 0 | E71: =+Precios!D69*Precios!D$3 -> 0 | F71: =+Precios!E69*Precios!E$3 -> 0 | G71: =+Precios!F69*Precios!F$3 -> 0 | H71: =+Precios!G69*Precios!G$3 -> 0 | I71: =+Precios!H69*Precios!H$3 -> 0 | J71: =+Precios!I69*Precios!I$3 -> 0 | ... S71: =+Precios!R69*Precios!R$3 -> 0 | AO71: =+AO70 -> 0 | AQ71: =+AQ70 -> 0 | AT71: =+AT70 -> 0 | AU71: =+AU70 -> 0 | AW71: =+Precios!AV69*Precios!AV$3 -> 0 | AX71: =+Precios!AW69*Precios!AW$3 -> 0 | AY71: =+Precios!AX69*Precios!AX$3 -> 0 | AZ71: =+Precios!AY69*Precios!AY$3 -> 0 | BA71: =+Precios!AZ69*Precios!AZ$3 -> 0 | BB71: =+Precios!BA69*Precios!BA$3 -> 0 | BC71: =+Precios!BB69*Precios!BB$3 -> 0 | BD71: =+Precios!BC69*Precios!BC$3 -> 0 | ... BM71: =+Precios!BL69*Precios!BL$3 -> 0
A72: =+SUM(C72:XFD72) -> 50000 | B72: =+Precios!A70 -> 46070 | C72: =+Precios!B70*Precios!B$3 -> 0 | D72: =+Precios!C70*Precios!C$3 -> 0 | E72: =+Precios!D70*Precios!D$3 -> 0 | F72: =+Precios!E70*Precios!E$3 -> 0 | G72: =+Precios!F70*Precios!F$3 -> 0 | H72: =+Precios!G70*Precios!G$3 -> 0 | I72: =+Precios!H70*Precios!H$3 -> 0 | J72: =+Precios!I70*Precios!I$3 -> 0 | ... S72: =+Precios!R70*Precios!R$3 -> 0 | AO72: =+AO71 -> 0 | AQ72: =+AQ71 -> 0 | AT72: =+AT71 -> 0 | AU72: =+AU71 -> 0 | AV72: 50000 | AW72: =+Precios!AV70*Precios!AV$3 -> 0 | AX72: =+Precios!AW70*Precios!AW$3 -> 0 | AY72: =+Precios!AX70*Precios!AX$3 -> 0 | AZ72: =+Precios!AY70*Precios!AY$3 -> 0 | BA72: =+Precios!AZ70*Precios!AZ$3 -> 0 | BB72: =+Precios!BA70*Precios!BA$3 -> 0 | BC72: =+Precios!BB70*Precios!BB$3 -> 0 | BD72: =+Precios!BC70*Precios!BC$3 -> 0 | ... BM72: =+Precios!BL70*Precios!BL$3 -> 0
A73: =+SUM(C73:XFD73) -> 50000 | B73: =+Precios!A71 -> 46071 | C73: =+Precios!B71*Precios!B$3 -> 0 | D73: =+Precios!C71*Precios!C$3 -> 0 | E73: =+Precios!D71*Precios!D$3 -> 0 | F73: =+Precios!E71*Precios!E$3 -> 0 | G73: =+Precios!F71*Precios!F$3 -> 0 | H73: =+Precios!G71*Precios!G$3 -> 0 | I73: =+Precios!H71*Precios!H$3 -> 0 | J73: =+Precios!I71*Precios!I$3 -> 0 | ... S73: =+Precios!R71*Precios!R$3 -> 0 | AO73: =+AO72 -> 0 | AU73: =+AU72 -> 0 | AV73: =+AV72 -> 50000 | AW73: =+Precios!AV71*Precios!AV$3 -> 0 | AX73: =+Precios!AW71*Precios!AW$3 -> 0 | AY73: =+Precios!AX71*Precios!AX$3 -> 0 | AZ73: =+Precios!AY71*Precios!AY$3 -> 0 | BA73: =+Precios!AZ71*Precios!AZ$3 -> 0 | BB73: =+Precios!BA71*Precios!BA$3 -> 0 | BC73: =+Precios!BB71*Precios!BB$3 -> 0 | BD73: =+Precios!BC71*Precios!BC$3 -> 0 | ... BM73: =+Precios!BL71*Precios!BL$3 -> 0
A74: =+SUM(C74:XFD74) -> 50000 | B74: =+Precios!A72 -> 46072 | C74: =+Precios!B72*Precios!B$3 -> 0 | D74: =+Precios!C72*Precios!C$3 -> 0 | E74: =+Precios!D72*Precios!D$3 -> 0 | F74: =+Precios!E72*Precios!E$3 -> 0 | G74: =+Precios!F72*Precios!F$3 -> 0 | H74: =+Precios!G72*Precios!G$3 -> 0 | I74: =+Precios!H72*Precios!H$3 -> 0 | J74: =+Precios!I72*Precios!I$3 -> 0 | ... S74: =+Precios!R72*Precios!R$3 -> 0 | AO74: =+AO73 -> 0 | AU74: =+AU73 -> 0 | AV74: =+AV73 -> 50000 | AW74: =+AW73 -> 0 | AX74: =+AX73 -> 0 | AY74: =+AY73 -> 0 | AZ74: =+Precios!AY72*Precios!AY$3 -> 0 | BA74: =+Precios!AZ72*Precios!AZ$3 -> 0 | BB74: =+Precios!BA72*Precios!BA$3 -> 0 | BC74: =+Precios!BB72*Precios!BB$3 -> 0 | BD74: =+Precios!BC72*Precios!BC$3 -> 0 | BE74: =+Precios!BD72*Precios!BD$3 -> 0 | BF74: =+Precios!BE72*Precios!BE$3 -> 0 | BG74: =+Precios!BF72*Precios!BF$3 -> 0 | ... BM74: =+Precios!BL72*Precios!BL$3 -> 0
A75: =+SUM(C75:XFD75) -> 50000 | B75: =+Precios!A73 -> 46073 | C75: =+Precios!B73*Precios!B$3 -> 0 | D75: =+Precios!C73*Precios!C$3 -> 0 | E75: =+Precios!D73*Precios!D$3 -> 0 | F75: =+Precios!E73*Precios!E$3 -> 0 | G75: =+Precios!F73*Precios!F$3 -> 0 | H75: =+Precios!G73*Precios!G$3 -> 0 | I75: =+Precios!H73*Precios!H$3 -> 0 | J75: =+Precios!I73*Precios!I$3 -> 0 | ... S75: =+Precios!R73*Precios!R$3 -> 0 | AO75: =+AO74 -> 0 | AU75: =+AU74 -> 0 | AV75: =+AV74 -> 50000 | AW75: =+AW74 -> 0 | AX75: =+AX74 -> 0 | AY75: =+AY74 -> 0 | AZ75: =+AZ74 -> 0 | BA75: =+BA74 -> 0 | BB75: =+Precios!BA73*Precios!BA$3 -> 0 | BC75: =+Precios!BB73*Precios!BB$3 -> 0 | BD75: =+Precios!BC73*Precios!BC$3 -> 0 | BE75: =+Precios!BD73*Precios!BD$3 -> 0 | BF75: =+Precios!BE73*Precios!BE$3 -> 0 | BG75: =+Precios!BF73*Precios!BF$3 -> 0 | BH75: =+Precios!BG73*Precios!BG$3 -> 0 | BI75: =+Precios!BH73*Precios!BH$3 -> 0 | ... BM75: =+Precios!BL73*Precios!BL$3 -> 0
A76: =+SUM(C76:XFD76) -> 50000 | B76: =+Precios!A74 -> 46076 | C76: =+Precios!B74*Precios!B$3 -> 0 | D76: =+Precios!C74*Precios!C$3 -> 0 | E76: =+Precios!D74*Precios!D$3 -> 0 | F76: =+Precios!E74*Precios!E$3 -> 0 | G76: =+Precios!F74*Precios!F$3 -> 0 | H76: =+Precios!G74*Precios!G$3 -> 0 | I76: =+Precios!H74*Precios!H$3 -> 0 | J76: =+Precios!I74*Precios!I$3 -> 0 | ... S76: =+Precios!R74*Precios!R$3 -> 0 | AO76: =+AO75 -> 0 | AU76: =+AU75 -> 0 | AV76: =+AV75 -> 50000 | AW76: =+AW75 -> 0 | AX76: =+AX75 -> 0 | AY76: =+AY75 -> 0 | AZ76: =+AZ75 -> 0 | BA76: =+BA75 -> 0 | BB76: =+BB75 -> 0 | BC76: =+Precios!BB74*Precios!BB$3 -> 0 | BD76: =+Precios!BC74*Precios!BC$3 -> 0 | BE76: =+Precios!BD74*Precios!BD$3 -> 0 | BF76: =+Precios!BE74*Precios!BE$3 -> 0 | BG76: =+Precios!BF74*Precios!BF$3 -> 0 | BH76: =+Precios!BG74*Precios!BG$3 -> 0 | BI76: =+Precios!BH74*Precios!BH$3 -> 0 | BJ76: =+Precios!BI74*Precios!BI$3 -> 0 | ... BM76: =+Precios!BL74*Precios!BL$3 -> 0
A77: =+SUM(C77:XFD77) -> 50000 | B77: =+Precios!A75 -> 46077 | C77: =+Precios!B75*Precios!B$3 -> 0 | D77: =+Precios!C75*Precios!C$3 -> 0 | E77: =+Precios!D75*Precios!D$3 -> 0 | F77: =+Precios!E75*Precios!E$3 -> 0 | G77: =+Precios!F75*Precios!F$3 -> 0 | H77: =+Precios!G75*Precios!G$3 -> 0 | I77: =+Precios!H75*Precios!H$3 -> 0 | J77: =+Precios!I75*Precios!I$3 -> 0 | ... S77: =+Precios!R75*Precios!R$3 -> 0 | AO77: =+AO76 -> 0 | AU77: =+AU76 -> 0 | AV77: =+AV76 -> 50000 | AW77: =+AW76 -> 0 | AX77: =+AX76 -> 0 | AY77: =+AY76 -> 0 | AZ77: =+AZ76 -> 0 | BA77: =+BA76 -> 0 | BB77: =+BB76 -> 0 | BC77: =+Precios!BB75*Precios!BB$3 -> 0 | BD77: =+Precios!BC75*Precios!BC$3 -> 0 | BE77: =+Precios!BD75*Precios!BD$3 -> 0 | BF77: =+Precios!BE75*Precios!BE$3 -> 0 | BG77: =+Precios!BF75*Precios!BF$3 -> 0 | BH77: =+Precios!BG75*Precios!BG$3 -> 0 | BI77: =+Precios!BH75*Precios!BH$3 -> 0 | BJ77: =+Precios!BI75*Precios!BI$3 -> 0 | ... BM77: =+Precios!BL75*Precios!BL$3 -> 0
A78: =+SUM(C78:XFD78) -> 50000 | B78: =+Precios!A76 -> 46078 | C78: =+Precios!B76*Precios!B$3 -> 0 | D78: =+Precios!C76*Precios!C$3 -> 0 | E78: =+Precios!D76*Precios!D$3 -> 0 | F78: =+Precios!E76*Precios!E$3 -> 0 | G78: =+Precios!F76*Precios!F$3 -> 0 | H78: =+Precios!G76*Precios!G$3 -> 0 | I78: =+Precios!H76*Precios!H$3 -> 0 | J78: =+Precios!I76*Precios!I$3 -> 0 | ... S78: =+Precios!R76*Precios!R$3 -> 0 | AO78: =+AO77 -> 0 | AU78: =+AU77 -> 0 | AV78: =+AV77 -> 50000 | AW78: =+AW77 -> 0 | AX78: =+AX77 -> 0 | AY78: =+AY77 -> 0 | AZ78: =+AZ77 -> 0 | BA78: =+BA77 -> 0 | BB78: =+BB77 -> 0 | BC78: =+Precios!BB76*Precios!BB$3 -> 0 | BD78: =+Precios!BC76*Precios!BC$3 -> 0 | BE78: =+Precios!BD76*Precios!BD$3 -> 0 | BF78: =+Precios!BE76*Precios!BE$3 -> 0 | BG78: =+Precios!BF76*Precios!BF$3 -> 0 | BH78: =+Precios!BG76*Precios!BG$3 -> 0 | BI78: =+Precios!BH76*Precios!BH$3 -> 0 | BJ78: =+Precios!BI76*Precios!BI$3 -> 0 | ... BM78: =+Precios!BL76*Precios!BL$3 -> 0
A79: =+SUM(C79:XFD79) -> 50000 | B79: =+Precios!A77 -> 46079 | C79: =+Precios!B77*Precios!B$3 -> 0 | D79: =+Precios!C77*Precios!C$3 -> 0 | E79: =+Precios!D77*Precios!D$3 -> 0 | F79: =+Precios!E77*Precios!E$3 -> 0 | G79: =+Precios!F77*Precios!F$3 -> 0 | H79: =+Precios!G77*Precios!G$3 -> 0 | I79: =+Precios!H77*Precios!H$3 -> 0 | J79: =+Precios!I77*Precios!I$3 -> 0 | ... S79: =+Precios!R77*Precios!R$3 -> 0 | AO79: =+AO78 -> 0 | AU79: =+AU78 -> 0 | AV79: =+AV78 -> 50000 | AW79: =+AW78 -> 0 | AY79: =+AY78 -> 0 | AZ79: =+AZ78 -> 0 | BA79: =+BA78 -> 0 | BB79: =+BB78 -> 0 | BC79: =+Precios!BB77*Precios!BB$3 -> 0 | BD79: =+Precios!BC77*Precios!BC$3 -> 0 | BE79: =+Precios!BD77*Precios!BD$3 -> 0 | BF79: =+Precios!BE77*Precios!BE$3 -> 0 | BG79: =+Precios!BF77*Precios!BF$3 -> 0 | BH79: =+Precios!BG77*Precios!BG$3 -> 0 | BI79: =+Precios!BH77*Precios!BH$3 -> 0 | BJ79: =+Precios!BI77*Precios!BI$3 -> 0 | ... BM79: =+Precios!BL77*Precios!BL$3 -> 0
A80: =+SUM(C80:XFD80) -> 50000 | B80: =+Precios!A78 -> 46080 | C80: =+Precios!B78*Precios!B$3 -> 0 | D80: =+Precios!C78*Precios!C$3 -> 0 | E80: =+Precios!D78*Precios!D$3 -> 0 | F80: =+Precios!E78*Precios!E$3 -> 0 | G80: =+Precios!F78*Precios!F$3 -> 0 | H80: =+Precios!G78*Precios!G$3 -> 0 | I80: =+Precios!H78*Precios!H$3 -> 0 | J80: =+Precios!I78*Precios!I$3 -> 0 | ... S80: =+Precios!R78*Precios!R$3 -> 0 | AO80: =+AO79 -> 0 | AU80: =+AU79 -> 0 | AV80: =+AV79 -> 50000 | AW80: =+AW79 -> 0 | AY80: =+AY79 -> 0 | AZ80: =+AZ79 -> 0 | BA80: =+BA79 -> 0 | BB80: =+BB79 -> 0 | BC80: =+BC79 -> 0 | BD80: =+Precios!BC78*Precios!BC$3 -> 0 | BE80: =+Precios!BD78*Precios!BD$3 -> 0 | BF80: =+Precios!BE78*Precios!BE$3 -> 0 | BG80: =+Precios!BF78*Precios!BF$3 -> 0 | BH80: =+Precios!BG78*Precios!BG$3 -> 0 | BI80: =+Precios!BH78*Precios!BH$3 -> 0 | BJ80: =+Precios!BI78*Precios!BI$3 -> 0 | BK80: =+Precios!BJ78*Precios!BJ$3 -> 0 | ... BM80: =+Precios!BL78*Precios!BL$3 -> 0
A81: =+SUM(C81:XFD81) -> 50000 | B81: =+Precios!A79 -> 46083 | C81: =+Precios!B79*Precios!B$3 -> 0 | D81: =+Precios!C79*Precios!C$3 -> 0 | E81: =+Precios!D79*Precios!D$3 -> 0 | F81: =+Precios!E79*Precios!E$3 -> 0 | G81: =+Precios!F79*Precios!F$3 -> 0 | H81: =+Precios!G79*Precios!G$3 -> 0 | I81: =+Precios!H79*Precios!H$3 -> 0 | J81: =+Precios!I79*Precios!I$3 -> 0 | ... S81: =+Precios!R79*Precios!R$3 -> 0 | AU81: =+AU80 -> 0 | AV81: =+AV80 -> 50000 | AW81: =+AW80 -> 0 | AY81: =+AY80 -> 0 | AZ81: =+AZ80 -> 0 | BA81: =+BA80 -> 0 | BB81: =+BB80 -> 0 | BC81: =+BC80 -> 0 | BD81: =+Precios!BC79*Precios!BC$3 -> 0 | BE81: =+Precios!BD79*Precios!BD$3 -> 0 | BF81: =+Precios!BE79*Precios!BE$3 -> 0 | BG81: =+Precios!BF79*Precios!BF$3 -> 0 | BH81: =+Precios!BG79*Precios!BG$3 -> 0 | BI81: =+Precios!BH79*Precios!BH$3 -> 0 | BJ81: =+Precios!BI79*Precios!BI$3 -> 0 | BK81: =+Precios!BJ79*Precios!BJ$3 -> 0 | ... BM81: =+Precios!BL79*Precios!BL$3 -> 0
A82: =+SUM(C82:XFD82) -> 50000 | B82: =+Precios!A80 -> 46084 | C82: =+Precios!B80*Precios!B$3 -> 0 | D82: =+Precios!C80*Precios!C$3 -> 0 | E82: =+Precios!D80*Precios!D$3 -> 0 | F82: =+Precios!E80*Precios!E$3 -> 0 | G82: =+Precios!F80*Precios!F$3 -> 0 | H82: =+Precios!G80*Precios!G$3 -> 0 | I82: =+Precios!H80*Precios!H$3 -> 0 | J82: =+Precios!I80*Precios!I$3 -> 0 | ... S82: =+Precios!R80*Precios!R$3 -> 0 | AU82: =+AU81 -> 0 | AV82: =+AV81 -> 50000 | AW82: =+AW81 -> 0 | AY82: =+AY81 -> 0 | AZ82: =+AZ81 -> 0 | BA82: =+BA81 -> 0 | BB82: =+BB81 -> 0 | BC82: =+BC81 -> 0 | BD82: =+Precios!BC80*Precios!BC$3 -> 0 | BE82: =+Precios!BD80*Precios!BD$3 -> 0 | BF82: =+Precios!BE80*Precios!BE$3 -> 0 | BG82: =+Precios!BF80*Precios!BF$3 -> 0 | BH82: =+Precios!BG80*Precios!BG$3 -> 0 | BI82: =+Precios!BH80*Precios!BH$3 -> 0 | BJ82: =+Precios!BI80*Precios!BI$3 -> 0 | BK82: =+Precios!BJ80*Precios!BJ$3 -> 0 | ... BM82: =+Precios!BL80*Precios!BL$3 -> 0
A83: =+SUM(C83:XFD83) -> 50000 | B83: =+Precios!A81 -> 46085 | C83: =+Precios!B81*Precios!B$3 -> 0 | D83: =+Precios!C81*Precios!C$3 -> 0 | E83: =+Precios!D81*Precios!D$3 -> 0 | F83: =+Precios!E81*Precios!E$3 -> 0 | G83: =+Precios!F81*Precios!F$3 -> 0 | H83: =+Precios!G81*Precios!G$3 -> 0 | I83: =+Precios!H81*Precios!H$3 -> 0 | J83: =+Precios!I81*Precios!I$3 -> 0 | ... S83: =+Precios!R81*Precios!R$3 -> 0 | AV83: =+AV82 -> 50000 | BC83: =+BC82 -> 0 | BD83: =+BD82 -> 0 | BE83: =+Precios!BD81*Precios!BD$3 -> 0 | BF83: =+Precios!BE81*Precios!BE$3 -> 0 | BG83: =+Precios!BF81*Precios!BF$3 -> 0 | BH83: =+Precios!BG81*Precios!BG$3 -> 0 | BI83: =+Precios!BH81*Precios!BH$3 -> 0 | BJ83: =+Precios!BI81*Precios!BI$3 -> 0 | BK83: =+Precios!BJ81*Precios!BJ$3 -> 0 | BL83: =+Precios!BK81*Precios!BK$3 -> 0 | BM83: =+Precios!BL81*Precios!BL$3 -> 0
A84: =+SUM(C84:XFD84) -> 100001 | B84: =+Precios!A82 -> 46086 | C84: =+Precios!B82*Precios!B$3 -> 0 | D84: =+Precios!C82*Precios!C$3 -> 0 | E84: =+Precios!D82*Precios!D$3 -> 0 | F84: =+Precios!E82*Precios!E$3 -> 0 | G84: =+Precios!F82*Precios!F$3 -> 0 | H84: =+Precios!G82*Precios!G$3 -> 0 | I84: =+Precios!H82*Precios!H$3 -> 0 | J84: =+Precios!I82*Precios!I$3 -> 0 | ... S84: =+Precios!R82*Precios!R$3 -> 0 | AV84: =+AV83 -> 50000 | BC84: =+BC83 -> 0 | BD84: =+BD83 -> 0 | BE84: =+Precios!BD82*Precios!BD$3 -> 50001 | BF84: =+Precios!BE82*Precios!BE$3 -> 0 | BG84: =+Precios!BF82*Precios!BF$3 -> 0 | BH84: =+Precios!BG82*Precios!BG$3 -> 0 | BI84: =+Precios!BH82*Precios!BH$3 -> 0 | BJ84: =+Precios!BI82*Precios!BI$3 -> 0 | BK84: =+Precios!BJ82*Precios!BJ$3 -> 0 | BL84: =+Precios!BK82*Precios!BK$3 -> 0 | BM84: =+Precios!BL82*Precios!BL$3 -> 0
A85: =+SUM(C85:XFD85) -> 100001 | B85: =+Precios!A83 -> 46087 | C85: =+Precios!B83*Precios!B$3 -> 0 | D85: =+Precios!C83*Precios!C$3 -> 0 | E85: =+Precios!D83*Precios!D$3 -> 0 | F85: =+Precios!E83*Precios!E$3 -> 0 | G85: =+Precios!F83*Precios!F$3 -> 0 | H85: =+Precios!G83*Precios!G$3 -> 0 | I85: =+Precios!H83*Precios!H$3 -> 0 | J85: =+Precios!I83*Precios!I$3 -> 0 | ... S85: =+Precios!R83*Precios!R$3 -> 0 | AV85: =+AV84 -> 50000 | BC85: =+BC84 -> 0 | BD85: =+BD84 -> 0 | BE85: =+BE84 -> 50001 | BF85: =+Precios!BE83*Precios!BE$3 -> 0 | BG85: =+Precios!BF83*Precios!BF$3 -> 0 | BH85: =+Precios!BG83*Precios!BG$3 -> 0 | BI85: =+Precios!BH83*Precios!BH$3 -> 0 | BJ85: =+Precios!BI83*Precios!BI$3 -> 0 | BK85: =+Precios!BJ83*Precios!BJ$3 -> 0 | BL85: =+Precios!BK83*Precios!BK$3 -> 0 | BM85: =+Precios!BL83*Precios!BL$3 -> 0
A86: =+SUM(C86:XFD86) -> 249963.46 | B86: =+Precios!A84 -> 46090 | C86: =+Precios!B84*Precios!B$3 -> 0 | D86: =+Precios!C84*Precios!C$3 -> 0 | E86: =+Precios!D84*Precios!D$3 -> 0 | F86: =+Precios!E84*Precios!E$3 -> 0 | G86: =+Precios!F84*Precios!F$3 -> 0 | H86: =+Precios!G84*Precios!G$3 -> 0 | I86: =+Precios!H84*Precios!H$3 -> 0 | J86: =+Precios!I84*Precios!I$3 -> 0 | ... S86: =+Precios!R84*Precios!R$3 -> 0 | AV86: =+AV85 -> 50000 | BC86: =+BC85 -> 0 | BD86: =+BD85 -> 0 | BE86: =+BE85 -> 50001 | BF86: =+TRACK!H58 -> 99960 | BG86: =+TRACK!F77*TRACK!G77 -> 50002.46 | BH86: =+Precios!BG84*Precios!BG$3 -> 0 | BI86: =+Precios!BH84*Precios!BH$3 -> 0 | BJ86: =+Precios!BI84*Precios!BI$3 -> 0 | BK86: =+Precios!BJ84*Precios!BJ$3 -> 0 | BL86: =+Precios!BK84*Precios!BK$3 -> 0 | BM86: =+Precios!BL84*Precios!BL$3 -> 0
A87: =+SUM(C87:XFD87) -> 249963.46 | B87: =+Precios!A85 -> 46091 | C87: =+Precios!B85*Precios!B$3 -> 0 | D87: =+Precios!C85*Precios!C$3 -> 0 | E87: =+Precios!D85*Precios!D$3 -> 0 | F87: =+Precios!E85*Precios!E$3 -> 0 | G87: =+Precios!F85*Precios!F$3 -> 0 | H87: =+Precios!G85*Precios!G$3 -> 0 | I87: =+Precios!H85*Precios!H$3 -> 0 | J87: =+Precios!I85*Precios!I$3 -> 0 | ... S87: =+Precios!R85*Precios!R$3 -> 0 | AV87: =+AV86 -> 50000 | BC87: =+BC86 -> 0 | BD87: =+BD86 -> 0 | BE87: =+BE86 -> 50001 | BF87: =+BF86 -> 99960 | BG87: =+BG86 -> 50002.46 | BH87: =+Precios!BG85*Precios!BG$3 -> 0 | BI87: =+Precios!BH85*Precios!BH$3 -> 0 | BJ87: =+Precios!BI85*Precios!BI$3 -> 0 | BK87: =+Precios!BJ85*Precios!BJ$3 -> 0 | BL87: =+Precios!BK85*Precios!BK$3 -> 0 | BM87: =+Precios!BL85*Precios!BL$3 -> 0
A88: =+SUM(C88:XFD88) -> 249963.46 | B88: =+Precios!A86 -> 46092 | C88: =+Precios!B86*Precios!B$3 -> 0 | D88: =+Precios!C86*Precios!C$3 -> 0 | E88: =+Precios!D86*Precios!D$3 -> 0 | F88: =+Precios!E86*Precios!E$3 -> 0 | G88: =+Precios!F86*Precios!F$3 -> 0 | H88: =+Precios!G86*Precios!G$3 -> 0 | I88: =+Precios!H86*Precios!H$3 -> 0 | J88: =+Precios!I86*Precios!I$3 -> 0 | ... S88: =+Precios!R86*Precios!R$3 -> 0 | AV88: =+AV87 -> 50000 | BC88: =+BC87 -> 0 | BD88: =+BD87 -> 0 | BE88: =+BE87 -> 50001 | BF88: =+BF87 -> 99960 | BG88: =+BG87 -> 50002.46 | BH88: =+Precios!BG86*Precios!BG$3 -> 0 | BI88: =+Precios!BH86*Precios!BH$3 -> 0 | BJ88: =+Precios!BI86*Precios!BI$3 -> 0 | BK88: =+Precios!BJ86*Precios!BJ$3 -> 0 | BL88: =+Precios!BK86*Precios!BK$3 -> 0 | BM88: =+Precios!BL86*Precios!BL$3 -> 0
A89: =+SUM(C89:XFD89) -> 249963.46 | B89: =+Precios!A87 -> 46093 | C89: =+Precios!B87*Precios!B$3 -> 0 | D89: =+Precios!C87*Precios!C$3 -> 0 | E89: =+Precios!D87*Precios!D$3 -> 0 | F89: =+Precios!E87*Precios!E$3 -> 0 | G89: =+Precios!F87*Precios!F$3 -> 0 | H89: =+Precios!G87*Precios!G$3 -> 0 | I89: =+Precios!H87*Precios!H$3 -> 0 | J89: =+Precios!I87*Precios!I$3 -> 0 | ... S89: =+Precios!R87*Precios!R$3 -> 0 | AV89: =+AV88 -> 50000 | BC89: =+BC88 -> 0 | BD89: =+BD88 -> 0 | BE89: =+BE88 -> 50001 | BF89: =+BF88 -> 99960 | BG89: =+BG88 -> 50002.46 | BH89: =+Precios!BG87*Precios!BG$3 -> 0 | BI89: =+Precios!BH87*Precios!BH$3 -> 0 | BJ89: =+Precios!BI87*Precios!BI$3 -> 0 | BK89: =+Precios!BJ87*Precios!BJ$3 -> 0 | BL89: =+Precios!BK87*Precios!BK$3 -> 0 | BM89: =+Precios!BL87*Precios!BL$3 -> 0
A90: =+SUM(C90:XFD90) -> 249963.46 | B90: =+Precios!A88 -> 46094 | C90: =+Precios!B88*Precios!B$3 -> 0 | D90: =+Precios!C88*Precios!C$3 -> 0 | E90: =+Precios!D88*Precios!D$3 -> 0 | F90: =+Precios!E88*Precios!E$3 -> 0 | G90: =+Precios!F88*Precios!F$3 -> 0 | H90: =+Precios!G88*Precios!G$3 -> 0 | I90: =+Precios!H88*Precios!H$3 -> 0 | J90: =+Precios!I88*Precios!I$3 -> 0 | ... S90: =+Precios!R88*Precios!R$3 -> 0 | AV90: =+AV89 -> 50000 | BC90: =+BC89 -> 0 | BD90: =+BD89 -> 0 | BE90: =+BE89 -> 50001 | BF90: =+BF89 -> 99960 | BG90: =+BG89 -> 50002.46 | BH90: =+BH89 -> 0 | BI90: =+Precios!BH88*Precios!BH$3 -> 0 | BJ90: =+Precios!BI88*Precios!BI$3 -> 0 | BK90: =+Precios!BJ88*Precios!BJ$3 -> 0 | BL90: =+Precios!BK88*Precios!BK$3 -> 0 | BM90: =+Precios!BL88*Precios!BL$3 -> 0
A91: =+SUM(C91:XFD91) -> 249963.46 | B91: =+Precios!A89 -> 46097 | C91: =+Precios!B89*Precios!B$3 -> 0 | D91: =+Precios!C89*Precios!C$3 -> 0 | E91: =+Precios!D89*Precios!D$3 -> 0 | F91: =+Precios!E89*Precios!E$3 -> 0 | G91: =+Precios!F89*Precios!F$3 -> 0 | H91: =+Precios!G89*Precios!G$3 -> 0 | I91: =+Precios!H89*Precios!H$3 -> 0 | J91: =+Precios!I89*Precios!I$3 -> 0 | ... S91: =+Precios!R89*Precios!R$3 -> 0 | AV91: =+AV90 -> 50000 | BC91: =+BC90 -> 0 | BD91: =+BD90 -> 0 | BE91: =+BE90 -> 50001 | BF91: =+BF90 -> 99960 | BG91: =+BG90 -> 50002.46 | BH91: =+BH90 -> 0 | BI91: =+Precios!BH89*Precios!BH$3 -> 0 | BJ91: =+Precios!BI89*Precios!BI$3 -> 0 | BK91: =+Precios!BJ89*Precios!BJ$3 -> 0 | BL91: =+Precios!BK89*Precios!BK$3 -> 0 | BM91: =+Precios!BL89*Precios!BL$3 -> 0
A92: =+SUM(C92:XFD92) -> 249963.46 | B92: =+Precios!A90 -> 46098 | C92: =+Precios!B90*Precios!B$3 -> 0 | D92: =+Precios!C90*Precios!C$3 -> 0 | E92: =+Precios!D90*Precios!D$3 -> 0 | F92: =+Precios!E90*Precios!E$3 -> 0 | G92: =+Precios!F90*Precios!F$3 -> 0 | H92: =+Precios!G90*Precios!G$3 -> 0 | I92: =+Precios!H90*Precios!H$3 -> 0 | J92: =+Precios!I90*Precios!I$3 -> 0 | ... S92: =+Precios!R90*Precios!R$3 -> 0 | AV92: =+AV91 -> 50000 | BC92: =+BC91 -> 0 | BD92: =+BD91 -> 0 | BE92: =+BE91 -> 50001 | BF92: =+BF91 -> 99960 | BG92: =+BG91 -> 50002.46 | BH92: =+BH91 -> 0 | BI92: =+BI91 -> 0 | BJ92: =+Precios!BI90*Precios!BI$3 -> 0 | BK92: =+Precios!BJ90*Precios!BJ$3 -> 0 | BL92: =+Precios!BK90*Precios!BK$3 -> 0 | BM92: =+Precios!BL90*Precios!BL$3 -> 0
A93: =+SUM(C93:XFD93) -> 249963.46 | B93: =+Precios!A91 -> 46099 | C93: =+Precios!B91*Precios!B$3 -> 0 | D93: =+Precios!C91*Precios!C$3 -> 0 | E93: =+Precios!D91*Precios!D$3 -> 0 | F93: =+Precios!E91*Precios!E$3 -> 0 | G93: =+Precios!F91*Precios!F$3 -> 0 | H93: =+Precios!G91*Precios!G$3 -> 0 | I93: =+Precios!H91*Precios!H$3 -> 0 | J93: =+Precios!I91*Precios!I$3 -> 0 | ... S93: =+Precios!R91*Precios!R$3 -> 0 | AV93: =+AV92 -> 50000 | BC93: =+BC92 -> 0 | BD93: =+BD92 -> 0 | BE93: =+BE92 -> 50001 | BF93: =+BF92 -> 99960 | BG93: =+BG92 -> 50002.46 | BH93: =+BH92 -> 0 | BI93: =+BI92 -> 0 | BJ93: =+Precios!BI91*Precios!BI$3 -> 0 | BK93: =+Precios!BJ91*Precios!BJ$3 -> 0 | BL93: =+Precios!BK91*Precios!BK$3 -> 0 | BM93: =+Precios!BL91*Precios!BL$3 -> 0
A94: =+SUM(C94:XFD94) -> 299963.46 | B94: =+Precios!A92 -> 46100 | C94: =+Precios!B92*Precios!B$3 -> 0 | D94: =+Precios!C92*Precios!C$3 -> 0 | E94: =+Precios!D92*Precios!D$3 -> 0 | F94: =+Precios!E92*Precios!E$3 -> 0 | G94: =+Precios!F92*Precios!F$3 -> 0 | H94: =+Precios!G92*Precios!G$3 -> 0 | I94: =+Precios!H92*Precios!H$3 -> 0 | J94: =+Precios!I92*Precios!I$3 -> 0 | ... S94: =+Precios!R92*Precios!R$3 -> 0 | AV94: =+AV93 -> 50000 | BC94: =+BC93 -> 0 | BD94: =+BD93 -> 0 | BE94: =+BE93 -> 50001 | BF94: =+BF93 -> 99960 | BG94: =+BG93 -> 50002.46 | BH94: =+BH93 -> 0 | BI94: =+BI93 -> 0 | BJ94: 50000 | BK94: =+Precios!BJ92*Precios!BJ$3 -> 0 | BL94: =+Precios!BK92*Precios!BK$3 -> 0 | BM94: =+Precios!BL92*Precios!BL$3 -> 0
A95: =+SUM(C95:XFD95) -> 299963.46 | B95: =+Precios!A93 -> 46101 | C95: =+Precios!B93*Precios!B$3 -> 0 | D95: =+Precios!C93*Precios!C$3 -> 0 | E95: =+Precios!D93*Precios!D$3 -> 0 | F95: =+Precios!E93*Precios!E$3 -> 0 | G95: =+Precios!F93*Precios!F$3 -> 0 | H95: =+Precios!G93*Precios!G$3 -> 0 | I95: =+Precios!H93*Precios!H$3 -> 0 | J95: =+Precios!I93*Precios!I$3 -> 0 | ... S95: =+Precios!R93*Precios!R$3 -> 0 | AV95: =+AV94 -> 50000 | BC95: =+BC94 -> 0 | BE95: =+BE94 -> 50001 | BF95: =+BF94 -> 99960 | BG95: =+BG94 -> 50002.46 | BJ95: =+BJ94 -> 50000 | BK95: =+Precios!BJ93*Precios!BJ$3 -> 0 | BL95: =+Precios!BK93*Precios!BK$3 -> 0 | BM95: =+Precios!BL93*Precios!BL$3 -> 0
A96: =+SUM(C96:XFD96) -> 299963.46 | B96: =+Precios!A94 -> 46104 | C96: =+Precios!B94*Precios!B$3 -> 0 | D96: =+Precios!C94*Precios!C$3 -> 0 | E96: =+Precios!D94*Precios!D$3 -> 0 | F96: =+Precios!E94*Precios!E$3 -> 0 | G96: =+Precios!F94*Precios!F$3 -> 0 | H96: =+Precios!G94*Precios!G$3 -> 0 | I96: =+Precios!H94*Precios!H$3 -> 0 | J96: =+Precios!I94*Precios!I$3 -> 0 | ... S96: =+Precios!R94*Precios!R$3 -> 0 | AV96: =+AV95 -> 50000 | BC96: =+BC95 -> 0 | BE96: =+BE95 -> 50001 | BF96: =+BF95 -> 99960 | BG96: =+BG95 -> 50002.46 | BJ96: =+BJ95 -> 50000 | BK96: =+Precios!BJ94*Precios!BJ$3 -> 0 | BL96: =+Precios!BK94*Precios!BK$3 -> 0 | BM96: =+Precios!BL94*Precios!BL$3 -> 0
A97: =+SUM(C97:XFD97) -> 299963.46 | B97: =+Precios!A95 -> 46105 | C97: =+Precios!B95*Precios!B$3 -> 0 | D97: =+Precios!C95*Precios!C$3 -> 0 | E97: =+Precios!D95*Precios!D$3 -> 0 | F97: =+Precios!E95*Precios!E$3 -> 0 | G97: =+Precios!F95*Precios!F$3 -> 0 | H97: =+Precios!G95*Precios!G$3 -> 0 | I97: =+Precios!H95*Precios!H$3 -> 0 | J97: =+Precios!I95*Precios!I$3 -> 0 | ... S97: =+Precios!R95*Precios!R$3 -> 0 | AV97: =+AV96 -> 50000 | BC97: =+BC96 -> 0 | BE97: =+BE96 -> 50001 | BF97: =+BF96 -> 99960 | BG97: =+BG96 -> 50002.46 | BJ97: =+BJ96 -> 50000 | BK97: =+Precios!BJ95*Precios!BJ$3 -> 0 | BL97: =+Precios!BK95*Precios!BK$3 -> 0 | BM97: =+Precios!BL95*Precios!BL$3 -> 0
A98: =+SUM(C98:XFD98) -> 249963.46 | B98: =+Precios!A96 -> 46106 | C98: =+Precios!B96*Precios!B$3 -> 0 | D98: =+Precios!C96*Precios!C$3 -> 0 | E98: =+Precios!D96*Precios!D$3 -> 0 | F98: =+Precios!E96*Precios!E$3 -> 0 | G98: =+Precios!F96*Precios!F$3 -> 0 | H98: =+Precios!G96*Precios!G$3 -> 0 | I98: =+Precios!H96*Precios!H$3 -> 0 | J98: =+Precios!I96*Precios!I$3 -> 0 | ... S98: =+Precios!R96*Precios!R$3 -> 0 | AV98: =+AV97 -> 50000 | BC98: =+BC97 -> 0 | BE98: =+BE97 -> 50001 | BF98: =+BF97 -> 99960 | BG98: =+BG97 -> 50002.46 | BK98: =+Precios!BJ96*Precios!BJ$3 -> 0 | BL98: =+Precios!BK96*Precios!BK$3 -> 0 | BM98: =+Precios!BL96*Precios!BL$3 -> 0
A99: =+SUM(C99:XFD99) -> 249963.46 | B99: =+Precios!A97 -> 46107 | C99: =+Precios!B97*Precios!B$3 -> 0 | D99: =+Precios!C97*Precios!C$3 -> 0 | E99: =+Precios!D97*Precios!D$3 -> 0 | F99: =+Precios!E97*Precios!E$3 -> 0 | G99: =+Precios!F97*Precios!F$3 -> 0 | H99: =+Precios!G97*Precios!G$3 -> 0 | I99: =+Precios!H97*Precios!H$3 -> 0 | J99: =+Precios!I97*Precios!I$3 -> 0 | ... S99: =+Precios!R97*Precios!R$3 -> 0 | AV99: =+AV98 -> 50000 | BC99: =+BC98 -> 0 | BE99: =+BE98 -> 50001 | BF99: =+BF98 -> 99960 | BG99: =+BG98 -> 50002.46 | BK99: =+Precios!BJ97*Precios!BJ$3 -> 0 | BL99: =+Precios!BK97*Precios!BK$3 -> 0 | BM99: =+Precios!BL97*Precios!BL$3 -> 0
A100: =+SUM(C100:XFD100) -> 249963.46 | B100: =+Precios!A98 -> 46108 | C100: =+Precios!B98*Precios!B$3 -> 0 | D100: =+Precios!C98*Precios!C$3 -> 0 | E100: =+Precios!D98*Precios!D$3 -> 0 | F100: =+Precios!E98*Precios!E$3 -> 0 | G100: =+Precios!F98*Precios!F$3 -> 0 | H100: =+Precios!G98*Precios!G$3 -> 0 | I100: =+Precios!H98*Precios!H$3 -> 0 | J100: =+Precios!I98*Precios!I$3 -> 0 | ... S100: =+Precios!R98*Precios!R$3 -> 0 | AV100: =+AV99 -> 50000 | BC100: =+BC99 -> 0 | BE100: =+BE99 -> 50001 | BF100: =+BF99 -> 99960 | BG100: =+BG99 -> 50002.46 | BK100: =+Precios!BJ98*Precios!BJ$3 -> 0 | BL100: =+Precios!BK98*Precios!BK$3 -> 0 | BM100: =+Precios!BL98*Precios!BL$3 -> 0
...

Sheet Value
E1: =+Precios!A1 -> BUY | F1: =+Precios!B1 -> 45985 | G1: =+Precios!C1 -> 45993 | H1: =+Precios!D1 -> 46001 | I1: =+Precios!E1 -> 46003 | J1: =+Precios!F1 -> 46002 | K1: =+Precios!G1 -> 46000 | L1: =+Precios!H1 -> 45981 | ... AX1: =+Precios!AT1 -> 46065 | AY1: 46070 | AZ1: =+Precios!AV1 -> 46071 | BA1: =+Precios!AW1 -> 46071 | BB1: =+Precios!AX1 -> 46071 | BC1: =+Precios!AY1 -> 46072 | BD1: =+Precios!AZ1 -> 46072 | BE1: =+Precios!BA1 -> 46073 | BF1: =+Precios!BB1 -> 46079 | BG1: =+Precios!BC1 -> 46084 | ... BY1: =+Precios!BU1 -> 46127
E2: =+Precios!A2 -> SELL | F2: =+Precios!B2 -> 45995 | G2: =+Precios!C2 -> 45995 | H2: =+Precios!D2 -> 46003 | I2: =+Precios!E2 -> 46003 | J2: =+Precios!F2 -> 46003 | K2: =+Precios!G2 -> 46003 | L2: =+Precios!H2 -> 46006 | ... AX2: =+Precios!AT2 -> 46084 | AZ2: =+Precios!AV2 -> 46084 | BA2: =+Precios!AW2 -> 46078 | BB2: =+Precios!AX2 -> 46084 | BC2: =+Precios!AY2 -> 46084 | BD2: =+Precios!AZ2 -> 46084 | BE2: =+Precios!BA2 -> 46084 | BF2: =+Precios!BB2 -> 46121 | BG2: =+Precios!BC2 -> 46100 | ... BY2: =+Precios!BU2 -> 0
C3: Acum Realised | E3: =+Precios!A3 -> Shares | F3: =+Precios!B3 -> 0 | G3: =+Precios!C3 -> 0 | H3: =+Precios!D3 -> 0 | I3: =+Precios!E3 -> 0 | J3: =+Precios!F3 -> 0 | K3: =+Precios!G3 -> 0 | L3: =+Precios!H3 -> 0 | ... AX3: =+Precios!AT3 -> 0 | AY3: 4039 | AZ3: =+Precios!AV3 -> 0 | BA3: =+Precios!AW3 -> 0 | BB3: =+Precios!AX3 -> 0 | BC3: =+Precios!AY3 -> 0 | BD3: =+Precios!AZ3 -> 0 | BE3: =+Precios!BA3 -> 0 | BF3: =+Precios!BB3 -> 0 | BG3: =+Precios!BC3 -> 0 | ... BY3: =+Precios!BU3 -> 1027
AY4: =+Cost!AV4 -> 2019 | BH4: =+Cost!BE4 -> 12143 | BN4: =+Cost!BK4 -> 352 | BO4: =+Cost!BL4 -> 273 | BR4: =+Cost!BO4 -> 2200 | BT4: =+Cost!BQ4 -> 2757 | BU4: =+Cost!BR4 -> 3603 | BV4: =+Cost!BS4 -> 6734
BN5: =+Cost!BK5 -> 289 | BO5: =+Cost!BL5 -> 241 | BV5: =+Cost!BS5 -> 5942
A6: Invested | B6: Realised | D6: Cash | E6: =+Precios!A4 -> 0 | F6: =+Precios!B4 -> 0 | G6: =+Precios!C4 -> 0 | H6: =+Precios!D4 -> 0 | I6: =+Precios!E4 -> 0 | J6: =+Precios!F4 -> 0 | K6: =+Precios!G4 -> 0 | L6: =+Precios!H4 -> 0 | ... AX6: =+Precios!AT4 -> 0 | AY6: CGEM | AZ6: =+Precios!AV4 -> 0 | BA6: =+Precios!AW4 -> 0 | BB6: =+Precios!AX4 -> 0 | BC6: =+Precios!AY4 -> 0 | BD6: =+Precios!AZ4 -> 0 | BE6: =+Precios!BA4 -> 0 | BF6: =+Precios!BB4 -> 0 | BG6: =+Precios!BC4 -> 0 | ... BY6: =+Precios!BU4 -> YOU
A7: =+SUM(F7:XFD7) -> 0 | C7: =+B7 -> 0 | D7: =1000000+C7-Cost!A7 -> 1000000 | E7: =+Precios!A5 -> 45979 | F7: =+Precios!B5*Precios!B$3 -> 0 | G7: =+Precios!C5*Precios!C$3 -> 0 | H7: =+Precios!D5*Precios!D$3 -> 0 | I7: =+Precios!E5*Precios!E$3 -> 0 | J7: =+Precios!F5*Precios!F$3 -> 0 | K7: =+Precios!G5*Precios!G$3 -> 0 | L7: =+Precios!H5*Precios!H$3 -> 0 | M7: =+Precios!I5*Precios!I$3 -> 0 | ... AX7: =+Precios!AT5*Precios!AT$3 -> 0 | AY7: =+Precios!AU5*$AY$3 -> 0 | AZ7: =+Precios!AV5*Precios!AV$3 -> 0 | BA7: =+Precios!AW5*Precios!AW$3 -> 0 | BB7: =+Precios!AX5*Precios!AX$3 -> 0 | BC7: =+Precios!AY5*Precios!AY$3 -> 0 | BD7: =+Precios!AZ5*Precios!AZ$3 -> 0 | BE7: =+Precios!BA5*Precios!BA$3 -> 0 | BF7: =+Precios!BB5*Precios!BB$3 -> 0 | BG7: =+Precios!BC5*Precios!BC$3 -> 0 | BH7: =+Precios!BD5*$BH$3 -> 0 | BI7: =+Precios!BE5*Precios!BE$3 -> 0 | BJ7: =+Precios!BF5*Precios!BF$3 -> 0 | BK7: =+Precios!BG5*Precios!BG$3 -> 0 | BL7: =+Precios!BH5*Precios!BH$3 -> 0 | BM7: =+Precios!BI5*Precios!BI$3 -> 0 | BN7: =+Precios!BJ5*$BN$3 -> 0 | BO7: =+Precios!BK5*$BO$3 -> 0 | BP7: =+Precios!BL5*Precios!BL$3 -> 0
A8: =+SUM(F8:XFD8) -> 0 | C8: =+C7+B8 -> 0 | D8: =1000000+C8-Cost!A8 -> 1000000 | E8: =+Precios!A6 -> 45980 | F8: =+Precios!B6*Precios!B$3 -> 0 | G8: =+Precios!C6*Precios!C$3 -> 0 | H8: =+Precios!D6*Precios!D$3 -> 0 | I8: =+Precios!E6*Precios!E$3 -> 0 | J8: =+Precios!F6*Precios!F$3 -> 0 | K8: =+Precios!G6*Precios!G$3 -> 0 | L8: =+Precios!H6*Precios!H$3 -> 0 | M8: =+Precios!I6*Precios!I$3 -> 0 | ... AX8: =+Precios!AT6*Precios!AT$3 -> 0 | AY8: =+Precios!AU6*$AY$3 -> 0 | AZ8: =+Precios!AV6*Precios!AV$3 -> 0 | BA8: =+Precios!AW6*Precios!AW$3 -> 0 | BB8: =+Precios!AX6*Precios!AX$3 -> 0 | BC8: =+Precios!AY6*Precios!AY$3 -> 0 | BD8: =+Precios!AZ6*Precios!AZ$3 -> 0 | BE8: =+Precios!BA6*Precios!BA$3 -> 0 | BF8: =+Precios!BB6*Precios!BB$3 -> 0 | BG8: =+Precios!BC6*Precios!BC$3 -> 0 | BH8: =+Precios!BD6*$BH$3 -> 0 | BI8: =+Precios!BE6*Precios!BE$3 -> 0 | BJ8: =+Precios!BF6*Precios!BF$3 -> 0 | BK8: =+Precios!BG6*Precios!BG$3 -> 0 | BL8: =+Precios!BH6*Precios!BH$3 -> 0 | BM8: =+Precios!BI6*Precios!BI$3 -> 0 | BN8: =+Precios!BJ6*$BN$3 -> 0 | BO8: =+Precios!BK6*$BO$3 -> 0 | BP8: =+Precios!BL6*Precios!BL$3 -> 0
A9: =+SUM(F9:XFD9) -> 0 | C9: =+C8+B9 -> 0 | D9: =1000000+C9-Cost!A9 -> 1000000 | E9: =+Precios!A7 -> 45981 | F9: =+Precios!B7*Precios!B$3 -> 0 | G9: =+Precios!C7*Precios!C$3 -> 0 | H9: =+Precios!D7*Precios!D$3 -> 0 | I9: =+Precios!E7*Precios!E$3 -> 0 | J9: =+Precios!F7*Precios!F$3 -> 0 | K9: =+Precios!G7*Precios!G$3 -> 0 | L9: =+Precios!H7*Precios!H$3 -> 0 | M9: =+Precios!I7*Precios!I$3 -> 0 | ... AX9: =+Precios!AT7*Precios!AT$3 -> 0 | AY9: =+Precios!AU7*$AY$3 -> 0 | AZ9: =+Precios!AV7*Precios!AV$3 -> 0 | BA9: =+Precios!AW7*Precios!AW$3 -> 0 | BB9: =+Precios!AX7*Precios!AX$3 -> 0 | BC9: =+Precios!AY7*Precios!AY$3 -> 0 | BD9: =+Precios!AZ7*Precios!AZ$3 -> 0 | BE9: =+Precios!BA7*Precios!BA$3 -> 0 | BF9: =+Precios!BB7*Precios!BB$3 -> 0 | BG9: =+Precios!BC7*Precios!BC$3 -> 0 | BH9: =+Precios!BD7*$BH$3 -> 0 | BI9: =+Precios!BE7*Precios!BE$3 -> 0 | BJ9: =+Precios!BF7*Precios!BF$3 -> 0 | BK9: =+Precios!BG7*Precios!BG$3 -> 0 | BL9: =+Precios!BH7*Precios!BH$3 -> 0 | BM9: =+Precios!BI7*Precios!BI$3 -> 0 | BN9: =+Precios!BJ7*$BN$3 -> 0 | BO9: =+Precios!BK7*$BO$3 -> 0 | BP9: =+Precios!BL7*Precios!BL$3 -> 0
A10: =+SUM(F10:XFD10) -> 0 | C10: =+C9+B10 -> 0 | D10: =1000000+C10-Cost!A10 -> 1000000 | E10: =+Precios!A8 -> 45982 | F10: =+Precios!B8*Precios!B$3 -> 0 | G10: =+Precios!C8*Precios!C$3 -> 0 | H10: =+Precios!D8*Precios!D$3 -> 0 | I10: =+Precios!E8*Precios!E$3 -> 0 | J10: =+Precios!F8*Precios!F$3 -> 0 | K10: =+Precios!G8*Precios!G$3 -> 0 | L10: =+Precios!H8*Precios!H$3 -> 0 | M10: =+Precios!I8*Precios!I$3 -> 0 | ... AX10: =+Precios!AT8*Precios!AT$3 -> 0 | AY10: =+Precios!AU8*$AY$3 -> 0 | AZ10: =+Precios!AV8*Precios!AV$3 -> 0 | BA10: =+Precios!AW8*Precios!AW$3 -> 0 | BB10: =+Precios!AX8*Precios!AX$3 -> 0 | BC10: =+Precios!AY8*Precios!AY$3 -> 0 | BD10: =+Precios!AZ8*Precios!AZ$3 -> 0 | BE10: =+Precios!BA8*Precios!BA$3 -> 0 | BF10: =+Precios!BB8*Precios!BB$3 -> 0 | BG10: =+Precios!BC8*Precios!BC$3 -> 0 | BH10: =+Precios!BD8*$BH$3 -> 0 | BI10: =+Precios!BE8*Precios!BE$3 -> 0 | BJ10: =+Precios!BF8*Precios!BF$3 -> 0 | BK10: =+Precios!BG8*Precios!BG$3 -> 0 | BL10: =+Precios!BH8*Precios!BH$3 -> 0 | BM10: =+Precios!BI8*Precios!BI$3 -> 0 | BN10: =+Precios!BJ8*$BN$3 -> 0 | BO10: =+Precios!BK8*$BO$3 -> 0 | BP10: =+Precios!BL8*Precios!BL$3 -> 0
A11: =+SUM(F11:XFD11) -> 0 | C11: =+C10+B11 -> 0 | D11: =1000000+C11-Cost!A11 -> 1000000 | E11: =+Precios!A9 -> 45985 | F11: =+Precios!B9*Precios!B$3 -> 0 | G11: =+Precios!C9*Precios!C$3 -> 0 | H11: =+Precios!D9*Precios!D$3 -> 0 | I11: =+Precios!E9*Precios!E$3 -> 0 | J11: =+Precios!F9*Precios!F$3 -> 0 | K11: =+Precios!G9*Precios!G$3 -> 0 | L11: =+Precios!H9*Precios!H$3 -> 0 | M11: =+Precios!I9*Precios!I$3 -> 0 | ... AX11: =+Precios!AT9*Precios!AT$3 -> 0 | AY11: =+Precios!AU9*$AY$3 -> 0 | AZ11: =+Precios!AV9*Precios!AV$3 -> 0 | BA11: =+Precios!AW9*Precios!AW$3 -> 0 | BB11: =+Precios!AX9*Precios!AX$3 -> 0 | BC11: =+Precios!AY9*Precios!AY$3 -> 0 | BD11: =+Precios!AZ9*Precios!AZ$3 -> 0 | BE11: =+Precios!BA9*Precios!BA$3 -> 0 | BF11: =+Precios!BB9*Precios!BB$3 -> 0 | BG11: =+Precios!BC9*Precios!BC$3 -> 0 | BH11: =+Precios!BD9*$BH$3 -> 0 | BI11: =+Precios!BE9*Precios!BE$3 -> 0 | BJ11: =+Precios!BF9*Precios!BF$3 -> 0 | BK11: =+Precios!BG9*Precios!BG$3 -> 0 | BL11: =+Precios!BH9*Precios!BH$3 -> 0 | BM11: =+Precios!BI9*Precios!BI$3 -> 0 | BN11: =+Precios!BJ9*$BN$3 -> 0 | BO11: =+Precios!BK9*$BO$3 -> 0 | BP11: =+Precios!BL9*Precios!BL$3 -> 0
A12: =+SUM(F12:XFD12) -> 0 | C12: =+C11+B12 -> 0 | D12: =1000000+C12-Cost!A12 -> 1000000 | E12: =+Precios!A10 -> 45986 | F12: =+Precios!B10*Precios!B$3 -> 0 | G12: =+Precios!C10*Precios!C$3 -> 0 | H12: =+Precios!D10*Precios!D$3 -> 0 | I12: =+Precios!E10*Precios!E$3 -> 0 | J12: =+Precios!F10*Precios!F$3 -> 0 | K12: =+Precios!G10*Precios!G$3 -> 0 | L12: =+Precios!H10*Precios!H$3 -> 0 | M12: =+Precios!I10*Precios!I$3 -> 0 | ... AX12: =+Precios!AT10*Precios!AT$3 -> 0 | AY12: =+Precios!AU10*$AY$3 -> 0 | AZ12: =+Precios!AV10*Precios!AV$3 -> 0 | BA12: =+Precios!AW10*Precios!AW$3 -> 0 | BB12: =+Precios!AX10*Precios!AX$3 -> 0 | BC12: =+Precios!AY10*Precios!AY$3 -> 0 | BD12: =+Precios!AZ10*Precios!AZ$3 -> 0 | BE12: =+Precios!BA10*Precios!BA$3 -> 0 | BF12: =+Precios!BB10*Precios!BB$3 -> 0 | BG12: =+Precios!BC10*Precios!BC$3 -> 0 | BH12: =+Precios!BD10*$BH$3 -> 0 | BI12: =+Precios!BE10*Precios!BE$3 -> 0 | BJ12: =+Precios!BF10*Precios!BF$3 -> 0 | BK12: =+Precios!BG10*Precios!BG$3 -> 0 | BL12: =+Precios!BH10*Precios!BH$3 -> 0 | BM12: =+Precios!BI10*Precios!BI$3 -> 0 | BN12: =+Precios!BJ10*$BN$3 -> 0 | BO12: =+Precios!BK10*$BO$3 -> 0 | BP12: =+Precios!BL10*Precios!BL$3 -> 0
A13: =+SUM(F13:XFD13) -> 0 | C13: =+C12+B13 -> 0 | D13: =1000000+C13-Cost!A13 -> 1000000 | E13: =+Precios!A11 -> 45987 | F13: =+Precios!B11*Precios!B$3 -> 0 | G13: =+Precios!C11*Precios!C$3 -> 0 | H13: =+Precios!D11*Precios!D$3 -> 0 | I13: =+Precios!E11*Precios!E$3 -> 0 | J13: =+Precios!F11*Precios!F$3 -> 0 | K13: =+Precios!G11*Precios!G$3 -> 0 | L13: =+Precios!H11*Precios!H$3 -> 0 | M13: =+Precios!I11*Precios!I$3 -> 0 | ... AX13: =+Precios!AT11*Precios!AT$3 -> 0 | AY13: =+Precios!AU11*$AY$3 -> 0 | AZ13: =+Precios!AV11*Precios!AV$3 -> 0 | BA13: =+Precios!AW11*Precios!AW$3 -> 0 | BB13: =+Precios!AX11*Precios!AX$3 -> 0 | BC13: =+Precios!AY11*Precios!AY$3 -> 0 | BD13: =+Precios!AZ11*Precios!AZ$3 -> 0 | BE13: =+Precios!BA11*Precios!BA$3 -> 0 | BF13: =+Precios!BB11*Precios!BB$3 -> 0 | BG13: =+Precios!BC11*Precios!BC$3 -> 0 | BH13: =+Precios!BD11*$BH$3 -> 0 | BI13: =+Precios!BE11*Precios!BE$3 -> 0 | BJ13: =+Precios!BF11*Precios!BF$3 -> 0 | BK13: =+Precios!BG11*Precios!BG$3 -> 0 | BL13: =+Precios!BH11*Precios!BH$3 -> 0 | BM13: =+Precios!BI11*Precios!BI$3 -> 0 | BN13: =+Precios!BJ11*$BN$3 -> 0 | BO13: =+Precios!BK11*$BO$3 -> 0 | BP13: =+Precios!BL11*Precios!BL$3 -> 0
A14: =+SUM(F14:XFD14) -> 0 | C14: =+C13+B14 -> 0 | D14: =1000000+C14-Cost!A14 -> 1000000 | E14: =+Precios!A12 -> 45988 | F14: =+Precios!B12*Precios!B$3 -> 0 | G14: =+Precios!C12*Precios!C$3 -> 0 | H14: =+Precios!D12*Precios!D$3 -> 0 | I14: =+Precios!E12*Precios!E$3 -> 0 | J14: =+Precios!F12*Precios!F$3 -> 0 | K14: =+Precios!G12*Precios!G$3 -> 0 | L14: =+Precios!H12*Precios!H$3 -> 0 | M14: =+Precios!I12*Precios!I$3 -> 0 | ... AX14: =+Precios!AT12*Precios!AT$3 -> 0 | AY14: =+Precios!AU12*$AY$3 -> 0 | AZ14: =+Precios!AV12*Precios!AV$3 -> 0 | BA14: =+Precios!AW12*Precios!AW$3 -> 0 | BB14: =+Precios!AX12*Precios!AX$3 -> 0 | BC14: =+Precios!AY12*Precios!AY$3 -> 0 | BD14: =+Precios!AZ12*Precios!AZ$3 -> 0 | BE14: =+Precios!BA12*Precios!BA$3 -> 0 | BF14: =+Precios!BB12*Precios!BB$3 -> 0 | BG14: =+Precios!BC12*Precios!BC$3 -> 0 | BH14: =+Precios!BD12*$BH$3 -> 0 | BI14: =+Precios!BE12*Precios!BE$3 -> 0 | BJ14: =+Precios!BF12*Precios!BF$3 -> 0 | BK14: =+Precios!BG12*Precios!BG$3 -> 0 | BL14: =+Precios!BH12*Precios!BH$3 -> 0 | BM14: =+Precios!BI12*Precios!BI$3 -> 0 | BN14: =+Precios!BJ12*$BN$3 -> 0 | BO14: =+Precios!BK12*$BO$3 -> 0 | BP14: =+Precios!BL12*Precios!BL$3 -> 0
A15: =+SUM(F15:XFD15) -> 0 | C15: =+C14+B15 -> 0 | D15: =1000000+C15-Cost!A15 -> 1000000 | E15: =+Precios!A13 -> 45989 | F15: =+Precios!B13*Precios!B$3 -> 0 | G15: =+Precios!C13*Precios!C$3 -> 0 | H15: =+Precios!D13*Precios!D$3 -> 0 | I15: =+Precios!E13*Precios!E$3 -> 0 | J15: =+Precios!F13*Precios!F$3 -> 0 | K15: =+Precios!G13*Precios!G$3 -> 0 | L15: =+Precios!H13*Precios!H$3 -> 0 | M15: =+Precios!I13*Precios!I$3 -> 0 | ... AX15: =+Precios!AT13*Precios!AT$3 -> 0 | AY15: =+Precios!AU13*$AY$3 -> 0 | AZ15: =+Precios!AV13*Precios!AV$3 -> 0 | BA15: =+Precios!AW13*Precios!AW$3 -> 0 | BB15: =+Precios!AX13*Precios!AX$3 -> 0 | BC15: =+Precios!AY13*Precios!AY$3 -> 0 | BD15: =+Precios!AZ13*Precios!AZ$3 -> 0 | BE15: =+Precios!BA13*Precios!BA$3 -> 0 | BF15: =+Precios!BB13*Precios!BB$3 -> 0 | BG15: =+Precios!BC13*Precios!BC$3 -> 0 | BH15: =+Precios!BD13*$BH$3 -> 0 | BI15: =+Precios!BE13*Precios!BE$3 -> 0 | BJ15: =+Precios!BF13*Precios!BF$3 -> 0 | BK15: =+Precios!BG13*Precios!BG$3 -> 0 | BL15: =+Precios!BH13*Precios!BH$3 -> 0 | BM15: =+Precios!BI13*Precios!BI$3 -> 0 | BN15: =+Precios!BJ13*$BN$3 -> 0 | BO15: =+Precios!BK13*$BO$3 -> 0 | BP15: =+Precios!BL13*Precios!BL$3 -> 0
A16: =+SUM(F16:XFD16) -> 0 | C16: =+C15+B16 -> 0 | D16: =1000000+C16-Cost!A16 -> 1000000 | E16: =+Precios!A14 -> 45992 | F16: =+Precios!B14*Precios!B$3 -> 0 | G16: =+Precios!C14*Precios!C$3 -> 0 | H16: =+Precios!D14*Precios!D$3 -> 0 | I16: =+Precios!E14*Precios!E$3 -> 0 | J16: =+Precios!F14*Precios!F$3 -> 0 | K16: =+Precios!G14*Precios!G$3 -> 0 | L16: =+Precios!H14*Precios!H$3 -> 0 | M16: =+Precios!I14*Precios!I$3 -> 0 | ... AX16: =+Precios!AT14*Precios!AT$3 -> 0 | AY16: =+Precios!AU14*$AY$3 -> 0 | AZ16: =+Precios!AV14*Precios!AV$3 -> 0 | BA16: =+Precios!AW14*Precios!AW$3 -> 0 | BB16: =+Precios!AX14*Precios!AX$3 -> 0 | BC16: =+Precios!AY14*Precios!AY$3 -> 0 | BD16: =+Precios!AZ14*Precios!AZ$3 -> 0 | BE16: =+Precios!BA14*Precios!BA$3 -> 0 | BF16: =+Precios!BB14*Precios!BB$3 -> 0 | BG16: =+Precios!BC14*Precios!BC$3 -> 0 | BH16: =+Precios!BD14*$BH$3 -> 0 | BI16: =+Precios!BE14*Precios!BE$3 -> 0 | BJ16: =+Precios!BF14*Precios!BF$3 -> 0 | BK16: =+Precios!BG14*Precios!BG$3 -> 0 | BL16: =+Precios!BH14*Precios!BH$3 -> 0 | BM16: =+Precios!BI14*Precios!BI$3 -> 0 | BN16: =+Precios!BJ14*$BN$3 -> 0 | BO16: =+Precios!BK14*$BO$3 -> 0 | BP16: =+Precios!BL14*Precios!BL$3 -> 0
A17: =+SUM(F17:XFD17) -> 0 | C17: =+C16+B17 -> 0 | D17: =1000000+C17-Cost!A17 -> 1000000 | E17: =+Precios!A15 -> 45993 | F17: =+Precios!B15*Precios!B$3 -> 0 | G17: =+Precios!C15*Precios!C$3 -> 0 | H17: =+Precios!D15*Precios!D$3 -> 0 | I17: =+Precios!E15*Precios!E$3 -> 0 | J17: =+Precios!F15*Precios!F$3 -> 0 | K17: =+Precios!G15*Precios!G$3 -> 0 | L17: =+Precios!H15*Precios!H$3 -> 0 | M17: =+Precios!I15*Precios!I$3 -> 0 | ... AX17: =+Precios!AT15*Precios!AT$3 -> 0 | AY17: =+Precios!AU15*$AY$3 -> 0 | AZ17: =+Precios!AV15*Precios!AV$3 -> 0 | BA17: =+Precios!AW15*Precios!AW$3 -> 0 | BB17: =+Precios!AX15*Precios!AX$3 -> 0 | BC17: =+Precios!AY15*Precios!AY$3 -> 0 | BD17: =+Precios!AZ15*Precios!AZ$3 -> 0 | BE17: =+Precios!BA15*Precios!BA$3 -> 0 | BF17: =+Precios!BB15*Precios!BB$3 -> 0 | BG17: =+Precios!BC15*Precios!BC$3 -> 0 | BH17: =+Precios!BD15*$BH$3 -> 0 | BI17: =+Precios!BE15*Precios!BE$3 -> 0 | BJ17: =+Precios!BF15*Precios!BF$3 -> 0 | BK17: =+Precios!BG15*Precios!BG$3 -> 0 | BL17: =+Precios!BH15*Precios!BH$3 -> 0 | BM17: =+Precios!BI15*Precios!BI$3 -> 0 | BN17: =+Precios!BJ15*$BN$3 -> 0 | BO17: =+Precios!BK15*$BO$3 -> 0 | BP17: =+Precios!BL15*Precios!BL$3 -> 0
A18: =+SUM(F18:XFD18) -> 0 | C18: =+C17+B18 -> 0 | D18: =1000000+C18-Cost!A18 -> 1000000 | E18: =+Precios!A16 -> 45994 | F18: =+Precios!B16*Precios!B$3 -> 0 | G18: =+Precios!C16*Precios!C$3 -> 0 | H18: =+Precios!D16*Precios!D$3 -> 0 | I18: =+Precios!E16*Precios!E$3 -> 0 | J18: =+Precios!F16*Precios!F$3 -> 0 | K18: =+Precios!G16*Precios!G$3 -> 0 | L18: =+Precios!H16*Precios!H$3 -> 0 | M18: =+Precios!I16*Precios!I$3 -> 0 | ... AX18: =+Precios!AT16*Precios!AT$3 -> 0 | AY18: =+Precios!AU16*$AY$3 -> 0 | AZ18: =+Precios!AV16*Precios!AV$3 -> 0 | BA18: =+Precios!AW16*Precios!AW$3 -> 0 | BB18: =+Precios!AX16*Precios!AX$3 -> 0 | BC18: =+Precios!AY16*Precios!AY$3 -> 0 | BD18: =+Precios!AZ16*Precios!AZ$3 -> 0 | BE18: =+Precios!BA16*Precios!BA$3 -> 0 | BF18: =+Precios!BB16*Precios!BB$3 -> 0 | BG18: =+Precios!BC16*Precios!BC$3 -> 0 | BH18: =+Precios!BD16*$BH$3 -> 0 | BI18: =+Precios!BE16*Precios!BE$3 -> 0 | BJ18: =+Precios!BF16*Precios!BF$3 -> 0 | BK18: =+Precios!BG16*Precios!BG$3 -> 0 | BL18: =+Precios!BH16*Precios!BH$3 -> 0 | BM18: =+Precios!BI16*Precios!BI$3 -> 0 | BN18: =+Precios!BJ16*$BN$3 -> 0 | BO18: =+Precios!BK16*$BO$3 -> 0 | BP18: =+Precios!BL16*Precios!BL$3 -> 0
A19: =+SUM(F19:XFD19) -> 0 | B19: =+TRACK!M3+TRACK!M4 -> 10271 | C19: =+C18+B19 -> 10271 | D19: =1000000+C19-Cost!A19 -> 1010271 | E19: =+Precios!A17 -> 45995 | F19: =+Precios!B17*Precios!B$3 -> 0 | G19: =+Precios!C17*Precios!C$3 -> 0 | H19: =+Precios!D17*Precios!D$3 -> 0 | I19: =+Precios!E17*Precios!E$3 -> 0 | J19: =+Precios!F17*Precios!F$3 -> 0 | K19: =+Precios!G17*Precios!G$3 -> 0 | L19: =+Precios!H17*Precios!H$3 -> 0 | M19: =+Precios!I17*Precios!I$3 -> 0 | ... AX19: =+Precios!AT17*Precios!AT$3 -> 0 | AY19: =+Precios!AU17*$AY$3 -> 0 | AZ19: =+Precios!AV17*Precios!AV$3 -> 0 | BA19: =+Precios!AW17*Precios!AW$3 -> 0 | BB19: =+Precios!AX17*Precios!AX$3 -> 0 | BC19: =+Precios!AY17*Precios!AY$3 -> 0 | BD19: =+Precios!AZ17*Precios!AZ$3 -> 0 | BE19: =+Precios!BA17*Precios!BA$3 -> 0 | BF19: =+Precios!BB17*Precios!BB$3 -> 0 | BG19: =+Precios!BC17*Precios!BC$3 -> 0 | BH19: =+Precios!BD17*$BH$3 -> 0 | BI19: =+Precios!BE17*Precios!BE$3 -> 0 | BJ19: =+Precios!BF17*Precios!BF$3 -> 0 | BK19: =+Precios!BG17*Precios!BG$3 -> 0 | BL19: =+Precios!BH17*Precios!BH$3 -> 0 | BM19: =+Precios!BI17*Precios!BI$3 -> 0 | BN19: =+Precios!BJ17*$BN$3 -> 0 | BO19: =+Precios!BK17*$BO$3 -> 0 | BP19: =+Precios!BL17*Precios!BL$3 -> 0
A20: =+SUM(F20:XFD20) -> 0 | C20: =+C19+B20 -> 10271 | D20: =1000000+C20-Cost!A20 -> 1010271 | E20: =+Precios!A18 -> 45996 | F20: =+Precios!B18*Precios!B$3 -> 0 | G20: =+Precios!C18*Precios!C$3 -> 0 | H20: =+Precios!D18*Precios!D$3 -> 0 | I20: =+Precios!E18*Precios!E$3 -> 0 | J20: =+Precios!F18*Precios!F$3 -> 0 | K20: =+Precios!G18*Precios!G$3 -> 0 | L20: =+Precios!H18*Precios!H$3 -> 0 | M20: =+Precios!I18*Precios!I$3 -> 0 | ... AX20: =+Precios!AT18*Precios!AT$3 -> 0 | AY20: =+Precios!AU18*$AY$3 -> 0 | AZ20: =+Precios!AV18*Precios!AV$3 -> 0 | BA20: =+Precios!AW18*Precios!AW$3 -> 0 | BB20: =+Precios!AX18*Precios!AX$3 -> 0 | BC20: =+Precios!AY18*Precios!AY$3 -> 0 | BD20: =+Precios!AZ18*Precios!AZ$3 -> 0 | BE20: =+Precios!BA18*Precios!BA$3 -> 0 | BF20: =+Precios!BB18*Precios!BB$3 -> 0 | BG20: =+Precios!BC18*Precios!BC$3 -> 0 | BH20: =+Precios!BD18*$BH$3 -> 0 | BI20: =+Precios!BE18*Precios!BE$3 -> 0 | BJ20: =+Precios!BF18*Precios!BF$3 -> 0 | BK20: =+Precios!BG18*Precios!BG$3 -> 0 | BL20: =+Precios!BH18*Precios!BH$3 -> 0 | BM20: =+Precios!BI18*Precios!BI$3 -> 0 | BN20: =+Precios!BJ18*$BN$3 -> 0 | BO20: =+Precios!BK18*$BO$3 -> 0 | BP20: =+Precios!BL18*Precios!BL$3 -> 0
A21: =+SUM(F21:XFD21) -> 0 | C21: =+C20+B21 -> 10271 | D21: =1000000+C21-Cost!A21 -> 1010271 | E21: =+Precios!A19 -> 45999 | F21: =+Precios!B19*Precios!B$3 -> 0 | G21: =+Precios!C19*Precios!C$3 -> 0 | H21: =+Precios!D19*Precios!D$3 -> 0 | I21: =+Precios!E19*Precios!E$3 -> 0 | J21: =+Precios!F19*Precios!F$3 -> 0 | K21: =+Precios!G19*Precios!G$3 -> 0 | L21: =+Precios!H19*Precios!H$3 -> 0 | M21: =+Precios!I19*Precios!I$3 -> 0 | ... AX21: =+Precios!AT19*Precios!AT$3 -> 0 | AY21: =+Precios!AU19*$AY$3 -> 0 | AZ21: =+Precios!AV19*Precios!AV$3 -> 0 | BA21: =+Precios!AW19*Precios!AW$3 -> 0 | BB21: =+Precios!AX19*Precios!AX$3 -> 0 | BC21: =+Precios!AY19*Precios!AY$3 -> 0 | BD21: =+Precios!AZ19*Precios!AZ$3 -> 0 | BE21: =+Precios!BA19*Precios!BA$3 -> 0 | BF21: =+Precios!BB19*Precios!BB$3 -> 0 | BG21: =+Precios!BC19*Precios!BC$3 -> 0 | BH21: =+Precios!BD19*$BH$3 -> 0 | BI21: =+Precios!BE19*Precios!BE$3 -> 0 | BJ21: =+Precios!BF19*Precios!BF$3 -> 0 | BK21: =+Precios!BG19*Precios!BG$3 -> 0 | BL21: =+Precios!BH19*Precios!BH$3 -> 0 | BM21: =+Precios!BI19*Precios!BI$3 -> 0 | BN21: =+Precios!BJ19*$BN$3 -> 0 | BO21: =+Precios!BK19*$BO$3 -> 0 | BP21: =+Precios!BL19*Precios!BL$3 -> 0
A22: =+SUM(F22:XFD22) -> 0 | C22: =+C21+B22 -> 10271 | D22: =1000000+C22-Cost!A22 -> 1010271 | E22: =+Precios!A20 -> 46000 | F22: =+Precios!B20*Precios!B$3 -> 0 | G22: =+Precios!C20*Precios!C$3 -> 0 | H22: =+Precios!D20*Precios!D$3 -> 0 | I22: =+Precios!E20*Precios!E$3 -> 0 | J22: =+Precios!F20*Precios!F$3 -> 0 | K22: =+Precios!G20*Precios!G$3 -> 0 | L22: =+Precios!H20*Precios!H$3 -> 0 | M22: =+Precios!I20*Precios!I$3 -> 0 | ... AX22: =+Precios!AT20*Precios!AT$3 -> 0 | AY22: =+Precios!AU20*$AY$3 -> 0 | AZ22: =+Precios!AV20*Precios!AV$3 -> 0 | BA22: =+Precios!AW20*Precios!AW$3 -> 0 | BB22: =+Precios!AX20*Precios!AX$3 -> 0 | BC22: =+Precios!AY20*Precios!AY$3 -> 0 | BD22: =+Precios!AZ20*Precios!AZ$3 -> 0 | BE22: =+Precios!BA20*Precios!BA$3 -> 0 | BF22: =+Precios!BB20*Precios!BB$3 -> 0 | BG22: =+Precios!BC20*Precios!BC$3 -> 0 | BH22: =+Precios!BD20*$BH$3 -> 0 | BI22: =+Precios!BE20*Precios!BE$3 -> 0 | BJ22: =+Precios!BF20*Precios!BF$3 -> 0 | BK22: =+Precios!BG20*Precios!BG$3 -> 0 | BL22: =+Precios!BH20*Precios!BH$3 -> 0 | BM22: =+Precios!BI20*Precios!BI$3 -> 0 | BN22: =+Precios!BJ20*$BN$3 -> 0 | BO22: =+Precios!BK20*$BO$3 -> 0 | BP22: =+Precios!BL20*Precios!BL$3 -> 0
A23: =+SUM(F23:XFD23) -> 0 | C23: =+C22+B23 -> 10271 | D23: =1000000+C23-Cost!A23 -> 1010271 | E23: =+Precios!A21 -> 46001 | F23: =+Precios!B21*Precios!B$3 -> 0 | G23: =+Precios!C21*Precios!C$3 -> 0 | H23: =+Precios!D21*Precios!D$3 -> 0 | I23: =+Precios!E21*Precios!E$3 -> 0 | J23: =+Precios!F21*Precios!F$3 -> 0 | K23: =+Precios!G21*Precios!G$3 -> 0 | L23: =+Precios!H21*Precios!H$3 -> 0 | M23: =+Precios!I21*Precios!I$3 -> 0 | ... AX23: =+Precios!AT21*Precios!AT$3 -> 0 | AY23: =+Precios!AU21*$AY$3 -> 0 | AZ23: =+Precios!AV21*Precios!AV$3 -> 0 | BA23: =+Precios!AW21*Precios!AW$3 -> 0 | BB23: =+Precios!AX21*Precios!AX$3 -> 0 | BC23: =+Precios!AY21*Precios!AY$3 -> 0 | BD23: =+Precios!AZ21*Precios!AZ$3 -> 0 | BE23: =+Precios!BA21*Precios!BA$3 -> 0 | BF23: =+Precios!BB21*Precios!BB$3 -> 0 | BG23: =+Precios!BC21*Precios!BC$3 -> 0 | BH23: =+Precios!BD21*$BH$3 -> 0 | BI23: =+Precios!BE21*Precios!BE$3 -> 0 | BJ23: =+Precios!BF21*Precios!BF$3 -> 0 | BK23: =+Precios!BG21*Precios!BG$3 -> 0 | BL23: =+Precios!BH21*Precios!BH$3 -> 0 | BM23: =+Precios!BI21*Precios!BI$3 -> 0 | BN23: =+Precios!BJ21*$BN$3 -> 0 | BO23: =+Precios!BK21*$BO$3 -> 0 | BP23: =+Precios!BL21*Precios!BL$3 -> 0
A24: =+SUM(F24:XFD24) -> 0 | C24: =+C23+B24 -> 10271 | D24: =1000000+C24-Cost!A24 -> 1010271 | E24: =+Precios!A22 -> 46002 | F24: =+Precios!B22*Precios!B$3 -> 0 | G24: =+Precios!C22*Precios!C$3 -> 0 | H24: =+Precios!D22*Precios!D$3 -> 0 | I24: =+Precios!E22*Precios!E$3 -> 0 | J24: =+Precios!F22*Precios!F$3 -> 0 | K24: =+Precios!G22*Precios!G$3 -> 0 | L24: =+Precios!H22*Precios!H$3 -> 0 | M24: =+Precios!I22*Precios!I$3 -> 0 | ... AX24: =+Precios!AT22*Precios!AT$3 -> 0 | AY24: =+Precios!AU22*$AY$3 -> 0 | AZ24: =+Precios!AV22*Precios!AV$3 -> 0 | BA24: =+Precios!AW22*Precios!AW$3 -> 0 | BB24: =+Precios!AX22*Precios!AX$3 -> 0 | BC24: =+Precios!AY22*Precios!AY$3 -> 0 | BD24: =+Precios!AZ22*Precios!AZ$3 -> 0 | BE24: =+Precios!BA22*Precios!BA$3 -> 0 | BF24: =+Precios!BB22*Precios!BB$3 -> 0 | BG24: =+Precios!BC22*Precios!BC$3 -> 0 | BH24: =+Precios!BD22*$BH$3 -> 0 | BI24: =+Precios!BE22*Precios!BE$3 -> 0 | BJ24: =+Precios!BF22*Precios!BF$3 -> 0 | BK24: =+Precios!BG22*Precios!BG$3 -> 0 | BL24: =+Precios!BH22*Precios!BH$3 -> 0 | BM24: =+Precios!BI22*Precios!BI$3 -> 0 | BN24: =+Precios!BJ22*$BN$3 -> 0 | BO24: =+Precios!BK22*$BO$3 -> 0 | BP24: =+Precios!BL22*Precios!BL$3 -> 0
A25: =+SUM(F25:XFD25) -> 0 | B25: =+TRACK!M5+TRACK!M6+TRACK!M7+TRACK!M8 -> -7096.4 | C25: =+C24+B25 -> 3174.6 | D25: =1000000+C25-Cost!A25 -> 1003174.6 | E25: =+Precios!A23 -> 46003 | F25: =+Precios!B23*Precios!B$3 -> 0 | G25: =+Precios!C23*Precios!C$3 -> 0 | H25: =+Precios!D23*Precios!D$3 -> 0 | I25: =+Precios!E23*Precios!E$3 -> 0 | J25: =+Precios!F23*Precios!F$3 -> 0 | K25: =+Precios!G23*Precios!G$3 -> 0 | L25: =+Precios!H23*Precios!H$3 -> 0 | M25: =+Precios!I23*Precios!I$3 -> 0 | ... AX25: =+Precios!AT23*Precios!AT$3 -> 0 | AY25: =+Precios!AU23*$AY$3 -> 0 | AZ25: =+Precios!AV23*Precios!AV$3 -> 0 | BA25: =+Precios!AW23*Precios!AW$3 -> 0 | BB25: =+Precios!AX23*Precios!AX$3 -> 0 | BC25: =+Precios!AY23*Precios!AY$3 -> 0 | BD25: =+Precios!AZ23*Precios!AZ$3 -> 0 | BE25: =+Precios!BA23*Precios!BA$3 -> 0 | BF25: =+Precios!BB23*Precios!BB$3 -> 0 | BG25: =+Precios!BC23*Precios!BC$3 -> 0 | BH25: =+Precios!BD23*$BH$3 -> 0 | BI25: =+Precios!BE23*Precios!BE$3 -> 0 | BJ25: =+Precios!BF23*Precios!BF$3 -> 0 | BK25: =+Precios!BG23*Precios!BG$3 -> 0 | BL25: =+Precios!BH23*Precios!BH$3 -> 0 | BM25: =+Precios!BI23*Precios!BI$3 -> 0 | BN25: =+Precios!BJ23*$BN$3 -> 0 | BO25: =+Precios!BK23*$BO$3 -> 0 | BP25: =+Precios!BL23*Precios!BL$3 -> 0
A26: =+SUM(F26:XFD26) -> 0 | B26: =+TRACK!M9+TRACK!M10 -> 14519 | C26: =+C25+B26 -> 17693.6 | D26: =1000000+C26-Cost!A26 -> 1017693.6 | E26: =+Precios!A24 -> 46006 | F26: =+Precios!B24*Precios!B$3 -> 0 | G26: =+Precios!C24*Precios!C$3 -> 0 | H26: =+Precios!D24*Precios!D$3 -> 0 | I26: =+Precios!E24*Precios!E$3 -> 0 | J26: =+Precios!F24*Precios!F$3 -> 0 | K26: =+Precios!G24*Precios!G$3 -> 0 | L26: =+Precios!H24*Precios!H$3 -> 0 | M26: =+Precios!I24*Precios!I$3 -> 0 | ... AX26: =+Precios!AT24*Precios!AT$3 -> 0 | AY26: =+Precios!AU24*$AY$3 -> 0 | AZ26: =+Precios!AV24*Precios!AV$3 -> 0 | BA26: =+Precios!AW24*Precios!AW$3 -> 0 | BB26: =+Precios!AX24*Precios!AX$3 -> 0 | BC26: =+Precios!AY24*Precios!AY$3 -> 0 | BD26: =+Precios!AZ24*Precios!AZ$3 -> 0 | BE26: =+Precios!BA24*Precios!BA$3 -> 0 | BF26: =+Precios!BB24*Precios!BB$3 -> 0 | BG26: =+Precios!BC24*Precios!BC$3 -> 0 | BH26: =+Precios!BD24*$BH$3 -> 0 | BI26: =+Precios!BE24*Precios!BE$3 -> 0 | BJ26: =+Precios!BF24*Precios!BF$3 -> 0 | BK26: =+Precios!BG24*Precios!BG$3 -> 0 | BL26: =+Precios!BH24*Precios!BH$3 -> 0 | BM26: =+Precios!BI24*Precios!BI$3 -> 0 | BN26: =+Precios!BJ24*$BN$3 -> 0 | BO26: =+Precios!BK24*$BO$3 -> 0 | BP26: =+Precios!BL24*Precios!BL$3 -> 0
A27: =+SUM(F27:XFD27) -> 0 | B27: =+TRACK!M11+TRACK!M12+TRACK!M13 -> -4386.41 | C27: =+C26+B27 -> 13307.19 | D27: =1000000+C27-Cost!A27 -> 1013307.2 | E27: =+Precios!A25 -> 46007 | F27: =+Precios!B25*Precios!B$3 -> 0 | G27: =+Precios!C25*Precios!C$3 -> 0 | H27: =+Precios!D25*Precios!D$3 -> 0 | I27: =+Precios!E25*Precios!E$3 -> 0 | J27: =+Precios!F25*Precios!F$3 -> 0 | K27: =+Precios!G25*Precios!G$3 -> 0 | L27: =+Precios!H25*Precios!H$3 -> 0 | M27: =+Precios!I25*Precios!I$3 -> 0 | ... AX27: =+Precios!AT25*Precios!AT$3 -> 0 | AY27: =+Precios!AU25*$AY$3 -> 0 | AZ27: =+Precios!AV25*Precios!AV$3 -> 0 | BA27: =+Precios!AW25*Precios!AW$3 -> 0 | BB27: =+Precios!AX25*Precios!AX$3 -> 0 | BC27: =+Precios!AY25*Precios!AY$3 -> 0 | BD27: =+Precios!AZ25*Precios!AZ$3 -> 0 | BE27: =+Precios!BA25*Precios!BA$3 -> 0 | BF27: =+Precios!BB25*Precios!BB$3 -> 0 | BG27: =+Precios!BC25*Precios!BC$3 -> 0 | BH27: =+Precios!BD25*$BH$3 -> 0 | BI27: =+Precios!BE25*Precios!BE$3 -> 0 | BJ27: =+Precios!BF25*Precios!BF$3 -> 0 | BK27: =+Precios!BG25*Precios!BG$3 -> 0 | BL27: =+Precios!BH25*Precios!BH$3 -> 0 | BM27: =+Precios!BI25*Precios!BI$3 -> 0 | BN27: =+Precios!BJ25*$BN$3 -> 0 | BO27: =+Precios!BK25*$BO$3 -> 0 | BP27: =+Precios!BL25*Precios!BL$3 -> 0
A28: =+SUM(F28:XFD28) -> 0 | B28: =+TRACK!M14+TRACK!M15 -> -7725 | C28: =+C27+B28 -> 5582.19 | D28: =1000000+C28-Cost!A28 -> 1005582.2 | E28: =+Precios!A26 -> 46008 | F28: =+Precios!B26*Precios!B$3 -> 0 | G28: =+Precios!C26*Precios!C$3 -> 0 | H28: =+Precios!D26*Precios!D$3 -> 0 | I28: =+Precios!E26*Precios!E$3 -> 0 | J28: =+Precios!F26*Precios!F$3 -> 0 | K28: =+Precios!G26*Precios!G$3 -> 0 | L28: =+Precios!H26*Precios!H$3 -> 0 | M28: =+Precios!I26*Precios!I$3 -> 0 | ... AX28: =+Precios!AT26*Precios!AT$3 -> 0 | AY28: =+Precios!AU26*$AY$3 -> 0 | AZ28: =+Precios!AV26*Precios!AV$3 -> 0 | BA28: =+Precios!AW26*Precios!AW$3 -> 0 | BB28: =+Precios!AX26*Precios!AX$3 -> 0 | BC28: =+Precios!AY26*Precios!AY$3 -> 0 | BD28: =+Precios!AZ26*Precios!AZ$3 -> 0 | BE28: =+Precios!BA26*Precios!BA$3 -> 0 | BF28: =+Precios!BB26*Precios!BB$3 -> 0 | BG28: =+Precios!BC26*Precios!BC$3 -> 0 | BH28: =+Precios!BD26*$BH$3 -> 0 | BI28: =+Precios!BE26*Precios!BE$3 -> 0 | BJ28: =+Precios!BF26*Precios!BF$3 -> 0 | BK28: =+Precios!BG26*Precios!BG$3 -> 0 | BL28: =+Precios!BH26*Precios!BH$3 -> 0 | BM28: =+Precios!BI26*Precios!BI$3 -> 0 | BN28: =+Precios!BJ26*$BN$3 -> 0 | BO28: =+Precios!BK26*$BO$3 -> 0 | BP28: =+Precios!BL26*Precios!BL$3 -> 0
A29: =+SUM(F29:XFD29) -> 0 | C29: =+C28+B29 -> 5582.19 | D29: =1000000+C29-Cost!A29 -> 1005582.2 | E29: =+Precios!A27 -> 46009 | F29: =+Precios!B27*Precios!B$3 -> 0 | G29: =+Precios!C27*Precios!C$3 -> 0 | H29: =+Precios!D27*Precios!D$3 -> 0 | I29: =+Precios!E27*Precios!E$3 -> 0 | J29: =+Precios!F27*Precios!F$3 -> 0 | K29: =+Precios!G27*Precios!G$3 -> 0 | L29: =+Precios!H27*Precios!H$3 -> 0 | M29: =+Precios!I27*Precios!I$3 -> 0 | ... AX29: =+Precios!AT27*Precios!AT$3 -> 0 | AY29: =+Precios!AU27*$AY$3 -> 0 | AZ29: =+Precios!AV27*Precios!AV$3 -> 0 | BA29: =+Precios!AW27*Precios!AW$3 -> 0 | BB29: =+Precios!AX27*Precios!AX$3 -> 0 | BC29: =+Precios!AY27*Precios!AY$3 -> 0 | BD29: =+Precios!AZ27*Precios!AZ$3 -> 0 | BE29: =+Precios!BA27*Precios!BA$3 -> 0 | BF29: =+Precios!BB27*Precios!BB$3 -> 0 | BG29: =+Precios!BC27*Precios!BC$3 -> 0 | BH29: =+Precios!BD27*$BH$3 -> 0 | BI29: =+Precios!BE27*Precios!BE$3 -> 0 | BJ29: =+Precios!BF27*Precios!BF$3 -> 0 | BK29: =+Precios!BG27*Precios!BG$3 -> 0 | BL29: =+Precios!BH27*Precios!BH$3 -> 0 | BM29: =+Precios!BI27*Precios!BI$3 -> 0 | BN29: =+Precios!BJ27*$BN$3 -> 0 | BO29: =+Precios!BK27*$BO$3 -> 0 | BP29: =+Precios!BL27*Precios!BL$3 -> 0
A30: =+SUM(F30:XFD30) -> 0 | C30: =+C29+B30 -> 5582.19 | D30: =1000000+C30-Cost!A30 -> 1005582.2 | E30: =+Precios!A28 -> 46010 | F30: =+Precios!B28*Precios!B$3 -> 0 | G30: =+Precios!C28*Precios!C$3 -> 0 | H30: =+Precios!D28*Precios!D$3 -> 0 | I30: =+Precios!E28*Precios!E$3 -> 0 | J30: =+Precios!F28*Precios!F$3 -> 0 | K30: =+Precios!G28*Precios!G$3 -> 0 | L30: =+Precios!H28*Precios!H$3 -> 0 | M30: =+Precios!I28*Precios!I$3 -> 0 | ... AX30: =+Precios!AT28*Precios!AT$3 -> 0 | AY30: =+Precios!AU28*$AY$3 -> 0 | AZ30: =+Precios!AV28*Precios!AV$3 -> 0 | BA30: =+Precios!AW28*Precios!AW$3 -> 0 | BB30: =+Precios!AX28*Precios!AX$3 -> 0 | BC30: =+Precios!AY28*Precios!AY$3 -> 0 | BD30: =+Precios!AZ28*Precios!AZ$3 -> 0 | BE30: =+Precios!BA28*Precios!BA$3 -> 0 | BF30: =+Precios!BB28*Precios!BB$3 -> 0 | BG30: =+Precios!BC28*Precios!BC$3 -> 0 | BH30: =+Precios!BD28*$BH$3 -> 0 | BI30: =+Precios!BE28*Precios!BE$3 -> 0 | BJ30: =+Precios!BF28*Precios!BF$3 -> 0 | BK30: =+Precios!BG28*Precios!BG$3 -> 0 | BL30: =+Precios!BH28*Precios!BH$3 -> 0 | BM30: =+Precios!BI28*Precios!BI$3 -> 0 | BN30: =+Precios!BJ28*$BN$3 -> 0 | BO30: =+Precios!BK28*$BO$3 -> 0 | BP30: =+Precios!BL28*Precios!BL$3 -> 0
A31: =+SUM(F31:XFD31) -> 0 | C31: =+C30+B31 -> 5582.19 | D31: =1000000+C31-Cost!A31 -> 1005582.2 | E31: =+Precios!A29 -> 46013 | F31: =+Precios!B29*Precios!B$3 -> 0 | G31: =+Precios!C29*Precios!C$3 -> 0 | H31: =+Precios!D29*Precios!D$3 -> 0 | I31: =+Precios!E29*Precios!E$3 -> 0 | J31: =+Precios!F29*Precios!F$3 -> 0 | K31: =+Precios!G29*Precios!G$3 -> 0 | L31: =+Precios!H29*Precios!H$3 -> 0 | M31: =+Precios!I29*Precios!I$3 -> 0 | ... AX31: =+Precios!AT29*Precios!AT$3 -> 0 | AY31: =+Precios!AU29*$AY$3 -> 0 | AZ31: =+Precios!AV29*Precios!AV$3 -> 0 | BA31: =+Precios!AW29*Precios!AW$3 -> 0 | BB31: =+Precios!AX29*Precios!AX$3 -> 0 | BC31: =+Precios!AY29*Precios!AY$3 -> 0 | BD31: =+Precios!AZ29*Precios!AZ$3 -> 0 | BE31: =+Precios!BA29*Precios!BA$3 -> 0 | BF31: =+Precios!BB29*Precios!BB$3 -> 0 | BG31: =+Precios!BC29*Precios!BC$3 -> 0 | BH31: =+Precios!BD29*$BH$3 -> 0 | BI31: =+Precios!BE29*Precios!BE$3 -> 0 | BJ31: =+Precios!BF29*Precios!BF$3 -> 0 | BK31: =+Precios!BG29*Precios!BG$3 -> 0 | BL31: =+Precios!BH29*Precios!BH$3 -> 0 | BM31: =+Precios!BI29*Precios!BI$3 -> 0 | BN31: =+Precios!BJ29*$BN$3 -> 0 | BO31: =+Precios!BK29*$BO$3 -> 0 | BP31: =+Precios!BL29*Precios!BL$3 -> 0
